Workbook

Sheet Anotações
B2: Deal com A Gazeta
B3: Conselho Consultivo | C3: Quais pessoas (Dudu, Omar, Simone?, Patrick?, Marcus Buaiz?, Angelo?, Fere?, Ulisses?, ), o que esperamos, qual remuneracao (% baixo ou pagar(quanto?)) , área (marketing, tech), qual frequencia (mensal/trimestral) etc
B4: Partnership de ações (tentar definir)
B5: Ações internas (eventos colaborador SG&A)
B6: Quais ferramentas precisamos desenvolver
B7: Produtos&Serviços gerais
B9: Fazer painel de iniciativas e Projetos | C9: https://docs.google.com/document/d/1Bd9xdiEdrcTYg6vKJGJvyknFmdaPA3eUgVTLtH2r8Kg/edit?tab=t.0
B11: Fechar OKR Trimestre e KPIs de acompanhamento
B13: Participacoes em outras empresas e ventures
B14: Hugz
B15: Marketing de Rochas
B16: Deal com Maely
B17: Capex outras iniciativas
B18: TurbOOH | C18: CAPEX infinito, Payback esperado 4 meses,
B20: Comites:
B21: Produto*
B22: Gente e Gestao
B23: Financeiro
B24: Vendas
B25: Content
B27: Premiações
B28: Final do Ano | C28: 30% Bonus | D28: 70% Dividendo | E28: BATER ISSO
B29: Spot Bonus | C29: Figurativo para os destaques
B30: Mensal | C30: Caju turbinado | D30: cafe da manha | E30: almoco equipe etc
B32: Distribuição = Caixa inicial + Geração de Caixa periodo - SALDO MINIMO CAIXA
B33: Poítica de 1x caixa para 2026 | D33: Visão de DRE
B36: Caixa | C36: 1700000 | I36: Mudanças
B37: Cap Table | C37: 0.7 | D37: Dividendo | E37: Salários | F37: Bonus | I37: Bônus no inicio do ano atrelado a geração de caixa
B38: Rodrigo | C38: 0.386 | D38: =C38*$C$37*$C$36 -> 459340 | E38: =25000*12 -> 300000 | F38: =E48 -> 38250 | G38: =E38+D38+F38 -> 797590 | I38: Heads - 30%
B39: Andre Musso | C39: 0.28 | D39: =C39*$C$37*$C$36 -> 333200 | E39: =25000*12 -> 300000 | F39: =E47 -> 38250 | G39: =E39+D39+F39 -> 671450 | I39: Especialistas (15 -20 pessoas) - 30%
B40: Victor Peixoto | C40: 0.284 | D40: =C40*$C$37*$C$36 -> 337960 | E40: =30000*12 -> 360000 | F40: =E44 -> 51000 | G40: =E40+D40+F40 -> 748960 | I40: Executivos - 40%
B41: Pool | C41: 0.05 | D41: =C41*$C$37*$C$36 -> 59500
I42: Condições
C43: Time | D43: 0.3 | E43: =C36*D43 -> 510000 | I43: <10k - Pagamento em 3x
B44: Victor | C44: CEO | D44: 0.1 | E44: =D44*$D$43*$C$36 -> 51000 | I44: 10k - Pagamento em 6x
B45: Rafael | C45: COO | D45: 0.075 | E45: =D45*$D$43*$C$36 -> 38250 | I45: Se sair da companhia, perde o bônus a receber
B46: João | C46: CRO | D46: 0.075 | E46: =D46*$D$43*$C$36 -> 38250
B47: André | C47: CIO | D47: 0.075 | E47: =D47*$D$43*$C$36 -> 38250 | I47: Spot bonus
B48: Rodrigo | C48: CNBO | D48: 0.075 | E48: =D48*$D$43*$C$36 -> 38250 | I48: Será uma premiação individual reconhecida pelos fundadores
B49: Lucas, Roberto, Glauber, Ismael, Padrão, Breno, Pedro, Karol | C49: Heads | D49: 0.3 | E49: =D49*$D$43*$C$36 -> 153000 | F49: =E49/10 -> 15300 | G49: Todos podem ganharar? Qual critério? | I49: Premios surpresas
B50: Pool de 20 pessoas? | C50: Especialistas | D50: 0.3 | E50: =D50*$D$43*$C$36 -> 153000 | F50: =E50/20 -> 7650 | G50: Vão ser 20? 15? O que queremos? | I50: Indicação ao partnership
D51: =SUM(D44:D50) -> 1 | E51: =sum(E44:E50) -> 510000 | I51: Precisa ter um ano de casa

Sheet Overview
B2: Trimestre | C2: 1 Trimestre | F2: 2 Trimestre | I2: 3 Trimestre | L2: 4 Trimestre | R2: 1 Trimestre
C3: Janeiro | D3: Feveiro | E3: Março | F3: Abril | G3: Maio | H3: Junho | I3: Julho | J3: Agosto | K3: Setembro | L3: Outubro | M3: Novembro | N3: Dezembro | O3: Total | R3: Inadimpência | S3: 0.06
B4: (+) MRR Ativo | C4: =Revenue!D5 -> 1156850 | D4: =Revenue!E5 -> 1267733.5 | E4: =Revenue!F5 -> 1368637.5 | F4: =Revenue!G5 -> 1485460.1 | G4: =Revenue!H5 -> 1591768.7 | H4: =Revenue!I5 -> 1688509.5 | I4: =Revenue!J5 -> 1806543.7 | J4: =Revenue!K5 -> 1913954.7 | ... N4: =Revenue!O5 -> 2337387.9 | O4: =sum(C4:N4) -> 20998078
B5: (+) Receita Pontual | C5: =Revenue!D37 -> 240000 | D5: =Revenue!E37 -> 280000 | E5: =Revenue!F37 -> 270000 | F5: =Revenue!G37 -> 288333.33 | G5: =Revenue!H37 -> 306666.67 | H5: =Revenue!I37 -> 325000 | I5: =Revenue!J37 -> 343333.33 | J5: =Revenue!K37 -> 361666.67 | ... N5: =Revenue!O37 -> 435000 | O5: =sum(C5:N5) -> 4045000 | R5: 2 Trimestre
B6: (+) Outras Receitas | C6: ='Outras Receitas'!C15 -> 20766.667 | D6: ='Outras Receitas'!D15 -> 60408 | E6: ='Outras Receitas'!E15 -> 25626.667 | F6: ='Outras Receitas'!F15 -> 43076.667 | G6: ='Outras Receitas'!G15 -> 90096.667 | H6: ='Outras Receitas'!H15 -> 48783.333 | I6: ='Outras Receitas'!I15 -> 85573.333 | J6: ='Outras Receitas'!J15 -> 135713.33 | ... N6: ='Outras Receitas'!N15 -> 137006.67 | O6: =sum(C6:N6) -> 1040111.3 | R6: Inadimpência | S6: 0.06
B7: (=) Receita Total Faturavel | C7: =C4+C5+C6 -> 1417616.7 | D7: =D4+D5+D6 -> 1608141.5 | E7: =E4+E5+E6 -> 1664264.2 | F7: =F4+F5+F6 -> 1816870.1 | G7: =G4+G5+G6 -> 1988532 | H7: =H4+H5+H6 -> 2062292.9 | I7: =I4+I5+I6 -> 2235450.3 | J7: =J4+J5+J6 -> 2411334.7 | ... O7: =O4+O5+O6 -> 26083189
B8: (-) Inadimplência | C8: =C7*$S$3 -> 85057 | D8: =D7*$S$3 -> 96488.49 | E8: =E7*$S$3 -> 99855.849 | F8: =F7*$S$6 -> 109012.21 | G8: =G7*$S$6 -> 119311.92 | H8: =H7*$S$6 -> 123737.57 | I8: =I7*$S$9 -> 134127.02 | J8: =J7*$S$9 -> 144680.08 | K8: =K7*$S$9 -> 148244.73 | L8: =L7*$S$12 -> 159959.15 | M8: =M7*$S$12 -> 169953.67 | N8: =N7*$S$12 -> 174563.67 | O8: =sum(C8:N8) -> 1564991.4 | P8: =O8/$O$7 -> 0.06 | R8: 3 Trimestre
B9: (-) Impostos Sob Receita | C9: ='Tributário'!F11+'Tributário'!F12+'Tributário'!F13 -> 133132.3 | D9: ='Tributário'!G11+'Tributário'!G12+'Tributário'!G13 -> 150146.17 | E9: ='Tributário'!H11+'Tributário'!H12+'Tributário'!H13 -> 155157.92 | F9: ='Tributário'!I11+'Tributário'!I12+'Tributário'!I13 -> 170420.41 | G9: ='Tributário'!J11+'Tributário'!J12+'Tributário'!J13 -> 185749.82 | H9: ='Tributário'!K11+'Tributário'!K12+'Tributário'!K13 -> 192336.66 | I9: ='Tributário'!L11+'Tributário'!L12+'Tributário'!L13 -> 207799.63 | J9: ='Tributário'!M11+'Tributário'!M12+'Tributário'!M13 -> 223506.1 | ... N9: ='Tributário'!Q11+'Tributário'!Q12+'Tributário'!Q13 -> 267982.85 | O9: =sum(C9:N9) -> 2422411.4 | P9: =O9/$O$7 -> 0.092872516 | R9: Inadimpência | S9: 0.06
B10: (=) Receita Líquida | C10: =C7-C8-C9 -> 1199427.4 | D10: =D7-D8-D9 -> 1361506.8 | E10: =E7-E8-E9 -> 1409250.4 | F10: =F7-F8-F9 -> 1537437.5 | G10: =G7-G8-G9 -> 1683470.3 | H10: =H7-H8-H9 -> 1746218.6 | I10: =I7-I8-I9 -> 1893523.7 | J10: =J7-J8-J9 -> 2043148.5 | ... N10: =N7-N8-N9 -> 2466848 | O10: =sum(C10:N10) -> 22095787 | Q10: =O10/$O$7 -> 0.84712748
B11: (-) CSV - Salários | C11: =CSV!D4 -> 345754.4 | D11: =CSV!E4 -> 380706.3 | E11: =CSV!F4 -> 399437.54 | F11: =CSV!G4 -> 465597.96 | G11: =CSV!H4 -> 488400.64 | H11: =CSV!I4 -> 495996.08 | I11: =CSV!J4 -> 557632.94 | J11: =CSV!K4 -> 583914.17 | ... N11: =CSV!O4 -> 687435.48 | O11: =sum(C11:N11) -> 6314099.1 | P11: =O11/$O$7 -> 0.24207542 | R11: 4 Trimestre
B12: (-) CSV - Benefício | C12: =(CSV!D7*400) -> 29200 | D12: =(CSV!E7*400) -> 32000 | E12: =(CSV!F7*400) -> 33200 | F12: =(CSV!G7*400) -> 37200 | G12: =(CSV!H7*400) -> 38800 | H12: =(CSV!I7*400) -> 39200 | I12: =(CSV!J7*400) -> 41600 | J12: =(CSV!K7*400) -> 43200 | ... N12: =(CSV!O7*400) -> 48800 | O12: =sum(C12:N12) -> 481200 | P12: =O12/$O$7 -> 0.018448664 | R12: Inadimpência | S12: 0.06
B13: (-) CSV - Stack Tecnologia | C13: ='SG&A'!C42 -> 41540 | D13: ='SG&A'!D42 -> 41932 | E13: ='SG&A'!E42 -> 42177 | F13: ='SG&A'!F42 -> 44635 | G13: ='SG&A'!G42 -> 44831 | H13: ='SG&A'!H42 -> 44929 | I13: ='SG&A'!I42 -> 62293 | J13: ='SG&A'!J42 -> 47538 | ... N13: ='SG&A'!N42 -> 49441 | O13: =sum(C13:N13) -> 565344 | P13: =O13/$O$7 -> 0.02167465
B14: (=) Margem Bruta | C14: =C10-C11-C12-C13 -> 782932.97 | D14: =D10-D11-D12-D13 -> 906868.54 | E14: =E10-E11-E12-E13 -> 934435.85 | F14: =F10-F11-F12-F13 -> 990004.53 | G14: =G10-G11-G12-G13 -> 1111438.6 | H14: =H10-H11-H12-H13 -> 1166093.5 | I14: =I10-I11-I12-I13 -> 1231997.7 | J14: =J10-J11-J12-J13 -> 1368496.4 | ... N14: =N10-N11-N12-N13 -> 1681171.6 | O14: =sum(C14:N14) -> 14735144 | Q14: =O14/$O$7 -> 0.56492875
B15: (-) CAC | C15: =CAC!C6 -> 262495.71 | D15: =CAC!D6 -> 285895.71 | E15: =CAC!E6 -> 311895.71 | F15: =CAC!F6 -> 337573.77 | G15: =CAC!G6 -> 422573.77 | H15: =CAC!H6 -> 362573.77 | I15: =CAC!I6 -> 453925.18 | J15: =CAC!J6 -> 371925.18 | ... N15: =CAC!N6 -> 428776.58 | O15: =sum(C15:N15) -> 4449113.7 | P15: =O15/$O$7 -> 0.17057399
B16: (-) SG&A | C16: ='SG&A'!C6-C12-C13 -> 227706 | D16: ='SG&A'!D6-D12-D13 -> 218106 | E16: ='SG&A'!E6-E12-E13 -> 218906 | F16: ='SG&A'!F6-F12-F13 -> 210206 | G16: ='SG&A'!G6-G12-G13 -> 211206 | H16: ='SG&A'!H6-H12-H13 -> 215606 | I16: ='SG&A'!I6-I12-I13 -> 213606 | J16: ='SG&A'!J6-J12-J13 -> 214006 | ... N16: ='SG&A'!N6-N12-N13 -> 265606 | O16: =sum(C16:N16) -> 2688672 | P16: =O16/$O$7 -> 0.10308065
B17: (-) Bônus | C17: 54000 | D17: 23000 | E17: 23000
B18: (=) EBITDA | C18: =C14-C15-C16-C17 -> 238731.26 | D18: =D14-D15-D16-D17 -> 379866.83 | E18: =E14-E15-E16-E17 -> 380634.14 | F18: =F14-F15-F16-F17 -> 442224.76 | G18: =G14-G15-G16-G17 -> 477658.87 | H18: =H14-H15-H16-H17 -> 587913.76 | I18: =I14-I15-I16-I17 -> 564466.57 | J18: =J14-J15-J16-J17 -> 782565.2 | ... O18: =O14-O15-O16-O17 -> 7597357.9 | Q18: =O18/$O$7 -> 0.29127411
B19: (-) IR + CSLL + ICMS + DIFALS | C19: ='Tributário'!F14 -> 99528.628 | D19: ='Tributário'!G14 -> 136974.72 | E19: ='Tributário'!H14 -> 137235.61 | F19: ='Tributário'!I14 -> 150356.42 | G19: ='Tributário'!J14 -> 162404.02 | H19: ='Tributário'!K14 -> 199890.68 | I19: ='Tributário'!L14 -> 191918.63 | J19: ='Tributário'!M14 -> 266072.17 | ... N19: ='Tributário'!Q14 -> 335508.25 | O19: =sum(C19:N19) -> 2583101.7 | P19: =O19/$O$7 -> 0.099033199
B20: (-) CAPEX | C20: ='CAPEX e Giro'!D5 -> 35000 | D20: ='CAPEX e Giro'!E5 -> 35000 | E20: ='CAPEX e Giro'!F5 -> 35000 | F20: ='CAPEX e Giro'!G5 -> 35000 | G20: ='CAPEX e Giro'!H5 -> 35000 | H20: ='CAPEX e Giro'!I5 -> 35000 | I20: ='CAPEX e Giro'!J5 -> 35000 | J20: ='CAPEX e Giro'!K5 -> 35000 | ... N20: ='CAPEX e Giro'!O5 -> 35000 | O20: =sum(C20:N20) -> 420000 | P20: =O20/$O$7 -> 0.016102325
B21: (=) Geração de Caixa | C21: =C18-C19-C20 -> 104202.63 | D21: =D18-D19-D20 -> 207892.11 | E21: =E18-E19-E20 -> 208398.53 | F21: =F18-F19-F20 -> 256868.34 | G21: =G18-G19-G20 -> 280254.86 | H21: =H18-H19-H20 -> 353023.08 | I21: =I18-I19-I20 -> 337547.94 | J21: =J18-J19-J20 -> 481493.03 | ... O21: =O18-O19-O20 -> 4594256.2 | P21: =O21/$O$7 -> 0.17613859
B22: (%) Margem Geração | C22: =C21/C7 -> 0.073505506 | D22: =D21/D7 -> 0.12927476 | E22: =E21/E7 -> 0.12521962 | F22: =F21/F7 -> 0.14137958 | G22: =G21/G7 -> 0.14093555 | H22: =H21/H7 -> 0.1711799 | I22: =I21/I7 -> 0.15099773 | J22: =J21/J7 -> 0.19967905 | ... N22: =N21/N7 -> 0.21182439
B24: Métricas Gerais
B25: Receita Total | C25: =C7-C8 -> 1332559.7 | D25: =D7-D8 -> 1511653 | E25: =E7-E8 -> 1564408.3 | F25: =F7-F8 -> 1707857.9 | G25: =G7-G8 -> 1869220.1 | H25: =H7-H8 -> 1938555.3 | I25: =I7-I8 -> 2101323.3 | J25: =J7-J8 -> 2266654.6 | ... N25: =N7-N8 -> 2734830.9
B26: Despesa Total | C26: =C9+C11+C15+C16+C19+C20+C12+C13+C17 -> 1228357 | D26: =D9+D11+D15+D16+D19+D20+D12+D13+D17 -> 1303760.9 | E26: =E9+E11+E15+E16+E19+E20+E12+E13+E17 -> 1356009.8 | F26: =F9+F11+F15+F16+F19+F20+F12+F13+F17 -> 1450989.6 | G26: =G9+G11+G15+G16+G19+G20+G12+G13+G17 -> 1588965.3 | H26: =H9+H11+H15+H16+H19+H20+H12+H13+H17 -> 1585532.2 | I26: =I9+I11+I15+I16+I19+I20+I12+I13+I17 -> 1763775.4 | J26: =J9+J11+J15+J16+J19+J20+J12+J13+J17 -> 1785161.6 | ... N26: =N9+N11+N15+N16+N19+N20+N12+N13+N17 -> 2118550.2
B27: Vendas MRR | C27: =CAC!Q7 -> 215000 | D27: =CAC!R7 -> 215000 | E27: =CAC!S7 -> 215000 | F27: =CAC!T7 -> 240000 | G27: =CAC!U7 -> 240000 | H27: =CAC!V7 -> 240000 | I27: =CAC!W7 -> 270000 | J27: =CAC!X7 -> 270000 | ... N27: =CAC!AB7 -> 300000
B28: Vendas Pontual | C28: =CAC!Q38 -> 270000 | D28: =CAC!R38 -> 270000 | E28: =CAC!S38 -> 270000 | F28: =CAC!T38 -> 325000 | G28: =CAC!U38 -> 325000 | H28: =CAC!V38 -> 325000 | I28: =CAC!W38 -> 380000 | J28: =CAC!X38 -> 380000 | ... N28: =CAC!AB38 -> 435000
B29: Numero de Colaboradores | C29: =C42 -> 109 | D29: =D42 -> 117 | E29: =E42 -> 122 | F29: =F42 -> 134 | G29: =G42 -> 138 | H29: =H42 -> 140 | I29: =I42 -> 146 | J29: =J42 -> 151 | ... N29: =N42 -> 168
B30: Receita Cabeça | C30: =C7/C29 -> 13005.657 | D30: =D7/D29 -> 13744.799 | E30: =E7/E29 -> 13641.509 | F30: =F7/F29 -> 13558.732 | G30: =G7/G29 -> 14409.652 | H30: =H7/H29 -> 14730.663 | I30: =I7/I29 -> 15311.304 | J30: =J7/J29 -> 15969.104 | ... N30: =N7/N29 -> 17317.825 | O30: =N30/C30-1 -> 0.33156088
B31: MRR Cabeça | C31: =C4/C29 -> 10613.303 | D31: =D4/D29 -> 10835.329 | E31: =E4/E29 -> 11218.34 | F31: =F4/F29 -> 11085.523 | G31: =G4/G29 -> 11534.556 | H31: =H4/H29 -> 12060.782 | I31: =I4/I29 -> 12373.587 | J31: =J4/J29 -> 12675.197 | ... N31: =N4/N29 -> 13913.023
B32: Numero de Clientes | C32: =C33/1.38 -> 300.66977 | D32: =D33/1.38 -> 330.2517 | E32: =E33/1.38 -> 352.00541 | F32: =F33/1.38 -> 377.78291 | G32: =G33/1.38 -> 402.43492 | H32: =H33/1.38 -> 423.7875 | I32: =I33/1.38 -> 449.22341 | J32: =J33/1.38 -> 474.6896 | K32: =K33/1.37 -> 500.42409 | L32: =L33/1.4 -> 515.46212 | M32: =M33/1.4 -> 541.19276 | N32: =N33/1.4 -> 563.56566
B33: Numero de Contratos | C33: =CSV!C12+CSV!C85+CSV!C141+CSV!C202+CSV!C225+CAC!Q42+CAC!Q47+CAC!Q52+CAC!Q57+CAC!Q62+CAC!Q67 -> 414.92429 | D33: =CSV!D12+CSV!D85+CSV!D141+CSV!D202+CSV!D225+CAC!R42+CAC!R47+CAC!R52+CAC!R57+CAC!R62+CAC!R67 -> 455.74735 | E33: =CSV!E12+CSV!E85+CSV!E141+CSV!E202+CSV!E225+CAC!S42+CAC!S47+CAC!S52+CAC!S57+CAC!S62+CAC!S67 -> 485.76747 | F33: =CSV!F12+CSV!F85+CSV!F141+CSV!F202+CSV!F225+CAC!T42+CAC!T47+CAC!T52+CAC!T57+CAC!T62+CAC!T67 -> 521.34042 | G33: =CSV!G12+CSV!G85+CSV!G141+CSV!G202+CSV!G225+CAC!U42+CAC!U47+CAC!U52+CAC!U57+CAC!U62+CAC!U67 -> 555.36019 | H33: =CSV!H12+CSV!H85+CSV!H141+CSV!H202+CSV!H225+CAC!V42+CAC!V47+CAC!V52+CAC!V57+CAC!V62+CAC!V67 -> 584.82675 | I33: =CSV!I12+CSV!I85+CSV!I141+CSV!I202+CSV!I225+CAC!W42+CAC!W47+CAC!W52+CAC!W57+CAC!W62+CAC!W67 -> 619.9283 | J33: =CSV!J12+CSV!J85+CSV!J141+CSV!J202+CSV!J225+CAC!X42+CAC!X47+CAC!X52+CAC!X57+CAC!X62+CAC!X67 -> 655.07165 | ... N33: =CSV!N12+CSV!N85+CSV!N141+CSV!N202+CSV!N225+CAC!AB42+CAC!AB47+CAC!AB52+CAC!AB57+CAC!AB62+CAC!AB67 -> 788.99192
B34: Ticket Medio Cliente | C34: =C7/C32 -> 4714.8626 | D34: =D7/D32 -> 4869.442 | E34: =E7/E32 -> 4727.9504 | F34: =F7/F32 -> 4809.2967 | G34: =G7/G32 -> 4941.2512 | H34: =H7/H32 -> 4866.3372 | I34: =I7/I32 -> 4976.2552 | J34: =J7/J32 -> 5079.8137 | ... N34: =N7/N32 -> 5162.4766
B35: Ticket Medio Contratos | C35: =C7/C33 -> 3416.5671 | D35: =D7/D33 -> 3528.5811 | E35: =E7/E33 -> 3426.051 | F35: =F7/F33 -> 3484.9976 | G35: =G7/G33 -> 3580.6168 | H35: =H7/H33 -> 3526.3313 | I35: =I7/I33 -> 3605.9821 | J35: =J7/J33 -> 3681.0244 | ... N35: =N7/N33 -> 3687.4833
B36: Churn Mês | C36: =Revenue!D32 -> 104116.5 | D36: =Revenue!E32 -> 114096.01 | E36: =Revenue!F32 -> 123177.37 | F36: =Revenue!G32 -> 133691.41 | G36: =Revenue!H32 -> 143259.18 | H36: =Revenue!I32 -> 151965.86 | I36: =Revenue!J32 -> 162588.93 | J36: =Revenue!K32 -> 172255.93 | ... N36: =Revenue!O32 -> 210364.91
B37: Aliquota Imposto Efetiva | C37: =(C19+C9)/C7 -> 0.16412118 | D37: =(D19+D9)/D7 -> 0.17854206 | E37: =(E19+E9)/E7 -> 0.17568937 | F37: =(F19+F9)/F7 -> 0.17655463 | G37: =(G19+G9)/G7 -> 0.17508083 | H37: =(H19+H9)/H7 -> 0.19018993 | I37: =(I19+I9)/I7 -> 0.17880883 | J37: =(J19+J9)/J7 -> 0.20303207 | ... O37: =(O19+O9)/O7 -> 0.19190571
B38: Geracao de caixa | C38: =C21 -> 104202.63 | D38: =D21 -> 207892.11 | E38: =E21 -> 208398.53 | F38: =F21 -> 256868.34 | G38: =G21 -> 280254.86 | H38: =H21 -> 353023.08 | I38: =I21 -> 337547.94 | J38: =J21 -> 481493.03 | ... N38: =N21 -> 616280.72
B39: Margem de geração | C39: =C22 -> 0.073505506 | D39: =D22 -> 0.12927476 | E39: =E22 -> 0.12521962 | F39: =F22 -> 0.14137958 | G39: =G22 -> 0.14093555 | H39: =H22 -> 0.1711799 | I39: =I22 -> 0.15099773 | J39: =J22 -> 0.19967905 | ... N39: =N22 -> 0.21182439 | O39: =P21 -> 0.17613859
B40: Saldo de Caixa | C40: =535000+C38 -> 639202.63 | D40: =C40+D38 -> 847094.74 | E40: =D40+E38 -> 1055493.3 | F40: =E40+F38 -> 1312361.6 | G40: =F40+G38 -> 1592616.5 | H40: =G40+H38 -> 1945639.5 | I40: =H40+I38 -> 2283187.5 | J40: =I40+J38 -> 2764680.5 | K40: =J40+K38 -> 3260111.3 | ... N40: =M40+N38 -> 5029256.2
B42: Numero de Colaboradores | C42: =CSV!D7+count('SG&A'!C20:C22)+count('SG&A'!C28:C37)+count(CAC!C22:C38)+count(CAC!C44:C59)+count(CAC!C66:C71)+count(CAC!C77:C86) -> 109 | D42: =CSV!E7+count('SG&A'!D20:D22)+count('SG&A'!D28:D37)+count(CAC!D22:D38)+count(CAC!D44:D59)+count(CAC!D66:D71)+count(CAC!D77:D86) -> 117 | E42: =CSV!F7+count('SG&A'!E20:E22)+count('SG&A'!E28:E37)+count(CAC!E22:E38)+count(CAC!E44:E59)+count(CAC!E66:E71)+count(CAC!E77:E86) -> 122 | F42: =CSV!G7+count('SG&A'!F20:F22)+count('SG&A'!F28:F37)+count(CAC!F22:F38)+count(CAC!F44:F59)+count(CAC!F66:F71)+count(CAC!F77:F86) -> 134 | G42: =CSV!H7+count('SG&A'!G20:G22)+count('SG&A'!G28:G37)+count(CAC!G22:G38)+count(CAC!G44:G59)+count(CAC!G66:G71)+count(CAC!G77:G86) -> 138 | H42: =CSV!I7+count('SG&A'!H20:H22)+count('SG&A'!H28:H37)+count(CAC!H22:H38)+count(CAC!H44:H59)+count(CAC!H66:H71)+count(CAC!H77:H86) -> 140 | I42: =CSV!J7+count('SG&A'!I20:I22)+count('SG&A'!I28:I37)+count(CAC!I22:I38)+count(CAC!I44:I59)+count(CAC!I66:I71)+count(CAC!I77:I86) -> 146 | J42: =CSV!K7+count('SG&A'!J20:J22)+count('SG&A'!J28:J37)+count(CAC!J22:J38)+count(CAC!J44:J59)+count(CAC!J66:J71)+count(CAC!J77:J86) -> 151 | ... N42: =CSV!O7+count('SG&A'!N20:N22)+count('SG&A'!N28:N37)+count(CAC!N22:N38)+count(CAC!N44:N59)+count(CAC!N66:N71)+count(CAC!N77:N86) -> 168
B43: Pessoas em CSV | C43: =CSV!D7 -> 73 | D43: =CSV!E7 -> 80 | E43: =CSV!F7 -> 83 | F43: =CSV!G7 -> 93 | G43: =CSV!H7 -> 97 | H43: =CSV!I7 -> 98 | I43: =CSV!J7 -> 104 | J43: =CSV!K7 -> 108 | ... N43: =CSV!O7 -> 122
B44: Pessoas em CAC | C44: =CAC!C5 -> 24 | D44: =CAC!D5 -> 25 | E44: =CAC!E5 -> 27 | F44: =CAC!F5 -> 30 | G44: =CAC!G5 -> 30 | H44: =CAC!H5 -> 30 | I44: =CAC!I5 -> 30 | J44: =CAC!J5 -> 31 | ... N44: =CAC!N5 -> 34
B45: Pessoas em SGEA | C45: ='SG&A'!C5 -> 12 | D45: ='SG&A'!D5 -> 12 | E45: ='SG&A'!E5 -> 12 | F45: ='SG&A'!F5 -> 11 | G45: ='SG&A'!G5 -> 11 | H45: ='SG&A'!H5 -> 12 | I45: ='SG&A'!I5 -> 12 | J45: ='SG&A'!J5 -> 12 | ... N45: ='SG&A'!N5 -> 12
B47: Despesa Total | C47: =C26 -> 1228357 | D47: =D26 -> 1303760.9 | E47: =E26 -> 1356009.8 | F47: =F26 -> 1450989.6 | G47: =G26 -> 1588965.3 | H47: =H26 -> 1585532.2 | I47: =I26 -> 1763775.4 | J47: =J26 -> 1785161.6 | ... N47: =N26 -> 2118550.2
B48: Saldo de Caixa | C48: =C40 -> 639202.63 | D48: =C48+D38 -> 847094.74 | E48: =D48+E38 -> 1055493.3 | F48: =E48+F38 -> 1312361.6 | G48: =F48+G38 -> 1592616.5 | H48: =G48+H38 -> 1945639.5 | I48: =H48+I38 -> 2283187.5 | J48: =I48+J38 -> 2764680.5 | K48: =J48+K38 -> 3260111.3 | ... N48: =M48+N38 -> 5029256.2
B49: Delta 1x Caixa | C49: =C48-C47 -> -589154.41 | D49: =D48-D47 -> -456666.16 | E49: =E48-E47 -> -300516.5 | F49: =F48-F47 -> -138627.95 | G49: =G48-G47 -> 3651.2087 | H49: =H48-H47 -> 360107.34 | I49: =I48-I47 -> 519412.11 | J49: =J48-J47 -> 979518.89 | ... N49: =N48-N47 -> 2910706
B50: Delta 1,5x Caixa | C50: =C48-(C47*1.5) -> -1203332.9 | D50: =D48-(D47*1.5) -> -1108546.6 | E50: =E48-(E47*1.5) -> -978521.39 | F50: =F48-(F47*1.5) -> -864122.74 | G50: =G48-(G47*1.5) -> -790831.42 | H50: =H48-(H47*1.5) -> -432658.76 | I50: =I48-(I47*1.5) -> -362475.58 | J50: =J48-(J47*1.5) -> 86938.082 | ... N50: =N48-(N47*1.5) -> 1851431
B51: Delta 2x Caixa | C51: =C48-(C47*2) -> -1817511.4 | D51: =D48-(D47*2) -> -1760427.1 | E51: =E48-(E47*2) -> -1656526.3 | F51: =F48-(F47*2) -> -1589617.5 | G51: =G48-(G47*2) -> -1585314 | H51: =H48-(H47*2) -> -1225424.9 | I51: =I48-(I47*2) -> -1244363.3 | J51: =J48-(J47*2) -> -805642.73 | ... N51: =N48-(N47*2) -> 792155.89
B52: Delta 3x Caixa | C52: =C48-(C47*3) -> -3045868.5 | D52: =D48-(D47*3) -> -3064188 | E52: =E48-(E47*3) -> -3012536 | F52: =F48-(F47*3) -> -3040607.1 | G52: =G48-(G47*3) -> -3174279.3 | H52: =H48-(H47*3) -> -2810957.1 | I52: =I48-(I47*3) -> -3008138.6 | J52: =J48-(J47*3) -> -2590804.3 | ... N52: =N48-(N47*3) -> -1326394.3
B53: x Caixa | C53: =C48/C47 -> 0.52037202 | D53: =D48/D47 -> 0.64973166 | E53: =E48/E47 -> 0.77838176 | F53: =F48/F47 -> 0.90445972 | G53: =G48/G47 -> 1.0022979 | H53: =H48/H47 -> 1.2271208 | I53: =I48/I47 -> 1.2944888 | J53: =J48/J47 -> 1.5487004 | ... N53: =N48/N47 -> 2.3739142
B55: Turnover máximo (25%): 38 desligamentos no ano

Sheet SG&A
B2: CSV
B3: Trimestre | C3: 1 Trimestre | F3: 2 Trimestre | I3: 3 Trimestre | L3: 4 Trimestre
B4: Mês | C4: Janeiro | D4: Feveiro | E4: Março | F4: Abril | G4: Maio | H4: Junho | I4: Julho | J4: Agosto | K4: Setembro | L4: Outubro | M4: Novembro | N4: Dezembro
B5: Pessoas Totais Commerce (CSV) | C5: =count(C20:C22)+count(C28:C37) -> 12 | D5: =count(D20:D22)+count(D28:D37) -> 12 | E5: =count(E20:E22)+count(E28:E37) -> 12 | F5: =count(F20:F22)+count(F28:F37) -> 11 | G5: =count(G20:G22)+count(G28:G37) -> 11 | H5: =count(H20:H22)+count(H28:H37) -> 12 | I5: =count(I20:I22)+count(I28:I37) -> 12 | J5: =count(J20:J22)+count(J28:J37) -> 12 | ... N5: =count(N20:N22)+count(N28:N37) -> 12
B6: (=) SG&A | C6: =SUM(C7:C14) -> 298446 | D6: =SUM(D7:D14) -> 292038 | E6: =SUM(E7:E14) -> 294283 | F6: =SUM(F7:F14) -> 292041 | G6: =SUM(G7:G14) -> 294837 | H6: =SUM(H7:H14) -> 299735 | I6: =SUM(I7:I14) -> 317499 | J6: =SUM(J7:J14) -> 304744 | ... N6: =SUM(N7:N14) -> 363847
B7: (-) UZK | C7: =C19 -> 80000 | D7: =D19 -> 80000 | E7: =E19 -> 80000 | F7: =F19 -> 80000 | G7: =G19 -> 80000 | H7: =H19 -> 80000 | I7: =I19 -> 80000 | J7: =J19 -> 80000 | ... N7: =N19 -> 80000
B8: (-) Backoffice | C8: =C27 -> 50000 | D8: =D27 -> 46000 | E8: =E27 -> 46000 | F8: =F27 -> 46000 | G8: =G27 -> 47000 | H8: =H27 -> 51000 | I8: =I27 -> 53500 | J8: =J27 -> 53500 | ... N8: =N27 -> 56500
B9: (-) Software | C9: =C42 -> 41540 | D9: =D42 -> 41932 | E9: =E42 -> 42177 | F9: =F42 -> 44635 | G9: =G42 -> 44831 | H9: =H42 -> 44929 | I9: =I42 -> 62293 | J9: =J42 -> 47538 | ... N9: =N42 -> 49441
B10: (-) Ocupação | C10: =C57 -> 34570 | D10: =D57 -> 44570 | E10: =E57 -> 44570 | F10: =F57 -> 34570 | G10: =G57 -> 34570 | H10: =H57 -> 34570 | I10: =I57 -> 29570 | J10: =J57 -> 29570 | ... N10: =N57 -> 29570
B11: (-) Beneficio Caju | C11: ='Overview Old'!C26*400 -> 44000 | D11: ='Overview Old'!D26*400 -> 47200 | E11: ='Overview Old'!E26*400 -> 49200 | F11: ='Overview Old'!F26*400 -> 54000 | G11: ='Overview Old'!G26*400 -> 55600 | H11: ='Overview Old'!H26*400 -> 56400 | I11: ='Overview Old'!I26*400 -> 58800 | J11: ='Overview Old'!J26*400 -> 60800 | K11: ='Overview Old'!K26*400 -> 62000 | L11: ='Overview Old'!L26*500 -> 81000 | M11: ='Overview Old'!M26*500 -> 82500 | N11: ='Overview Old'!N26*500 -> 84500
B12: (-) Premiações | C12: 5000 | D12: 5000 | E12: 5000 | F12: 5000 | G12: 5000 | H12: 5000 | I12: 5000 | J12: 5000 | K12: 5000 | L12: 5000 | M12: 5000 | N12: 5000
B13: (-) Eventos e Brindes Internos | C13: 30000 | D13: 10000 | E13: 10000 | F13: 10000 | G13: 10000 | H13: 10000 | I13: 10000 | J13: 10000 | K13: 10000 | L13: 10000 | M13: 20000 | N13: 40000
B14: (-) Outras despesas | C14: =C68 -> 13336 | D14: =D68 -> 17336 | E14: =E68 -> 17336 | F14: =F68 -> 17836 | G14: =G68 -> 17836 | H14: =H68 -> 17836 | I14: =I68 -> 18336 | J14: =J68 -> 18336 | ... N14: =N68 -> 18836
B16: UZK
B17: Trimestre | C17: 1 Trimestre | F17: 2 Trimestre | I17: 3 Trimestre | L17: 4 Trimestre
B18: Mês | C18: Janeiro | D18: Feveiro | E18: Março | F18: Abril | G18: Maio | H18: Junho | I18: Julho | J18: Agosto | K18: Setembro | L18: Outubro | M18: Novembro | N18: Dezembro
B19: (=) UZK | C19: =SUM(C20:C22) -> 80000 | D19: =SUM(D20:D22) -> 80000 | E19: =SUM(E20:E22) -> 80000 | F19: =SUM(F20:F22) -> 80000 | G19: =SUM(G20:G22) -> 80000 | H19: =SUM(H20:H22) -> 80000 | I19: =SUM(I20:I22) -> 80000 | J19: =SUM(J20:J22) -> 80000 | ... N19: =SUM(N20:N22) -> 80000
B20: (-) Victor Peixoto | C20: 30000 | D20: 30000 | E20: 30000 | F20: 30000 | G20: 30000 | H20: 30000 | I20: 30000 | J20: 30000 | K20: 30000 | L20: 30000 | M20: 30000 | N20: 30000
B21: (-) Rodrigo Queiroz | C21: 25000 | D21: 25000 | E21: 25000 | F21: 25000 | G21: 25000 | H21: 25000 | I21: 25000 | J21: 25000 | K21: 25000 | L21: 25000 | M21: 25000 | N21: 25000
B22: (-) André Musso | C22: 25000 | D22: 25000 | E22: 25000 | F22: 25000 | G22: 25000 | H22: 25000 | I22: 25000 | J22: 25000 | K22: 25000 | L22: 25000 | M22: 25000 | N22: 25000
B24: Backoffice
B25: Trimestre | C25: 1 Trimestre | F25: 2 Trimestre | I25: 3 Trimestre | L25: 4 Trimestre
B26: Mês | C26: Janeiro | D26: Feveiro | E26: Março | F26: Abril | G26: Maio | H26: Junho | I26: Julho | J26: Agosto | K26: Setembro | L26: Outubro | M26: Novembro | N26: Dezembro
B27: (=) Backoffice | C27: =SUM(C28:C37) -> 50000 | D27: =SUM(D28:D37) -> 46000 | E27: =SUM(E28:E37) -> 46000 | F27: =SUM(F28:F37) -> 46000 | G27: =SUM(G28:G37) -> 47000 | H27: =SUM(H28:H37) -> 51000 | I27: =SUM(I28:I37) -> 53500 | J27: =SUM(J28:J37) -> 53500 | ... N27: =SUM(N28:N37) -> 56500
B28: (-) Marlon Carneiro | C28: 7000 | D28: 7000 | E28: 7000 | F28: 7500 | G28: 7500 | H28: 7500 | I28: 7500 | J28: 7500 | K28: 7500 | L28: 8000 | M28: 8000 | N28: 8000
B29: (-) Warley Pablo | C29: 3500 | D29: 3500 | E29: 3500 | F29: 3500 | G29: 3500 | H29: 3500 | I29: 4000 | J29: 4000 | K29: 4000 | L29: 4000 | M29: 4000 | N29: 4000
B30: (-) Eduardo Tonane | C30: 2000 | D30: 2000 | E30: 2000 | F30: 2000 | G30: 3000 | H30: 3000 | I30: 3000 | J30: 3000 | K30: 3000 | L30: 3500 | M30: 3500 | N30: 3500
B31: (-) Karol Tognere | C31: 7000 | D31: 7000 | E31: 7000 | F31: 8000 | G31: 8000 | H31: 8000 | I31: 9000 | J31: 9000 | K31: 9000 | L31: 10000 | M31: 10000 | N31: 10000
B32: (-) Lianca Lopes | C32: 4000 | D32: 4000 | E32: 4000 | F32: 4500 | G32: 4500 | H32: 4500 | I32: 4500 | J32: 4500 | K32: 4500 | L32: 5000 | M32: 5000 | N32: 5000
B33: (-) Caio Massaroni | C33: 7000 | D33: 7000 | E33: 7000 | F33: 7500 | G33: 7500 | H33: 7500 | I33: 8000 | J33: 8000 | K33: 8000 | L33: 8000 | M33: 8000 | N33: 8000
B34: (-) Thiago Folador | C34: 6500 | D34: 6500 | E34: 6500 | F34: 7000 | G34: 7000 | H34: 7000 | I34: 7000 | J34: 7000 | K34: 7000 | L34: 7500 | M34: 7500 | N34: 7500
B35: (-) Julia Viana | C35: 6000 | D35: 6000 | E35: 6000 | F35: 6000 | G35: 6000 | H35: 6000 | I35: 6500 | J35: 6500 | K35: 6500 | L35: 6500 | M35: 6500 | N35: 6500
B36: (-) Marcelus | C36: 7000 | D36: 3000 | E36: 3000
B37: Novo - Contratar | H37: 4000 | I37: 4000 | J37: 4000 | K37: 4000 | L37: 4000 | M37: 4000 | N37: 4000
B39: Software
B40: Trimestre | C40: 1 Trimestre | F40: 2 Trimestre | I40: 3 Trimestre | L40: 4 Trimestre
B41: Mês | C41: Janeiro | D41: Feveiro | E41: Março | F41: Abril | G41: Maio | H41: Junho | I41: Julho | J41: Agosto | K41: Setembro | L41: Outubro | M41: Novembro | N41: Dezembro
B42: (=) Software | C42: =SUM(C43:C52) -> 41540 | D42: =SUM(D43:D52) -> 41932 | E42: =SUM(E43:E52) -> 42177 | F42: =SUM(F43:F52) -> 44635 | G42: =SUM(G43:G52) -> 44831 | H42: =SUM(H43:H52) -> 44929 | I42: =SUM(I43:I52) -> 62293 | J42: =SUM(J43:J52) -> 47538 | ... N42: =SUM(N43:N52) -> 49441
B43: GohighLevel | C43: 5000 | D43: 5000 | E43: 5000 | F43: 5000 | G43: 5000 | H43: 5000 | I43: 5000 | J43: 5000 | K43: 5000 | L43: 5000 | M43: 5000 | N43: 5000
B44: Adobe | C44: 2700 | D44: 2700 | E44: 2700 | F44: 3500 | G44: 3500 | H44: 3500 | I44: 4000 | J44: 4000 | K44: 4000 | L44: 4500 | M44: 4500 | N44: 4500
B45: Software Comercial | C45: 2000 | D45: 2000 | E45: 2000 | F45: 2500 | G45: 2500 | H45: 2500 | I45: 3000 | J45: 3000 | K45: 3000 | L45: 3000 | M45: 3000 | N45: 3000
B46: Safetec | C46: ='Overview Old'!C26*49 -> 5390 | D46: ='Overview Old'!D26*49 -> 5782 | E46: ='Overview Old'!E26*49 -> 6027 | F46: ='Overview Old'!F26*49 -> 6615 | G46: ='Overview Old'!G26*49 -> 6811 | H46: ='Overview Old'!H26*49 -> 6909 | I46: ='Overview Old'!I26*49 -> 7203 | J46: ='Overview Old'!J26*49 -> 7448 | ... N46: ='Overview Old'!N26*49 -> 8281
B47: Webflow | C47: 1300 | D47: 1300 | E47: 1300 | F47: 1300 | G47: 1300 | H47: 1300 | I47: 1300 | J47: 1300 | K47: 1300 | L47: 1300 | M47: 1300 | N47: 1300
B48: Conta Azul | C48: 800 | D48: 800 | E48: 800 | F48: 800 | G48: 800 | H48: 800 | I48: 800 | J48: 800 | K48: 800 | L48: 800 | M48: 800 | N48: 800
B49: Replit e AI Gerais | C49: 20000 | D49: 20000 | E49: 20000 | F49: 20000 | G49: 20000 | H49: 20000 | I49: 20000 | J49: 20000 | K49: 20000 | L49: 20000 | M49: 20000 | N49: 20000
B50: Bitrix | I50: 15000
B51: Clickup | C51: =25*19*6 -> 2850 | D51: =25*19*6 -> 2850 | E51: =25*19*6 -> 2850 | F51: =30*19*6 -> 3420 | G51: =30*19*6 -> 3420 | H51: =30*19*6 -> 3420 | I51: =35*19*6 -> 3990 | J51: =35*19*6 -> 3990 | K51: =35*19*6 -> 3990 | L51: =40*19*6 -> 4560 | M51: =40*19*6 -> 4560 | N51: =40*19*6 -> 4560
B52: Outros | C52: 1500 | D52: 1500 | E52: 1500 | F52: 1500 | G52: 1500 | H52: 1500 | I52: 2000 | J52: 2000 | K52: 2000 | L52: 2000 | M52: 2000 | N52: 2000
B54: Ocupação
B55: Trimestre | C55: 1 Trimestre | F55: 2 Trimestre | I55: 3 Trimestre | L55: 4 Trimestre
B56: Mês | C56: Janeiro | D56: Feveiro | E56: Março | F56: Abril | G56: Maio | H56: Junho | I56: Julho | J56: Agosto | K56: Setembro | L56: Outubro | M56: Novembro | N56: Dezembro
B57: (=) Ocupação | C57: =SUM(C58:C63) -> 34570 | D57: =SUM(D58:D63) -> 44570 | E57: =SUM(E58:E63) -> 44570 | F57: =SUM(F58:F63) -> 34570 | G57: =SUM(G58:G63) -> 34570 | H57: =SUM(H58:H63) -> 34570 | I57: =SUM(I58:I63) -> 29570 | J57: =SUM(J58:J63) -> 29570 | ... N57: =SUM(N58:N63) -> 29570
B58: Telefonia/Internet | C58: 1000 | D58: 1000 | E58: 1000 | F58: 1000 | G58: 1000 | H58: 1000 | I58: 1000 | J58: 1000 | K58: 1000 | L58: 1000 | M58: 1000 | N58: 1000
B59: Energia/Agua/IPTU | C59: 2450 | D59: 2450 | E59: 2450 | F59: 2450 | G59: 2450 | H59: 2450 | I59: 2450 | J59: 2450 | K59: 2450 | L59: 2450 | M59: 2450 | N59: 2450
B60: Aluguel/Condominio | C60: 16120 | D60: 16120 | E60: 16120 | F60: 16120 | G60: 16120 | H60: 16120 | I60: 16120 | J60: 16120 | K60: 16120 | L60: 16120 | M60: 16120 | N60: 16120
B61: Expediente/Limpeza/Outros | C61: 10000 | D61: 10000 | E61: 10000 | F61: 10000 | G61: 10000 | H61: 10000 | I61: 10000 | J61: 10000 | K61: 10000 | L61: 10000 | M61: 10000 | N61: 10000
B62: Despesa com Infraestrutura | C62: 5000 | D62: 15000 | E62: 15000 | F62: 5000 | G62: 5000 | H62: 5000
B65: Outras Despesas
B66: Trimestre | C66: 1 Trimestre | F66: 2 Trimestre | I66: 3 Trimestre | L66: 4 Trimestre
B67: Mês | C67: Janeiro | D67: Feveiro | E67: Março | F67: Abril | G67: Maio | H67: Junho | I67: Julho | J67: Agosto | K67: Setembro | L67: Outubro | M67: Novembro | N67: Dezembro
B68: (=) Outras Despesas | C68: =SUM(C69:C75) -> 13336 | D68: =SUM(D69:D75) -> 17336 | E68: =SUM(E69:E75) -> 17336 | F68: =SUM(F69:F75) -> 17836 | G68: =SUM(G69:G75) -> 17836 | H68: =SUM(H69:H75) -> 17836 | I68: =SUM(I69:I75) -> 18336 | J68: =SUM(J69:J75) -> 18336 | ... N68: =SUM(N69:N75) -> 18836
B69: Tarifas/Taxas | C69: 1500 | D69: 1500 | E69: 1500 | F69: 2000 | G69: 2000 | H69: 2000 | I69: 2500 | J69: 2500 | K69: 2500 | L69: 3000 | M69: 3000 | N69: 3000
B70: Outras Desp Adm. | C70: 2500 | D70: 2500 | E70: 2500 | F70: 2500 | G70: 2500 | H70: 2500 | I70: 2500 | J70: 2500 | K70: 2500 | L70: 2500 | M70: 2500 | N70: 2500
B71: Contabilidade | C71: =3840+1496 -> 5336 | D71: =3840+1496 -> 5336 | E71: =3840+1496 -> 5336 | F71: =3840+1496 -> 5336 | G71: =3840+1496 -> 5336 | H71: =3840+1496 -> 5336 | I71: =3840+1496 -> 5336 | J71: =3840+1496 -> 5336 | ... N71: =3840+1496 -> 5336
B72: Juridico | C72: 3000 | D72: 3000 | E72: 3000 | F72: 3000 | G72: 3000 | H72: 3000 | I72: 3000 | J72: 3000 | K72: 3000 | L72: 3000 | M72: 3000 | N72: 3000
B73: Consultoria Contabil | C73: 1000 | D73: 1000 | E73: 1000 | F73: 1000 | G73: 1000 | H73: 1000 | I73: 1000 | J73: 1000 | K73: 1000 | L73: 1000 | M73: 1000 | N73: 1000
B74: Cursos e Mentorias | D74: 4000 | E74: 4000 | F74: 4000 | G74: 4000 | H74: 4000 | I74: 4000 | J74: 4000 | K74: 4000 | L74: 4000 | M74: 4000 | N74: 4000

Sheet CSV
C2: Commerce
C3: Mês | D3: Janeiro | E3: Feveiro | F3: Março | G3: Abril | H3: Maio | I3: Junho | J3: Julho | K3: Agosto | L3: Setembro | M3: Outubro | N3: Novembro | O3: Dezembro
C4: CSV Total | D4: =D24+D96+D152+D213+D236+D124+D182+D64+D265+D295+D322+D342 -> 345754.4 | E4: =E24+E96+E152+E213+E236+E124+E182+E64+E265+E295+E322+E342 -> 380706.3 | F4: =F24+F96+F152+F213+F236+F124+F182+F64+F265+F295+F322+F342 -> 399437.54 | G4: =G24+G96+G152+G213+G236+G124+G182+G64+G265+G295+G322+G342 -> 465597.96 | H4: =H24+H96+H152+H213+H236+H124+H182+H64+H265+H295+H322+H342 -> 488400.64 | I4: =I24+I96+I152+I213+I236+I124+I182+I64+I265+I295+I322+I342 -> 495996.08 | J4: =J24+J96+J152+J213+J236+J124+J182+J64+J265+J295+J322+J342 -> 557632.94 | K4: =K24+K96+K152+K213+K236+K124+K182+K64+K265+K295+K322+K342 -> 583914.17 | ... O4: =O24+O96+O152+O213+O236+O124+O182+O64+O265+O295+O322+O342 -> 687435.48
C5: Quantidade de operadores | D5: =D15+D144+D205+D228+D88+D117+D175+D57+D258+D313 -> 67 | E5: =E15+E144+E205+E228+E88+E117+E175+E57+E258+E313 -> 73 | F5: =F15+F144+F205+F228+F88+F117+F175+F57+F258+F313 -> 76 | G5: =G15+G144+G205+G228+G88+G117+G175+G57+G258+G313 -> 86 | H5: =H15+H144+H205+H228+H88+H117+H175+H57+H258+H313 -> 89 | I5: =I15+I144+I205+I228+I88+I117+I175+I57+I258+I313 -> 90 | J5: =J15+J144+J205+J228+J88+J117+J175+J57+J258+J313 -> 95 | K5: =K15+K144+K205+K228+K88+K117+K175+K57+K258+K313 -> 99 | ... O5: =O15+O144+O205+O228+O88+O117+O175+O57+O258+O313 -> 112
C6: Quantidade de Líderes | D6: =D286 -> 6 | E6: =E286 -> 7 | F6: =F286 -> 7 | G6: =G286 -> 7 | H6: =H286 -> 8 | I6: =I286 -> 8 | J6: =J286 -> 9 | K6: =K286 -> 9 | ... O6: =O286 -> 10
C7: Pessoas Totais Commerce (CSV) | D7: =D5+D6 -> 73 | E7: =E5+E6 -> 80 | F7: =F5+F6 -> 83 | G7: =G5+G6 -> 93 | H7: =H5+H6 -> 97 | I7: =I5+I6 -> 98 | J7: =J5+J6 -> 104 | K7: =K5+K6 -> 108 | ... O7: =O5+O6 -> 122
B9: Performance
B10: Mês | C10: Dezembro | D10: Janeiro | E10: Feveiro | F10: Março | G10: Abril | H10: Maio | I10: Junho | J10: Julho | K10: Agosto | L10: Setembro | M10: Outubro | N10: Novembro | O10: Dezembro
B11: MRR Performance | C11: =Revenue!C7 -> 475000 | D11: =Revenue!D7 -> 496750 | E11: =Revenue!E7 -> 516542.5 | F11: =Revenue!F7 -> 534553.68 | G11: =Revenue!G7 -> 558443.84 | H11: =Revenue!H7 -> 580183.9 | I11: =Revenue!I7 -> 599967.35 | J11: =Revenue!J7 -> 626970.29 | ... O11: =Revenue!O7 -> 754263.58 | P11: =SUM(D11:O11) -> 7426334.9
B12: Contratos Performance | C12: =Revenue!C9 -> 176 | D12: =Revenue!D9 -> 181.85009 | E12: =Revenue!E9 -> 187.15183 | F12: =Revenue!F9 -> 191.95774 | G12: =Revenue!G9 -> 198.82868 | H12: =Revenue!H9 -> 205.06444 | I12: =Revenue!I9 -> 210.72459 | J12: =Revenue!J9 -> 218.8743 | ... O12: =Revenue!O9 -> 257.94236
B13: Capacity Contratos | C13: 12 | D13: 12 | E13: 12 | F13: 12 | G13: 12 | H13: 12 | I13: 12 | J13: 12 | K13: 12 | L13: 12 | M13: 12 | N13: 12 | O13: 12
B14: Operadores Necessários | C14: =C12/C13 -> 14.666667 | D14: =D12/D13 -> 15.154174 | E14: =E12/E13 -> 15.595986 | F14: =F12/F13 -> 15.996478 | G14: =G12/G13 -> 16.569057 | H14: =H12/H13 -> 17.088703 | I14: =I12/I13 -> 17.560383 | J14: =J12/J13 -> 18.239525 | ... O14: =O12/O13 -> 21.495197
B15: Operadores Atuais | C15: 15 | D15: =count(D25:D50) -> 17 | E15: =count(E25:E50) -> 19 | F15: =count(F25:F50) -> 20 | G15: =count(G25:G50) -> 20 | H15: =count(H25:H50) -> 21 | I15: =count(I25:I50) -> 21 | J15: =count(J25:J50) -> 22 | K15: =count(K25:K50) -> 22 | ... O15: =count(O25:O50) -> 25
B16: Necessidade de contratar | C16: =C14-C15 -> -0.33333333 | D16: =D14-D15 -> -1.8458256 | E16: =E14-E15 -> -3.4040141 | F16: =F14-F15 -> -4.003522 | G16: =G14-G15 -> -3.4309431 | H16: =H14-H15 -> -3.9112966 | I16: =I14-I15 -> -3.4396175 | J16: =J14-J15 -> -3.7604746 | ... O16: =O14-O15 -> -3.504803
B17: Contratos por gestor | C17: =C12/C15 -> 11.733333 | D17: =D12/D15 -> 10.697064 | E17: =E12/E15 -> 9.8500964 | F17: =F12/F15 -> 9.5978868 | G17: =G12/G15 -> 9.9414342 | H17: =H12/H15 -> 9.7649734 | I17: =I12/I15 -> 10.034504 | J17: =J12/J15 -> 9.948832 | ... O17: =O12/O15 -> 10.317695
B18: MRR por Gestor | C18: =C11/C15 -> 31666.667 | D18: =D11/D15 -> 29220.588 | E18: =E11/E15 -> 27186.447 | F18: =F11/F15 -> 26727.684 | G18: =G11/G15 -> 27922.192 | H18: =H11/H15 -> 27627.805 | I18: =I11/I15 -> 28569.874 | J18: =J11/J15 -> 28498.649 | ... O18: =O11/O15 -> 30170.543
B19: CSV | D19: =(D24+D64)/D11 -> 0.19305486 | E19: =(E24+E64)/E11 -> 0.20598499 | F19: =(F24+F64)/F11 -> 0.21026888 | G19: =(G24+G64)/G11 -> 0.21694214 | H19: =(H24+H64)/H11 -> 0.22001645 | I19: =(I24+I64)/I11 -> 0.21526171 | J19: =(J24+J64)/J11 -> 0.22473154 | K19: =(K24+K64)/K11 -> 0.23313889 | ... O19: =(O24+O64)/O11 -> 0.24215673
C21: Gestor de Performance
C22: Trimestre | D22: 1 Trimestre | G22: 2 Trimestre | J22: 3 Trimestre | M22: 4 Trimestre
C23: Mês | D23: Janeiro | E23: Feveiro | F23: Março | G23: Abril | H23: Maio | I23: Junho | J23: Julho | K23: Agosto | L23: Setembro | M23: Outubro | N23: Novembro | O23: Dezembro | P23: =O24/O11 -> 0.1785185
C24: (=) Gestor de Performance | D24: =SUM(D25:D50) -> 66650 | E24: =SUM(E25:E50) -> 76650 | F24: =SUM(F25:F50) -> 82650 | G24: =SUM(G25:G50) -> 87650 | H24: =SUM(H25:H50) -> 94150 | I24: =SUM(I25:I50) -> 95650 | J24: =SUM(J25:J50) -> 105650 | K24: =SUM(K25:K50) -> 110150 | ... O24: =SUM(O25:O50) -> 134650 | P24: =SUM(D24:O24) -> 1226300
C25: (-) Gabriel Taufner | D25: 2000 | E25: 2000 | F25: 2000 | G25: 2000 | H25: 2500 | I25: 2500 | J25: 2500 | K25: 3000 | L25: 3000 | M25: 3000 | N25: 3500 | O25: 3500
C26: (-) Allan Eduardo | D26: 3000 | E26: 3000 | F26: 3000 | G26: 3500 | H26: 3500 | I26: 3500 | J26: 4000 | K26: 4000 | L26: 4000 | M26: 4500 | N26: 4500 | O26: 4500
C27: (-) Victor Matsushita | D27: 3000 | E27: 3000 | F27: 3500 | G27: 3500 | H27: 3500 | I27: 4000 | J27: 4000 | K27: 4000 | L27: 4500 | M27: 4500 | N27: 4500 | O27: 5000
C28: (-) Gustavo Pires | D28: 4000 | E28: 4000 | F28: 4000 | G28: 4000 | H28: 4500 | I28: 4500 | J28: 4500 | K28: 5000 | L28: 5000 | M28: 5000 | N28: 5000 | O28: 5000
C29: (-) Rayan Coutinho | D29: 4250 | E29: 4250 | F29: 4250 | G29: 4750 | H29: 4750 | I29: 4750 | J29: 5250 | K29: 5250 | L29: 5250 | M29: 5250 | N29: 5750 | O29: 5750
C30: (-) Rafael Avila | D30: 5000 | E30: 5000 | F30: 5000 | G30: 5500 | H30: 5500 | I30: 5500 | J30: 6000 | K30: 6000 | L30: 6000 | M30: 6500 | N30: 6500 | O30: 6500
C31: (-) Thiago Martins | D31: 5000 | E31: 5000 | F31: 5000 | G31: 5000 | H31: 5500 | I31: 5500 | J31: 5500 | K31: 6000 | L31: 6000 | M31: 6000 | N31: 6500 | O31: 6500
C32: (-) Lucas Rosseti | D32: 5000 | E32: 5000 | F32: 5000 | G32: 5500 | H32: 5500 | I32: 5500 | J32: 6000 | K32: 6000 | L32: 6000 | M32: 6500 | N32: 6500 | O32: 6500
C33: (-) Thiago Andrey | D33: 5000 | E33: 5000 | F33: 5000 | G33: 5500 | H33: 5500 | I33: 5500 | J33: 6000 | K33: 6000 | L33: 6000 | M33: 6500 | N33: 6500 | O33: 6500
C34: (-) Victor Arpini | D34: 6000 | E34: 6000 | F34: 6000 | G34: 6000 | H34: 6000 | I34: 6000 | J34: 6000 | K34: 6000 | L34: 6000 | M34: 6500 | N34: 6500 | O34: 6500
C35: (-) Bruno Parreira | D35: 4000 | E35: 4000 | F35: 4000 | G35: 4500 | H35: 4500 | I35: 4500 | J35: 5000 | K35: 5000 | L35: 5000 | M35: 5000 | N35: 5000 | O35: 5000
C36: (-) Jônatas Cavalcante | D36: 4000 | E36: 4000 | F36: 4000 | G36: 4500 | H36: 4500 | I36: 4500 | J36: 5000 | K36: 5000 | L36: 5000 | M36: 5000 | N36: 5000 | O36: 5000
... C41: (-) Bruno Silva | D41: 3000 | E41: 3000 | F41: 3000 | G41: 3000 | H41: 3000 | I41: 3000 | J41: 3000 | K41: 5500 | L41: 5500 | M41: 6000 | N41: 6000 | O41: 6000
C42: Novo - Contratar | E42: 5000 | F42: 5000 | G42: 5000 | H42: 5000 | I42: 5500 | J42: 5500 | K42: 5500 | L42: 5500 | M42: 6000 | N42: 6000 | O42: 6000
C43: Novo - Contratar | E43: 5000 | F43: 5000 | G43: 5000 | H43: 5000 | I43: 5000 | J43: 5000 | K43: 5500 | L43: 5500 | M43: 5500 | N43: 5500 | O43: 5500
C44: Novo - Contratar | F44: 5000 | G44: 5000 | H44: 5000 | I44: 5000 | J44: 5000 | K44: 5000 | L44: 5500 | M44: 5500 | N44: 5500 | O44: 5500
C45: Novo - Contratar | H45: 5000 | I45: 5000 | J45: 5000 | K45: 5000 | L45: 5000 | M45: 5500 | N45: 5500 | O45: 5500
C46: Novo - Contratar | J46: 5000 | K46: 5000 | L46: 5000 | M46: 5000 | N46: 5500 | O46: 5500
C47: Novo - Contratar | L47: 5000 | M47: 5000 | N47: 5000 | O47: 5000
C48: Novo - Contratar | M48: 5000 | N48: 5000 | O48: 5000
C49: Novo - Contratar | O49: 5000
C50: Novo - Contratar
B52: Designer Performance
B53: Mês | C53: Dezembro | D53: Janeiro | E53: Feveiro | F53: Março | G53: Abril | H53: Maio | I53: Junho | J53: Julho | K53: Agosto | L53: Setembro | M53: Outubro | N53: Novembro | O53: Dezembro
B54: Contratos Performance | C54: =C12 -> 176 | D54: =D12 -> 181.85009 | E54: =E12 -> 187.15183 | F54: =F12 -> 191.95774 | G54: =G12 -> 198.82868 | H54: =H12 -> 205.06444 | I54: =I12 -> 210.72459 | J54: =J12 -> 218.8743 | ... O54: =O12 -> 257.94236
B55: Capacity | C55: 26 | D55: 26 | E55: 26 | F55: 26 | G55: 26 | H55: 26 | I55: 26 | J55: 26 | K55: 26 | L55: 26 | M55: 26 | N55: 26 | O55: 26
B56: Designers Necessários | C56: =C54/C55 -> 6.7692308 | D56: =D54/D55 -> 6.9942343 | E56: =E54/E55 -> 7.1981474 | F56: =F54/F55 -> 7.3829899 | G56: =G54/G55 -> 7.6472571 | H56: =H54/H55 -> 7.8870939 | I56: =I54/I55 -> 8.1047919 | J56: =J54/J55 -> 8.4182425 | ... O56: =O54/O55 -> 9.9208601
B57: Designers Atuais | C57: 6 | D57: =count(D65:D80) -> 8 | E57: =count(E65:E80) -> 8 | F57: =count(F65:F80) -> 8 | G57: =count(G65:G80) -> 9 | H57: =count(H65:H80) -> 9 | I57: =count(I65:I80) -> 9 | J57: =count(J65:J80) -> 9 | K57: =count(K65:K80) -> 10 | ... O57: =count(O65:O80) -> 11
B58: Necessidade de contratar | C58: =C56-C57 -> 0.76923077 | D58: =D56-D57 -> -1.0057657 | E58: =E56-E57 -> -0.80185265 | F58: =F56-F57 -> -0.61701013 | G58: =G56-G57 -> -1.3527429 | H58: =H56-H57 -> -1.1129061 | I58: =I56-I57 -> -0.89520807 | J58: =J56-J57 -> -0.58175753 | ... O58: =O56-O57 -> -1.0791399
B59: Contas por Designer | C59: =C54/C57 -> 29.333333 | D59: =D54/D57 -> 22.731262 | E59: =E54/E57 -> 23.393979 | F59: =F54/F57 -> 23.994717 | G59: =G54/G57 -> 22.092076 | H59: =H54/H57 -> 22.784938 | I59: =I54/I57 -> 23.413843 | J59: =J54/J57 -> 24.319367 | ... O59: =O54/O57 -> 23.449306
C61: Designer Performance
C62: Trimestre | D62: 1 Trimestre | G62: 2 Trimestre | J62: 3 Trimestre | M62: 4 Trimestre
C63: Mês | D63: Janeiro | E63: Feveiro | F63: Março | G63: Abril | H63: Maio | I63: Junho | J63: Julho | K63: Agosto | L63: Setembro | M63: Outubro | N63: Novembro | O63: Dezembro
C64: (=) Designer Performance | D64: =SUM(D65:D75) -> 29250 | E64: =SUM(E65:E75) -> 29750 | F64: =SUM(F65:F75) -> 29750 | G64: =SUM(G65:G75) -> 33500 | H64: =SUM(H65:H75) -> 33500 | I64: =SUM(I65:I75) -> 33500 | J64: =SUM(J65:J75) -> 35250 | K64: =SUM(K65:K75) -> 41750 | ... O64: =SUM(O65:O75) -> 48000 | P64: =SUM(D64:O64) -> 440000
C65: Wendel Martins de Azevedo | D65: 4500 | E65: 4500 | F65: 4500 | G65: 4500 | H65: 4500 | I65: 4500 | J65: 5000 | K65: 5000 | L65: 5000 | M65: 5000 | N65: 5000 | O65: 5000
C66: George Lucas | D66: 4000 | E66: 4000 | F66: 4000 | G66: 4250 | H66: 4250 | I66: 4250 | J66: 4500 | K66: 4500 | L66: 4500 | M66: 4500 | N66: 4500 | O66: 4500
C67: Carlos | D67: 4000 | E67: 4000 | F67: 4000 | G67: 4000 | H67: 4000 | I67: 4000 | J67: 4250 | K67: 4250 | L67: 4250 | M67: 4250 | N67: 4250 | O67: 4250
C68: Leonardo Soares | D68: 3500 | E68: 4000 | F68: 4000 | G68: 4500 | H68: 4500 | I68: 4500 | J68: 4500 | K68: 4500 | L68: 4500 | M68: 4750 | N68: 4750 | O68: 4750
C69: Rayanne Vieira | D69: 3500 | E69: 3500 | F69: 3500 | G69: 3500 | H69: 3500 | I69: 3500 | J69: 4000 | K69: 4000 | L69: 4000 | M69: 4000 | N69: 4000 | O69: 4000
C70: Bernardo | D70: 2750 | E70: 2750 | F70: 2750 | G70: 2750 | H70: 2750 | I70: 2750 | J70: 3000 | K70: 3500 | L70: 3500 | M70: 3500 | N70: 3500 | O70: 3500
C71: João Lucas | D71: 4000 | E71: 4000 | F71: 4000 | G71: 4000 | H71: 4000 | I71: 4000 | J71: 4000 | K71: 4000 | L71: 4000 | M71: 4000 | N71: 4000 | O71: 4000
C72: Elizio | D72: 3000 | E72: 3000 | F72: 3000 | G72: 3000 | H72: 3000 | I72: 3000 | J72: 3000 | K72: 3000 | L72: 3000 | M72: 3000 | N72: 3000 | O72: 3000
C73: Novo - Contratar | G73: 3000 | H73: 3000 | I73: 3000 | J73: 3000 | K73: 3000 | L73: 3000 | M73: 3000 | N73: 3000 | O73: 3000
C74: Novo - Contratar | K74: 6000 | L74: 6000 | M74: 6000 | N74: 6000 | O74: 6000
C75: Novo - Contratar | O75: 6000
C76: Novo - Contratar
C77: Novo - Contratar
C78: Novo - Contratar
C79: Novo - Contratar
C80: Novo - Contratar
B82: Creators
B83: Mês | C83: Dezembro | D83: Janeiro | E83: Feveiro | F83: Março | G83: Abril | H83: Maio | I83: Junho | J83: Julho | K83: Agosto | L83: Setembro | M83: Outubro | N83: Novembro | O83: Dezembro
B84: MRR Creators | C84: =Revenue!C12 -> 223000 | D84: =Revenue!D12+CAC!Q55 -> 310680 | E84: =Revenue!E12+CAC!R55 -> 341328.8 | F84: =Revenue!F12+CAC!S55 -> 369219.21 | G84: =Revenue!G12+CAC!T55 -> 411849.48 | H84: =Revenue!H12+CAC!U55 -> 440633.03 | I84: =Revenue!I12+CAC!V55 -> 466826.05 | J84: =Revenue!J12+CAC!W55 -> 509161.71 | K84: =Revenue!K12+CAC!X55 -> 537677.16 | ... O84: =Revenue!O12+CAC!AB55 -> 659818.47 | P84: =SUM(D84:O84) -> 5850613.2
B85: Contratos Creators | C85: =Revenue!C14 -> 53 | D85: =Revenue!D14+CAC!Q57 -> 66.841115 | E85: =Revenue!E14+CAC!R57 -> 72.391107 | F85: =Revenue!F14+CAC!S57 -> 77.422467 | G85: =Revenue!G14+CAC!T57 -> 84.816069 | H85: =Revenue!H14+CAC!U57 -> 90.100104 | I85: =Revenue!I14+CAC!V57 -> 94.897313 | J85: =Revenue!J14+CAC!W57 -> 102.33161 | K85: =Revenue!K14+CAC!X57 -> 107.65766 | ... O85: =Revenue!O14+CAC!AB57 -> 130.21087
B86: Capacity | C86: 18 | D86: 18 | E86: 18 | F86: 18 | G86: 18 | H86: 18 | I86: 18 | J86: 18 | K86: 18 | L86: 18 | M86: 18 | N86: 18 | O86: 18
B87: Operadores Necessários | C87: =C85/C86 -> 2.9444444 | D87: =D85/D86 -> 3.7133953 | E87: =E85/E86 -> 4.0217281 | F87: =F85/F86 -> 4.3012482 | G87: =G85/G86 -> 4.7120039 | H87: =H85/H86 -> 5.0055613 | I87: =I85/I86 -> 5.2720729 | J87: =J85/J86 -> 5.6850893 | ... O87: =O85/O86 -> 7.2339375
B88: Operadores Atuais | C88: 3 | D88: =count(D97:D109) -> 6 | E88: =count(E97:E109) -> 7 | F88: =count(F97:F109) -> 7 | G88: =count(G97:G109) -> 7 | H88: =count(H97:H109) -> 7 | I88: =count(I97:I109) -> 7 | J88: =count(J97:J109) -> 7 | K88: =count(K97:K109) -> 8 | ... O88: =count(O97:O109) -> 9
B89: Necessidade de contratar | C89: =C87-C88 -> -0.055555556 | D89: =D87-D88 -> -2.2866047 | E89: =E87-E88 -> -2.9782719 | F89: =F87-F88 -> -2.6987518 | G89: =G87-G88 -> -2.2879961 | H89: =H87-H88 -> -1.9944387 | I89: =I87-I88 -> -1.7279271 | J89: =J87-J88 -> -1.3149107 | ... O89: =O87-O88 -> -1.7660625
B90: Contas por Analista | C90: =C85/C88 -> 17.666667 | D90: =D85/D88 -> 11.140186 | E90: =E85/E88 -> 10.341587 | F90: =F85/F88 -> 11.060352 | G90: =G85/G88 -> 12.116581 | H90: =H85/H88 -> 12.871443 | I90: =I85/I88 -> 13.556759 | J90: =J85/J88 -> 14.618801 | ... O90: =O85/O88 -> 14.467875
B91: MRR por Analista | C91: =C84/C88 -> 74333.333 | D91: =D84/D88 -> 51780 | E91: =E84/E88 -> 48761.257 | F91: =F84/F88 -> 52745.601 | G91: =G84/G88 -> 58835.64 | H91: =H84/H88 -> 62947.575 | I91: =I84/I88 -> 66689.436 | J91: =J84/J88 -> 72737.387 | ... O91: =O84/O88 -> 73313.164
C93: Analista de Creators
C94: Trimestre | D94: 1 Trimestre | G94: 2 Trimestre | J94: 3 Trimestre | M94: 4 Trimestre
C95: Mês | D95: Janeiro | E95: Feveiro | F95: Março | G95: Abril | H95: Maio | I95: Junho | J95: Julho | K95: Agosto | L95: Setembro | M95: Outubro | N95: Novembro | O95: Dezembro
C96: (=) Analista de Creators | D96: =SUM(D97:D109) -> 22500 | E96: =SUM(E97:E109) -> 26000 | F96: =SUM(F97:F109) -> 26000 | G96: =SUM(G97:G109) -> 29000 | H96: =SUM(H97:H109) -> 29000 | I96: =SUM(I97:I109) -> 29500 | J96: =SUM(J97:J109) -> 31000 | K96: =SUM(K97:K109) -> 35000 | ... O96: =SUM(O97:O109) -> 44000
C97: Debora Mund | D97: 4500 | E97: 4500 | F97: 4500 | G97: 5000 | H97: 5000 | I97: 5000 | J97: 5500 | K97: 5500 | L97: 5500 | M97: 6000 | N97: 6000 | O97: 6000
C98: Ana Lello | D98: 4000 | E98: 4000 | F98: 4000 | G98: 4500 | H98: 4500 | I98: 4500 | J98: 5000 | K98: 5000 | L98: 5000 | M98: 5500 | N98: 5500 | O98: 5500
C99: Lara Grobério Miranda Carlos | D99: 5000 | E99: 5000 | F99: 5000 | G99: 5500 | H99: 5500 | I99: 5500 | J99: 5500 | K99: 5500 | L99: 5500 | M99: 6000 | N99: 6000 | O99: 6000
C100: Mariana | D100: 4000 | E100: 4000 | F100: 4000 | G100: 4500 | H100: 4500 | I100: 4500 | J100: 5000 | K100: 5000 | L100: 5000 | M100: 5500 | N100: 5500 | O100: 5500
C101: Geiziele (estagiária) | D101: 1500 | E101: 1500 | F101: 1500 | G101: 2000 | H101: 2000 | I101: 2000 | J101: 2000 | K101: 2000 | L101: 2000 | M101: 3000 | N101: 3000 | O101: 3000
C102: Raquel Oliveira | D102: 3500 | E102: 3500 | F102: 3500 | G102: 4000 | H102: 4000 | I102: 4000 | J102: 4000 | K102: 4000 | L102: 4500 | M102: 4500 | N102: 4500 | O102: 4500
C103: Novo - Contratar | E103: 3500 | F103: 3500 | G103: 3500 | H103: 3500 | I103: 4000 | J103: 4000 | K103: 4000 | L103: 4000 | M103: 4500 | N103: 4500 | O103: 4500
C104: Novo - Contratar | K104: 4000 | L104: 4000 | M104: 4500 | N104: 4500 | O104: 4500
C105: Novo - Contratar | N105: 4500 | O105: 4500
C106: Novo - Contratar
C107: Novo - Contratar
C108: Novo - Contratar
C109: Novo - Contratar
B112: Designer Creators
B113: Mês | C113: Dezembro | D113: Janeiro | E113: Feveiro | F113: Março | G113: Abril | H113: Maio | I113: Junho | J113: Julho | K113: Agosto | L113: Setembro | M113: Outubro | N113: Novembro | O113: Dezembro
...

Sheet Overview Old
B2: Trimestre | C2: 1 Trimestre | F2: 2 Trimestre | I2: 3 Trimestre | L2: 4 Trimestre | R2: 1 Trimestre
C3: Janeiro | D3: Feveiro | E3: Março | F3: Abril | G3: Maio | H3: Junho | I3: Julho | J3: Agosto | K3: Setembro | L3: Outubro | M3: Novembro | N3: Dezembro | O3: Total | R3: Inadimpência | S3: 0.06
B4: (+) MRR Ativo | C4: =Revenue!D5 -> 1156850 | D4: =Revenue!E5 -> 1267733.5 | E4: =Revenue!F5 -> 1368637.5 | F4: =Revenue!G5 -> 1485460.1 | G4: =Revenue!H5 -> 1591768.7 | H4: =Revenue!I5 -> 1688509.5 | I4: =Revenue!J5 -> 1806543.7 | J4: =Revenue!K5 -> 1913954.7 | ... N4: =Revenue!O5 -> 2337387.9 | O4: =sum(C4:N4) -> 20998078
B5: (+) Receita Pontual | C5: =Revenue!D37 -> 240000 | D5: =Revenue!E37 -> 280000 | E5: =Revenue!F37 -> 270000 | F5: =Revenue!G37 -> 288333.33 | G5: =Revenue!H37 -> 306666.67 | H5: =Revenue!I37 -> 325000 | I5: =Revenue!J37 -> 343333.33 | J5: =Revenue!K37 -> 361666.67 | ... N5: =Revenue!O37 -> 435000 | O5: =sum(C5:N5) -> 4045000 | R5: 2 Trimestre
B6: (+) Outras Receitas | C6: ='Outras Receitas'!C15 -> 20766.667 | D6: ='Outras Receitas'!D15 -> 60408 | E6: ='Outras Receitas'!E15 -> 25626.667 | F6: ='Outras Receitas'!F15 -> 43076.667 | G6: ='Outras Receitas'!G15 -> 90096.667 | H6: ='Outras Receitas'!H15 -> 48783.333 | I6: ='Outras Receitas'!I15 -> 85573.333 | J6: ='Outras Receitas'!J15 -> 135713.33 | ... N6: ='Outras Receitas'!N15 -> 137006.67 | O6: =sum(C6:N6) -> 1040111.3 | R6: Inadimpência | S6: 0.06
B7: (=) Receita Total Faturavel | C7: =C4+C5+C6 -> 1417616.7 | D7: =D4+D5+D6 -> 1608141.5 | E7: =E4+E5+E6 -> 1664264.2 | F7: =F4+F5+F6 -> 1816870.1 | G7: =G4+G5+G6 -> 1988532 | H7: =H4+H5+H6 -> 2062292.9 | I7: =I4+I5+I6 -> 2235450.3 | J7: =J4+J5+J6 -> 2411334.7 | ... O7: =O4+O5+O6 -> 26083189
B8: (-) Inadimplência | C8: =C7*$S$3 -> 85057 | D8: =D7*$S$3 -> 96488.49 | E8: =E7*$S$3 -> 99855.849 | F8: =F7*$S$6 -> 109012.21 | G8: =G7*$S$6 -> 119311.92 | H8: =H7*$S$6 -> 123737.57 | I8: =I7*$S$9 -> 134127.02 | J8: =J7*$S$9 -> 144680.08 | K8: =K7*$S$9 -> 148244.73 | L8: =L7*$S$12 -> 159959.15 | M8: =M7*$S$12 -> 169953.67 | N8: =N7*$S$12 -> 174563.67 | O8: =sum(C8:N8) -> 1564991.4 | P8: =O8/$O$7 -> 0.06 | R8: 3 Trimestre
B9: (-) Impostos Sob Receita | C9: ='Tributário'!F11+'Tributário'!F12+'Tributário'!F13 -> 133132.3 | D9: ='Tributário'!G11+'Tributário'!G12+'Tributário'!G13 -> 150146.17 | E9: ='Tributário'!H11+'Tributário'!H12+'Tributário'!H13 -> 155157.92 | F9: ='Tributário'!I11+'Tributário'!I12+'Tributário'!I13 -> 170420.41 | G9: ='Tributário'!J11+'Tributário'!J12+'Tributário'!J13 -> 185749.82 | H9: ='Tributário'!K11+'Tributário'!K12+'Tributário'!K13 -> 192336.66 | I9: ='Tributário'!L11+'Tributário'!L12+'Tributário'!L13 -> 207799.63 | J9: ='Tributário'!M11+'Tributário'!M12+'Tributário'!M13 -> 223506.1 | ... N9: ='Tributário'!Q11+'Tributário'!Q12+'Tributário'!Q13 -> 267982.85 | O9: =sum(C9:N9) -> 2422411.4 | P9: =O9/$O$7 -> 0.092872516 | R9: Inadimpência | S9: 0.06
B10: (=) Receita Líquida | C10: =C7-C8-C9 -> 1199427.4 | D10: =D7-D8-D9 -> 1361506.8 | E10: =E7-E8-E9 -> 1409250.4 | F10: =F7-F8-F9 -> 1537437.5 | G10: =G7-G8-G9 -> 1683470.3 | H10: =H7-H8-H9 -> 1746218.6 | I10: =I7-I8-I9 -> 1893523.7 | J10: =J7-J8-J9 -> 2043148.5 | ... N10: =N7-N8-N9 -> 2466848 | O10: =sum(C10:N10) -> 22095787 | Q10: =O10/$O$7 -> 0.84712748
B11: (-) CSV | C11: =CSV!D4 -> 345754.4 | D11: =CSV!E4 -> 380706.3 | E11: =CSV!F4 -> 399437.54 | F11: =CSV!G4 -> 465597.96 | G11: =CSV!H4 -> 488400.64 | H11: =CSV!I4 -> 495996.08 | I11: =CSV!J4 -> 557632.94 | J11: =CSV!K4 -> 583914.17 | ... N11: =CSV!O4 -> 687435.48 | O11: =sum(C11:N11) -> 6314099.1 | P11: =O11/$O$7 -> 0.24207542 | R11: 4 Trimestre
B12: (=) Margem Bruta | C12: =C10-C11 -> 853672.97 | D12: =D10-D11 -> 980800.54 | E12: =E10-E11 -> 1009812.8 | F12: =F10-F11 -> 1071839.5 | G12: =G10-G11 -> 1195069.6 | H12: =H10-H11 -> 1250222.5 | I12: =I10-I11 -> 1335890.7 | J12: =J10-J11 -> 1459234.4 | ... N12: =N10-N11 -> 1779412.6 | O12: =sum(C12:N12) -> 15781688 | Q12: =O12/$O$7 -> 0.60505206 | R12: Inadimpência | S12: 0.06
B13: (-) CAC | C13: =CAC!C6 -> 262495.71 | D13: =CAC!D6 -> 285895.71 | E13: =CAC!E6 -> 311895.71 | F13: =CAC!F6 -> 337573.77 | G13: =CAC!G6 -> 422573.77 | H13: =CAC!H6 -> 362573.77 | I13: =CAC!I6 -> 453925.18 | J13: =CAC!J6 -> 371925.18 | ... N13: =CAC!N6 -> 428776.58 | O13: =sum(C13:N13) -> 4449113.7 | P13: =O13/$O$7 -> 0.17057399
B14: (-) SG&A | C14: ='SG&A'!C6 -> 298446 | D14: ='SG&A'!D6 -> 292038 | E14: ='SG&A'!E6 -> 294283 | F14: ='SG&A'!F6 -> 292041 | G14: ='SG&A'!G6 -> 294837 | H14: ='SG&A'!H6 -> 299735 | I14: ='SG&A'!I6 -> 317499 | J14: ='SG&A'!J6 -> 304744 | ... N14: ='SG&A'!N6 -> 363847 | O14: =sum(C14:N14) -> 3735216 | P14: =O14/$O$7 -> 0.14320396
B15: (=) EBITDA | C15: =C12-C13-C14 -> 292731.26 | D15: =D12-D13-D14 -> 402866.83 | E15: =E12-E13-E14 -> 403634.14 | F15: =F12-F13-F14 -> 442224.76 | G15: =G12-G13-G14 -> 477658.87 | H15: =H12-H13-H14 -> 587913.76 | I15: =I12-I13-I14 -> 564466.57 | J15: =J12-J13-J14 -> 782565.2 | ... N15: =N12-N13-N14 -> 986788.97 | O15: =sum(C15:N15) -> 7597357.9 | Q15: =O15/$O$7 -> 0.29127411
B16: (-) IR + CSLL | C16: ='Tributário'!F14 -> 99528.628 | D16: ='Tributário'!G14 -> 136974.72 | E16: ='Tributário'!H14 -> 137235.61 | F16: ='Tributário'!I14 -> 150356.42 | G16: ='Tributário'!J14 -> 162404.02 | H16: ='Tributário'!K14 -> 199890.68 | I16: ='Tributário'!L14 -> 191918.63 | J16: ='Tributário'!M14 -> 266072.17 | ... N16: ='Tributário'!Q14 -> 335508.25 | O16: =sum(C16:N16) -> 2583101.7 | P16: =O16/$O$7 -> 0.099033199
B17: (-) CAPEX | C17: ='CAPEX e Giro'!D5 -> 35000 | D17: ='CAPEX e Giro'!E5 -> 35000 | E17: ='CAPEX e Giro'!F5 -> 35000 | F17: ='CAPEX e Giro'!G5 -> 35000 | G17: ='CAPEX e Giro'!H5 -> 35000 | H17: ='CAPEX e Giro'!I5 -> 35000 | I17: ='CAPEX e Giro'!J5 -> 35000 | J17: ='CAPEX e Giro'!K5 -> 35000 | ... N17: ='CAPEX e Giro'!O5 -> 35000 | O17: =sum(C17:N17) -> 420000 | P17: =O17/$O$7 -> 0.016102325
B18: (=) Geração de Caixa | C18: =C15-C16-C17 -> 158202.63 | D18: =D15-D16-D17 -> 230892.11 | E18: =E15-E16-E17 -> 231398.53 | F18: =F15-F16-F17 -> 256868.34 | G18: =G15-G16-G17 -> 280254.86 | H18: =H15-H16-H17 -> 353023.08 | I18: =I15-I16-I17 -> 337547.94 | J18: =J15-J16-J17 -> 481493.03 | ... O18: =O15-O16-O17 -> 4594256.2 | P18: =O18/$O$7 -> 0.17613859
B19: (%) Margem Geração | C19: =C18/C7 -> 0.11159761 | D19: =D18/D7 -> 0.14357698 | E19: =E18/E7 -> 0.13903955 | F19: =F18/F7 -> 0.14137958 | G19: =G18/G7 -> 0.14093555 | H19: =H18/H7 -> 0.1711799 | I19: =I18/I7 -> 0.15099773 | J19: =J18/J7 -> 0.19967905 | ... N19: =N18/N7 -> 0.21182439
B21: Métricas Gerais
B22: Receita Total | C22: =C7-C8 -> 1332559.7 | D22: =D7-D8 -> 1511653 | E22: =E7-E8 -> 1564408.3 | F22: =F7-F8 -> 1707857.9 | G22: =G7-G8 -> 1869220.1 | H22: =H7-H8 -> 1938555.3 | I22: =I7-I8 -> 2101323.3 | J22: =J7-J8 -> 2266654.6 | ... N22: =N7-N8 -> 2734830.9
B23: Despesa Total | C23: =C9+C11+C13+C14+C16+C17 -> 1174357 | D23: =D9+D11+D13+D14+D16+D17 -> 1280760.9 | E23: =E9+E11+E13+E14+E16+E17 -> 1333009.8 | F23: =F9+F11+F13+F14+F16+F17 -> 1450989.6 | G23: =G9+G11+G13+G14+G16+G17 -> 1588965.3 | H23: =H9+H11+H13+H14+H16+H17 -> 1585532.2 | I23: =I9+I11+I13+I14+I16+I17 -> 1763775.4 | J23: =J9+J11+J13+J14+J16+J17 -> 1785161.6 | ... N23: =N9+N11+N13+N14+N16+N17 -> 2118550.2
B24: Vendas MRR | C24: =CAC!Q7 -> 215000 | D24: =CAC!R7 -> 215000 | E24: =CAC!S7 -> 215000 | F24: =CAC!T7 -> 240000 | G24: =CAC!U7 -> 240000 | H24: =CAC!V7 -> 240000 | I24: =CAC!W7 -> 270000 | J24: =CAC!X7 -> 270000 | ... N24: =CAC!AB7 -> 300000
B25: Vendas Pontual | C25: =CAC!Q38 -> 270000 | D25: =CAC!R38 -> 270000 | E25: =CAC!S38 -> 270000 | F25: =CAC!T38 -> 325000 | G25: =CAC!U38 -> 325000 | H25: =CAC!V38 -> 325000 | I25: =CAC!W38 -> 380000 | J25: =CAC!X38 -> 380000 | ... N25: =CAC!AB38 -> 435000
B26: Numero de Colaboradores | C26: =CSV!D7+count('SG&A'!C20:C22)+count('SG&A'!C28:C37)+count(CAC!C21:C38)+count(CAC!C44:C59)+count(CAC!C66:C71)+count(CAC!C77:C86) -> 110 | D26: =CSV!E7+count('SG&A'!D20:D22)+count('SG&A'!D28:D37)+count(CAC!D21:D38)+count(CAC!D44:D59)+count(CAC!D66:D71)+count(CAC!D77:D86) -> 118 | E26: =CSV!F7+count('SG&A'!E20:E22)+count('SG&A'!E28:E37)+count(CAC!E21:E38)+count(CAC!E44:E59)+count(CAC!E66:E71)+count(CAC!E77:E86) -> 123 | F26: =CSV!G7+count('SG&A'!F20:F22)+count('SG&A'!F28:F37)+count(CAC!F21:F38)+count(CAC!F44:F59)+count(CAC!F66:F71)+count(CAC!F77:F86) -> 135 | G26: =CSV!H7+count('SG&A'!G20:G22)+count('SG&A'!G28:G37)+count(CAC!G21:G38)+count(CAC!G44:G59)+count(CAC!G66:G71)+count(CAC!G77:G86) -> 139 | H26: =CSV!I7+count('SG&A'!H20:H22)+count('SG&A'!H28:H37)+count(CAC!H21:H38)+count(CAC!H44:H59)+count(CAC!H66:H71)+count(CAC!H77:H86) -> 141 | I26: =CSV!J7+count('SG&A'!I20:I22)+count('SG&A'!I28:I37)+count(CAC!I21:I38)+count(CAC!I44:I59)+count(CAC!I66:I71)+count(CAC!I77:I86) -> 147 | J26: =CSV!K7+count('SG&A'!J20:J22)+count('SG&A'!J28:J37)+count(CAC!J21:J38)+count(CAC!J44:J59)+count(CAC!J66:J71)+count(CAC!J77:J86) -> 152 | ... N26: =CSV!O7+count('SG&A'!N20:N22)+count('SG&A'!N28:N37)+count(CAC!N21:N38)+count(CAC!N44:N59)+count(CAC!N66:N71)+count(CAC!N77:N86) -> 169
B27: Receita Cabeça | C27: =C7/C26 -> 12887.424 | D27: =D7/D26 -> 13628.318 | E27: =E7/E26 -> 13530.603 | F27: =F7/F26 -> 13458.297 | G27: =G7/G26 -> 14305.986 | H27: =H7/H26 -> 14626.19 | I27: =I7/I26 -> 15207.145 | J27: =J7/J26 -> 15864.044 | ... N27: =N7/N26 -> 17215.352
B28: MRR Cabeça | C28: =C4/C26 -> 10516.818 | D28: =D4/D26 -> 10743.504 | E28: =E4/E26 -> 11127.134 | F28: =F4/F26 -> 11003.408 | G28: =G4/G26 -> 11451.573 | H28: =H4/H26 -> 11975.245 | I28: =I4/I26 -> 12289.413 | J28: =J4/J26 -> 12591.807 | ... N28: =N4/N26 -> 13830.698
B29: Numero de Clientes | C29: =C30/1.38 -> 300.66977 | D29: =D30/1.38 -> 330.2517 | E29: =E30/1.38 -> 352.00541 | F29: =F30/1.38 -> 377.78291 | G29: =G30/1.38 -> 402.43492 | H29: =H30/1.38 -> 423.7875 | I29: =I30/1.38 -> 449.22341 | J29: =J30/1.38 -> 474.6896 | K29: =K30/1.37 -> 500.42409 | L29: =L30/1.4 -> 515.46212 | M29: =M30/1.4 -> 541.19276 | N29: =N30/1.4 -> 563.56566
B30: Numero de Contratos | C30: =CSV!C12+CSV!C85+CSV!C141+CSV!C202+CSV!C225+CAC!Q42+CAC!Q47+CAC!Q52+CAC!Q57+CAC!Q62+CAC!Q67 -> 414.92429 | D30: =CSV!D12+CSV!D85+CSV!D141+CSV!D202+CSV!D225+CAC!R42+CAC!R47+CAC!R52+CAC!R57+CAC!R62+CAC!R67 -> 455.74735 | E30: =CSV!E12+CSV!E85+CSV!E141+CSV!E202+CSV!E225+CAC!S42+CAC!S47+CAC!S52+CAC!S57+CAC!S62+CAC!S67 -> 485.76747 | F30: =CSV!F12+CSV!F85+CSV!F141+CSV!F202+CSV!F225+CAC!T42+CAC!T47+CAC!T52+CAC!T57+CAC!T62+CAC!T67 -> 521.34042 | G30: =CSV!G12+CSV!G85+CSV!G141+CSV!G202+CSV!G225+CAC!U42+CAC!U47+CAC!U52+CAC!U57+CAC!U62+CAC!U67 -> 555.36019 | H30: =CSV!H12+CSV!H85+CSV!H141+CSV!H202+CSV!H225+CAC!V42+CAC!V47+CAC!V52+CAC!V57+CAC!V62+CAC!V67 -> 584.82675 | I30: =CSV!I12+CSV!I85+CSV!I141+CSV!I202+CSV!I225+CAC!W42+CAC!W47+CAC!W52+CAC!W57+CAC!W62+CAC!W67 -> 619.9283 | J30: =CSV!J12+CSV!J85+CSV!J141+CSV!J202+CSV!J225+CAC!X42+CAC!X47+CAC!X52+CAC!X57+CAC!X62+CAC!X67 -> 655.07165 | ... N30: =CSV!N12+CSV!N85+CSV!N141+CSV!N202+CSV!N225+CAC!AB42+CAC!AB47+CAC!AB52+CAC!AB57+CAC!AB62+CAC!AB67 -> 788.99192
B31: Ticket Medio Cliente | C31: =C7/C29 -> 4714.8626 | D31: =D7/D29 -> 4869.442 | E31: =E7/E29 -> 4727.9504 | F31: =F7/F29 -> 4809.2967 | G31: =G7/G29 -> 4941.2512 | H31: =H7/H29 -> 4866.3372 | I31: =I7/I29 -> 4976.2552 | J31: =J7/J29 -> 5079.8137 | ... N31: =N7/N29 -> 5162.4766
B32: Ticket Medio Contratos | C32: =C7/C30 -> 3416.5671 | D32: =D7/D30 -> 3528.5811 | E32: =E7/E30 -> 3426.051 | F32: =F7/F30 -> 3484.9976 | G32: =G7/G30 -> 3580.6168 | H32: =H7/H30 -> 3526.3313 | I32: =I7/I30 -> 3605.9821 | J32: =J7/J30 -> 3681.0244 | ... N32: =N7/N30 -> 3687.4833
B33: Churn Mês | C33: =Revenue!D32 -> 104116.5 | D33: =Revenue!E32 -> 114096.01 | E33: =Revenue!F32 -> 123177.37 | F33: =Revenue!G32 -> 133691.41 | G33: =Revenue!H32 -> 143259.18 | H33: =Revenue!I32 -> 151965.86 | I33: =Revenue!J32 -> 162588.93 | J33: =Revenue!K32 -> 172255.93 | ... N33: =Revenue!O32 -> 210364.91
B34: Aliquota Imposto Efetiva | C34: =(C16+C9)/C7 -> 0.16412118 | D34: =(D16+D9)/D7 -> 0.17854206 | E34: =(E16+E9)/E7 -> 0.17568937 | F34: =(F16+F9)/F7 -> 0.17655463 | G34: =(G16+G9)/G7 -> 0.17508083 | H34: =(H16+H9)/H7 -> 0.19018993 | I34: =(I16+I9)/I7 -> 0.17880883 | J34: =(J16+J9)/J7 -> 0.20303207 | ... O34: =(O16+O9)/O7 -> 0.19190571
B35: Geracao de caixa | C35: =C18 -> 158202.63 | D35: =D18 -> 230892.11 | E35: =E18 -> 231398.53 | F35: =F18 -> 256868.34 | G35: =G18 -> 280254.86 | H35: =H18 -> 353023.08 | I35: =I18 -> 337547.94 | J35: =J18 -> 481493.03 | ... N35: =N18 -> 616280.72
B36: Margem de geração | C36: =C19 -> 0.11159761 | D36: =D19 -> 0.14357698 | E36: =E19 -> 0.13903955 | F36: =F19 -> 0.14137958 | G36: =G19 -> 0.14093555 | H36: =H19 -> 0.1711799 | I36: =I19 -> 0.15099773 | J36: =J19 -> 0.19967905 | ... N36: =N19 -> 0.21182439 | O36: =P18 -> 0.17613859
B37: Saldo de Caixa | C37: =535000+C35 -> 693202.63 | D37: =C37+D35 -> 924094.74 | E37: =D37+E35 -> 1155493.3 | F37: =E37+F35 -> 1412361.6 | G37: =F37+G35 -> 1692616.5 | H37: =G37+H35 -> 2045639.5 | I37: =H37+I35 -> 2383187.5 | J37: =I37+J35 -> 2864680.5 | K37: =J37+K35 -> 3360111.3 | ... N37: =M37+N35 -> 5129256.2
B39: Numero de Colaboradores | C39: =CSV!D7+count('SG&A'!C20:C22)+count('SG&A'!C28:C37)+count(CAC!C21:C38)+count(CAC!C44:C59)+count(CAC!C66:C71)+count(CAC!C77:C86) -> 110 | D39: =CSV!E7+count('SG&A'!D20:D22)+count('SG&A'!D28:D37)+count(CAC!D21:D38)+count(CAC!D44:D59)+count(CAC!D66:D71)+count(CAC!D77:D86) -> 118 | E39: =CSV!F7+count('SG&A'!E20:E22)+count('SG&A'!E28:E37)+count(CAC!E21:E38)+count(CAC!E44:E59)+count(CAC!E66:E71)+count(CAC!E77:E86) -> 123 | F39: =CSV!G7+count('SG&A'!F20:F22)+count('SG&A'!F28:F37)+count(CAC!F21:F38)+count(CAC!F44:F59)+count(CAC!F66:F71)+count(CAC!F77:F86) -> 135 | G39: =CSV!H7+count('SG&A'!G20:G22)+count('SG&A'!G28:G37)+count(CAC!G21:G38)+count(CAC!G44:G59)+count(CAC!G66:G71)+count(CAC!G77:G86) -> 139 | H39: =CSV!I7+count('SG&A'!H20:H22)+count('SG&A'!H28:H37)+count(CAC!H21:H38)+count(CAC!H44:H59)+count(CAC!H66:H71)+count(CAC!H77:H86) -> 141 | I39: =CSV!J7+count('SG&A'!I20:I22)+count('SG&A'!I28:I37)+count(CAC!I21:I38)+count(CAC!I44:I59)+count(CAC!I66:I71)+count(CAC!I77:I86) -> 147 | J39: =CSV!K7+count('SG&A'!J20:J22)+count('SG&A'!J28:J37)+count(CAC!J21:J38)+count(CAC!J44:J59)+count(CAC!J66:J71)+count(CAC!J77:J86) -> 152 | ... N39: =CSV!O7+count('SG&A'!N20:N22)+count('SG&A'!N28:N37)+count(CAC!N21:N38)+count(CAC!N44:N59)+count(CAC!N66:N71)+count(CAC!N77:N86) -> 169
B40: Pessoas em CSV | C40: =CSV!D7 -> 73 | D40: =CSV!E7 -> 80 | E40: =CSV!F7 -> 83 | F40: =CSV!G7 -> 93 | G40: =CSV!H7 -> 97 | H40: =CSV!I7 -> 98 | I40: =CSV!J7 -> 104 | J40: =CSV!K7 -> 108 | ... N40: =CSV!O7 -> 122
B41: Pessoas em CAC | C41: =CAC!C5 -> 24 | D41: =CAC!D5 -> 25 | E41: =CAC!E5 -> 27 | F41: =CAC!F5 -> 30 | G41: =CAC!G5 -> 30 | H41: =CAC!H5 -> 30 | I41: =CAC!I5 -> 30 | J41: =CAC!J5 -> 31 | ... N41: =CAC!N5 -> 34
B42: Pessoas em SGEA | C42: ='SG&A'!C5 -> 12 | D42: ='SG&A'!D5 -> 12 | E42: ='SG&A'!E5 -> 12 | F42: ='SG&A'!F5 -> 11 | G42: ='SG&A'!G5 -> 11 | H42: ='SG&A'!H5 -> 12 | I42: ='SG&A'!I5 -> 12 | J42: ='SG&A'!J5 -> 12 | ... N42: ='SG&A'!N5 -> 12
B45: Despesa Total | C45: =C23 -> 1174357 | D45: =D23 -> 1280760.9 | E45: =E23 -> 1333009.8 | F45: =F23 -> 1450989.6 | G45: =G23 -> 1588965.3 | H45: =H23 -> 1585532.2 | I45: =I23 -> 1763775.4 | J45: =J23 -> 1785161.6 | ... N45: =N23 -> 2118550.2
B46: Saldo de Caixa | C46: 642014.04 | D46: =C46+D35 -> 872906.15 | E46: =D46+E35 -> 1104304.7 | F46: =E46+F35 -> 1361173 | G46: =F46+G35 -> 1641427.9 | H46: =G46+H35 -> 1994451 | I46: =H46+I35 -> 2331998.9 | J46: =I46+J35 -> 2813491.9 | K46: =J46+K35 -> 3308922.7 | ... N46: =M46+N35 -> 5078067.6
B47: Delta 1x Caixa | C47: =C46-C45 -> -532343 | D47: =D46-D45 -> -407854.76 | E47: =E46-E45 -> -228705.09 | F47: =F46-F45 -> -89816.547 | G47: =G46-G45 -> 52462.617 | H47: =H46-H45 -> 408918.75 | I47: =I46-I45 -> 568223.52 | J47: =J46-J45 -> 1028330.3 | ... N47: =N46-N45 -> 2959517.5
B48: Delta 1,5x Caixa | C48: =C46-(C45*1.5) -> -1119521.5 | D48: =D46-(D45*1.5) -> -1048235.2 | E48: =E46-(E45*1.5) -> -895209.98 | F48: =F46-(F45*1.5) -> -815311.33 | G48: =G46-(G45*1.5) -> -742020.01 | H48: =H46-(H45*1.5) -> -383847.35 | I48: =I46-(I45*1.5) -> -313664.17 | J48: =J46-(J45*1.5) -> 135749.49 | ... N48: =N46-(N45*1.5) -> 1900242.4
B49: Delta 2x Caixa | C49: =C46-(C45*2) -> -1706700 | D49: =D46-(D45*2) -> -1688615.7 | E49: =E46-(E45*2) -> -1561714.9 | F49: =F46-(F45*2) -> -1540806.1 | G49: =G46-(G45*2) -> -1536502.6 | H49: =H46-(H45*2) -> -1176613.4 | I49: =I46-(I45*2) -> -1195551.9 | J49: =J46-(J45*2) -> -756831.32 | ... N49: =N46-(N45*2) -> 840967.3
B50: Delta 3x Caixa | C50: =C46-(C45*3) -> -2881057.1 | D50: =D46-(D45*3) -> -2969376.6 | E50: =E46-(E45*3) -> -2894724.6 | F50: =F46-(F45*3) -> -2991795.7 | G50: =G46-(G45*3) -> -3125467.9 | H50: =H46-(H45*3) -> -2762145.6 | I50: =I46-(I45*3) -> -2959327.2 | J50: =J46-(J45*3) -> -2541992.9 | ... N50: =N46-(N45*3) -> -1277582.9
B51: x Caixa | C51: =C46/C45 -> 0.54669408 | D51: =D46/D45 -> 0.68155277 | E51: =E46/E45 -> 0.82842954 | F51: =F46/F45 -> 0.9380998 | G51: =G46/G45 -> 1.0330168 | H51: =H46/H45 -> 1.2579063 | I51: =I46/I45 -> 1.3221632 | J51: =J46/J45 -> 1.5760432 | ... N51: =N46/N45 -> 2.3969542

Sheet BP ORÇADO X REALIZADO
B2: Trimestre | C2: 1 Trimestre | I2: 2 Trimestre | O2: 3 Trimestre | U2: 4 Trimestre | AD2: 1 Trimestre
C3: Janeiro | D3: Realizado Jan | E3: Feveiro | F3: Realizado Fev | G3: Março | H3: Realizado Mar | I3: Abril | J3: Realizado Abr | K3: Maio | L3: Realizado Mai | M3: Junho | N3: Realizado Jun | O3: Julho | P3: Realizado Jul | Q3: Agosto | R3: Realizado Ago | S3: Setembro | T3: Realizado Set | U3: Outubro | V3: Realizado Out | W3: Novembro | X3: Realizado Nov | Y3: Dezembro | Z3: Realizado Dez | AA3: Total | AD3: Inadimpência | AE3: 0.06
B4: (+) MRR Ativo | C4: =Revenue!D5 -> 1156850 | D4: 1119046 | E4: =Revenue!E5 -> 1267733.5 | G4: =Revenue!F5 -> 1368637.5 | I4: =Revenue!G5 -> 1485460.1 | K4: =Revenue!H5 -> 1591768.7 | M4: =Revenue!I5 -> 1688509.5 | O4: =Revenue!J5 -> 1806543.7 | Q4: =Revenue!K5 -> 1913954.7 | S4: =Revenue!L5 -> 2011698.8 | U4: =Revenue!M5 -> 2130645.9 | W4: =Revenue!N5 -> 2238887.8 | Y4: =Revenue!O5 -> 2337387.9 | AA4: =C4+E4+G4+I4+K4+M4+O4+Q4+S4+U4+W4+Y4 -> 20998078
B5: (+) Receita Pontual | C5: =Revenue!D37 -> 240000 | D5: =D7-D4 -> 326472 | E5: =Revenue!E37 -> 280000 | G5: =Revenue!F37 -> 270000 | I5: =Revenue!G37 -> 288333.33 | K5: =Revenue!H37 -> 306666.67 | M5: =Revenue!I37 -> 325000 | O5: =Revenue!J37 -> 343333.33 | Q5: =Revenue!K37 -> 361666.67 | S5: =Revenue!L37 -> 380000 | U5: =Revenue!M37 -> 398333.33 | W5: =Revenue!N37 -> 416666.67 | Y5: =Revenue!O37 -> 435000 | AA5: =C5+E5+G5+I5+K5+M5+O5+Q5+S5+U5+W5+Y5 -> 4045000 | AD5: 2 Trimestre
B6: (+) Outras Receitas | C6: ='Outras Receitas'!C15 -> 20766.667 | E6: ='Outras Receitas'!D15 -> 60408 | G6: ='Outras Receitas'!E15 -> 25626.667 | I6: ='Outras Receitas'!F15 -> 43076.667 | K6: ='Outras Receitas'!G15 -> 90096.667 | M6: ='Outras Receitas'!H15 -> 48783.333 | O6: ='Outras Receitas'!I15 -> 85573.333 | Q6: ='Outras Receitas'!J15 -> 135713.33 | S6: ='Outras Receitas'!K15 -> 79046.667 | U6: ='Outras Receitas'!L15 -> 137006.67 | W6: ='Outras Receitas'!M15 -> 177006.67 | Y6: ='Outras Receitas'!N15 -> 137006.67 | AA6: =C6+E6+G6+I6+K6+M6+O6+Q6+S6+U6+W6+Y6 -> 1040111.3 | AD6: Inadimpência | AE6: 0.06
B7: (=) Receita Total Faturavel | C7: =C4+C5+C6 -> 1417616.7 | D7: 1445518 | E7: =E4+E5+E6 -> 1608141.5 | G7: =G4+G5+G6 -> 1664264.2 | I7: =I4+I5+I6 -> 1816870.1 | K7: =K4+K5+K6 -> 1988532 | M7: =M4+M5+M6 -> 2062292.9 | O7: =O4+O5+O6 -> 2235450.3 | Q7: =Q4+Q5+Q6 -> 2411334.7 | S7: =S4+S5+S6 -> 2470745.5 | U7: =U4+U5+U6 -> 2665985.9 | W7: =W4+W5+W6 -> 2832561.1 | Y7: =Y4+Y5+Y6 -> 2909394.5 | AA7: =AA4+AA5+AA6 -> 26083189
B8: (-) Inadimplência | C8: =C7*$AE$3 -> 85057 | D8: 283761 | E8: =E7*$AE$3 -> 96488.49 | G8: =G7*$AE$3 -> 99855.849 | I8: =I7*$AE$6 -> 109012.21 | K8: =K7*$AE$6 -> 119311.92 | M8: =M7*$AE$6 -> 123737.57 | O8: =O7*$AE$9 -> 134127.02 | Q8: =Q7*$AE$9 -> 144680.08 | S8: =S7*$AE$9 -> 148244.73 | U8: =U7*$AE$12 -> 159959.15 | W8: =W7*$AE$12 -> 169953.67 | Y8: =Y7*$AE$12 -> 174563.67 | AA8: =C8+E8+G8+I8+K8+M8+O8+Q8+S8+U8+W8+Y8 -> 1564991.4 | AB8: =AA8/$AA$7 -> 0.06 | AD8: 3 Trimestre
B9: (-) Impostos Sob Receita | C9: ='Tributário'!F11+'Tributário'!F12+'Tributário'!F13 -> 133132.3 | D9: 104303 | E9: ='Tributário'!G11+'Tributário'!G12+'Tributário'!G13 -> 150146.17 | G9: ='Tributário'!H11+'Tributário'!H12+'Tributário'!H13 -> 155157.92 | I9: ='Tributário'!I11+'Tributário'!I12+'Tributário'!I13 -> 170420.41 | K9: ='Tributário'!J11+'Tributário'!J12+'Tributário'!J13 -> 185749.82 | M9: ='Tributário'!K11+'Tributário'!K12+'Tributário'!K13 -> 192336.66 | O9: ='Tributário'!L11+'Tributário'!L12+'Tributário'!L13 -> 207799.63 | Q9: ='Tributário'!M11+'Tributário'!M12+'Tributário'!M13 -> 223506.1 | S9: ='Tributário'!N11+'Tributário'!N12+'Tributário'!N13 -> 228811.48 | U9: ='Tributário'!O11+'Tributário'!O12+'Tributário'!O13 -> 246246.46 | W9: ='Tributário'!P11+'Tributário'!P12+'Tributário'!P13 -> 261121.62 | Y9: ='Tributário'!Q11+'Tributário'!Q12+'Tributário'!Q13 -> 267982.85 | AA9: =C9+E9+G9+I9+K9+M9+O9+Q9+S9+U9+W9+Y9 -> 2422411.4 | AB9: =AA9/$AA$7 -> 0.092872516 | AD9: Inadimpência | AE9: 0.06
B10: (=) Receita Líquida | C10: =C7-C8-C9 -> 1199427.4 | D10: =D7-D8-D9 -> 1057454 | E10: =E7-E8-E9 -> 1361506.8 | G10: =G7-G8-G9 -> 1409250.4 | I10: =I7-I8-I9 -> 1537437.5 | K10: =K7-K8-K9 -> 1683470.3 | M10: =M7-M8-M9 -> 1746218.6 | O10: =O7-O8-O9 -> 1893523.7 | Q10: =Q7-Q8-Q9 -> 2043148.5 | S10: =S7-S8-S9 -> 2093689.3 | U10: =U7-U8-U9 -> 2259780.3 | W10: =W7-W8-W9 -> 2401485.8 | Y10: =Y7-Y8-Y9 -> 2466848 | AA10: =C10+E10+G10+I10+K10+M10+O10+Q10+S10+U10+W10+Y10 -> 22095787 | AC10: =AA10/$AA$7 -> 0.84712748
B11: (-) CSV - Salários | C11: =CSV!D4 -> 345754.4 | D11: 349675 | E11: =CSV!E4 -> 380706.3 | G11: =CSV!F4 -> 399437.54 | I11: =CSV!G4 -> 465597.96 | K11: =CSV!H4 -> 488400.64 | M11: =CSV!I4 -> 495996.08 | O11: =CSV!J4 -> 557632.94 | Q11: =CSV!K4 -> 583914.17 | S11: =CSV!L4 -> 598990.1 | U11: =CSV!M4 -> 647359.19 | W11: =CSV!N4 -> 662874.26 | Y11: =CSV!O4 -> 687435.48 | AA11: =C11+E11+G11+I11+K11+M11+O11+Q11+S11+U11+W11+Y11 -> 6314099.1 | AB11: =AA11/$AA$7 -> 0.24207542 | AD11: 4 Trimestre
B12: (-) CSV - Benefício | C12: =(CSV!D7*400) -> 29200 | D12: 37241 | E12: =(CSV!E7*400) -> 32000 | G12: =(CSV!F7*400) -> 33200 | I12: =(CSV!G7*400) -> 37200 | K12: =(CSV!H7*400) -> 38800 | M12: =(CSV!I7*400) -> 39200 | O12: =(CSV!J7*400) -> 41600 | Q12: =(CSV!K7*400) -> 43200 | S12: =(CSV!L7*400) -> 44000 | U12: =(CSV!M7*400) -> 46400 | W12: =(CSV!N7*400) -> 47600 | Y12: =(CSV!O7*400) -> 48800 | AA12: =C12+E12+G12+I12+K12+M12+O12+Q12+S12+U12+W12+Y12 -> 481200 | AB12: =AA12/$AA$7 -> 0.018448664 | AD12: Inadimpência | AE12: 0.06
B13: (-) CSV - Stack Tecnologia | C13: ='SG&A'!C42 -> 41540 | E13: ='SG&A'!D42 -> 41932 | G13: ='SG&A'!E42 -> 42177 | I13: ='SG&A'!F42 -> 44635 | K13: ='SG&A'!G42 -> 44831 | M13: ='SG&A'!H42 -> 44929 | O13: ='SG&A'!I42 -> 62293 | Q13: ='SG&A'!J42 -> 47538 | S13: ='SG&A'!K42 -> 47685 | U13: ='SG&A'!L42 -> 49098 | W13: ='SG&A'!M42 -> 49245 | Y13: ='SG&A'!N42 -> 49441 | AA13: =C13+E13+G13+I13+K13+M13+O13+Q13+S13+U13+W13+Y13 -> 565344 | AB13: =AA13/$AA$7 -> 0.02167465
B14: (=) Margem Bruta | C14: =C10-C11-C12-C13 -> 782932.97 | D14: =D10-D11-D12 -> 670538 | E14: =E10-E11-E12-E13 -> 906868.54 | G14: =G10-G11-G12-G13 -> 934435.85 | I14: =I10-I11-I12-I13 -> 990004.53 | K14: =K10-K11-K12-K13 -> 1111438.6 | M14: =M10-M11-M12-M13 -> 1166093.5 | O14: =O10-O11-O12-O13 -> 1231997.7 | Q14: =Q10-Q11-Q12-Q13 -> 1368496.4 | S14: =S10-S11-S12-S13 -> 1403014.2 | U14: =U10-U11-U12-U13 -> 1516923.1 | W14: =W10-W11-W12-W13 -> 1641766.6 | Y14: =Y10-Y11-Y12-Y13 -> 1681171.6 | AA14: =C14+E14+G14+I14+K14+M14+O14+Q14+S14+U14+W14+Y14 -> 14735144 | AC14: =AA14/$AA$7 -> 0.56492875
B15: (-) CAC | C15: =CAC!C6 -> 262495.71 | D15: 236184 | E15: =CAC!D6 -> 285895.71 | G15: =CAC!E6 -> 311895.71 | I15: =CAC!F6 -> 337573.77 | K15: =CAC!G6 -> 422573.77 | M15: =CAC!H6 -> 362573.77 | O15: =CAC!I6 -> 453925.18 | Q15: =CAC!J6 -> 371925.18 | S15: =CAC!K6 -> 384925.18 | U15: =CAC!L6 -> 420776.58 | W15: =CAC!M6 -> 405776.58 | Y15: =CAC!N6 -> 428776.58 | AA15: =C15+E15+G15+I15+K15+M15+O15+Q15+S15+U15+W15+Y15 -> 4449113.7 | AB15: =AA15/$AA$7 -> 0.17057399
B16: (-) SG&A | C16: ='SG&A'!C6-C12-C13 -> 227706 | D16: 286179 | E16: ='SG&A'!D6-E12-E13 -> 218106 | G16: ='SG&A'!E6-G12-G13 -> 218906 | I16: ='SG&A'!F6-I12-I13 -> 210206 | K16: ='SG&A'!G6-K12-K13 -> 211206 | M16: ='SG&A'!H6-M12-M13 -> 215606 | O16: ='SG&A'!I6-O12-O13 -> 213606 | Q16: ='SG&A'!J6-Q12-Q13 -> 214006 | S16: ='SG&A'!K6-S12-S13 -> 214406 | U16: ='SG&A'!L6-U12-U13 -> 234506 | W16: ='SG&A'!M6-W12-W13 -> 244806 | Y16: ='SG&A'!N6-Y12-Y13 -> 265606 | AA16: =C16+E16+G16+I16+K16+M16+O16+Q16+S16+U16+W16+Y16 -> 2688672 | AB16: =AA16/$AA$7 -> 0.10308065
B17: (-) Bônus | C17: =Overview!C17 -> 54000 | E17: =Overview!D17 -> 23000 | G17: =Overview!E17 -> 23000
B18: (=) EBITDA | C18: =C14-C15-C16-C17 -> 238731.26 | D18: =D14-D15-D16 -> 148175 | E18: =E14-E15-E16-E17 -> 379866.83 | G18: =G14-G15-G16-G17 -> 380634.14 | I18: =I14-I15-I16-I17 -> 442224.76 | K18: =K14-K15-K16-K17 -> 477658.87 | M18: =M14-M15-M16-M17 -> 587913.76 | O18: =O14-O15-O16-O17 -> 564466.57 | Q18: =Q14-Q15-Q16 -> 782565.2 | S18: =S14-S15-S16 -> 803682.99 | U18: =U14-U15-U16 -> 861640.54 | W18: =W14-W15-W16 -> 991183.99 | Y18: =Y14-Y15-Y16 -> 986788.97 | AA18: =C18+E18+G18+I18+K18+M18+O18+Q18+S18+U18+W18+Y18 -> 7497357.9 | AC18: =AA18/$AA$7 -> 0.28744023
B19: (-) IR + CSLL | C19: ='Tributário'!F14 -> 99528.628 | E19: ='Tributário'!G14 -> 136974.72 | G19: ='Tributário'!H14 -> 137235.61 | I19: ='Tributário'!I14 -> 150356.42 | K19: ='Tributário'!J14 -> 162404.02 | M19: ='Tributário'!K14 -> 199890.68 | O19: ='Tributário'!L14 -> 191918.63 | Q19: ='Tributário'!M14 -> 266072.17 | S19: ='Tributário'!N14 -> 273252.22 | U19: ='Tributário'!O14 -> 292957.78 | W19: ='Tributário'!P14 -> 337002.56 | Y19: ='Tributário'!Q14 -> 335508.25 | AA19: =C19+E19+G19+I19+K19+M19+O19+Q19+S19+U19+W19+Y19 -> 2583101.7 | AB19: =AA19/$AA$7 -> 0.099033199
B20: (-) CAPEX | C20: ='CAPEX e Giro'!D5 -> 35000 | E20: ='CAPEX e Giro'!E5 -> 35000 | G20: ='CAPEX e Giro'!F5 -> 35000 | I20: ='CAPEX e Giro'!G5 -> 35000 | K20: ='CAPEX e Giro'!H5 -> 35000 | M20: ='CAPEX e Giro'!I5 -> 35000 | O20: ='CAPEX e Giro'!J5 -> 35000 | Q20: ='CAPEX e Giro'!K5 -> 35000 | S20: ='CAPEX e Giro'!L5 -> 35000 | U20: ='CAPEX e Giro'!M5 -> 35000 | W20: ='CAPEX e Giro'!N5 -> 35000 | Y20: ='CAPEX e Giro'!O5 -> 35000 | AA20: =C20+E20+G20+I20+K20+M20+O20+Q20+S20+U20+W20+Y20 -> 420000 | AB20: =AA20/$AA$7 -> 0.016102325
B21: (=) Geração de Caixa | C21: =C18-C19-C20 -> 104202.63 | E21: =E18-E19-E20 -> 207892.11 | G21: =G18-G19-G20 -> 208398.53 | I21: =I18-I19-I20 -> 256868.34 | K21: =K18-K19-K20 -> 280254.86 | M21: =M18-M19-M20 -> 353023.08 | O21: =O18-O19-O20 -> 337547.94 | Q21: =Q18-Q19-Q20 -> 481493.03 | S21: =S18-S19-S20 -> 495430.77 | U21: =U18-U19-U20 -> 533682.76 | W21: =W18-W19-W20 -> 619181.43 | Y21: =Y18-Y19-Y20 -> 616280.72 | AA21: =AA18-AA19-AA20 -> 4494256.2 | AB21: =AA21/$AA$7 -> 0.1723047
B22: (%) Margem Geração | C22: =C21/C7 -> 0.073505506 | E22: =E21/E7 -> 0.12927476 | G22: =G21/G7 -> 0.12521962 | I22: =I21/I7 -> 0.14137958 | K22: =K21/K7 -> 0.14093555 | M22: =M21/M7 -> 0.1711799 | O22: =O21/O7 -> 0.15099773 | Q22: =Q21/Q7 -> 0.19967905 | S22: =S21/S7 -> 0.20051874 | U22: =U21/U7 -> 0.20018214 | W22: =W21/W7 -> 0.2185942 | Y22: =Y21/Y7 -> 0.21182439
B24: Métricas Gerais
C25: Janeiro | D25: Realizado Jan | E25: Feveiro | G25: Março | I25: Abril | K25: Maio | M25: Junho | O25: Julho | Q25: Agosto | S25: Setembro | U25: Outubro | W25: Novembro | Y25: Dezembro
B26: Receita Total | C26: =C7-C8 -> 1332559.7 | E26: =E7-E8 -> 1511653 | G26: =G7-G8 -> 1564408.3 | I26: =I7-I8 -> 1707857.9 | K26: =K7-K8 -> 1869220.1 | M26: =M7-M8 -> 1938555.3 | O26: =O7-O8 -> 2101323.3 | Q26: =Q7-Q8 -> 2266654.6 | S26: =S7-S8 -> 2322500.7 | U26: =U7-U8 -> 2506026.8 | W26: =W7-W8 -> 2662607.4 | Y26: =Y7-Y8 -> 2734830.9
B27: Despesa Total | C27: =C9+C11+C15+C16+C19+C20+C12+C13 -> 1174357 | E27: =E9+E11+E15+E16+E19+E20+E12+E13 -> 1280760.9 | G27: =G9+G11+G15+G16+G19+G20+G12+G13 -> 1333009.8 | I27: =I9+I11+I15+I16+I19+I20+I12+I13 -> 1450989.6 | K27: =K9+K11+K15+K16+K19+K20+K12+K13 -> 1588965.3 | M27: =M9+M11+M15+M16+M19+M20+M12+M13 -> 1585532.2 | O27: =O9+O11+O15+O16+O19+O20+O12+O13 -> 1763775.4 | Q27: =Q9+Q11+Q15+Q16+Q19+Q20+Q12+Q13 -> 1785161.6 | S27: =S9+S11+S15+S16+S19+S20+S12+S13 -> 1827070 | U27: =U9+U11+U15+U16+U19+U20+U12+U13 -> 1972344 | W27: =W9+W11+W15+W16+W19+W20+W12+W13 -> 2043426 | Y27: =Y9+Y11+Y15+Y16+Y19+Y20+Y12+Y13 -> 2118550.2
B28: Vendas MRR | C28: =CAC!Q7 -> 215000 | E28: =CAC!R7 -> 215000 | G28: =CAC!S7 -> 215000 | I28: =CAC!T7 -> 240000 | K28: =CAC!U7 -> 240000 | M28: =CAC!V7 -> 240000 | O28: =CAC!W7 -> 270000 | Q28: =CAC!X7 -> 270000 | S28: =CAC!Y7 -> 270000 | U28: =CAC!Z7 -> 300000 | W28: =CAC!AA7 -> 300000 | Y28: =CAC!AB7 -> 300000
B29: Vendas Pontual | C29: =CAC!Q38 -> 270000 | E29: =CAC!R38 -> 270000 | G29: =CAC!S38 -> 270000 | I29: =CAC!T38 -> 325000 | K29: =CAC!U38 -> 325000 | M29: =CAC!V38 -> 325000 | O29: =CAC!W38 -> 380000 | Q29: =CAC!X38 -> 380000 | S29: =CAC!Y38 -> 380000 | U29: =CAC!Z38 -> 435000 | W29: =CAC!AA38 -> 435000 | Y29: =CAC!AB38 -> 435000
B30: Numero de Colaboradores | C30: =C42 -> 109 | E30: =E42 -> 117 | G30: =G42 -> 122 | I30: =I42 -> 134 | K30: =K42 -> 138 | M30: =M42 -> 140 | O30: =O42 -> 146 | Q30: =Q42 -> 151 | S30: =S42 -> 154 | U30: =U42 -> 161 | W30: =W42 -> 164 | Y30: =Y42 -> 168
B31: Receita Cabeça | C31: =C7/C30 -> 13005.657 | E31: =E7/E30 -> 13744.799 | G31: =G7/G30 -> 13641.509 | I31: =I7/I30 -> 13558.732 | K31: =K7/K30 -> 14409.652 | M31: =M7/M30 -> 14730.663 | O31: =O7/O30 -> 15311.304 | Q31: =Q7/Q30 -> 15969.104 | S31: =S7/S30 -> 16043.802 | U31: =U7/U30 -> 16558.919 | W31: =W7/W30 -> 17271.714 | Y31: =Y7/Y30 -> 17317.825
B32: MRR Cabeça | C32: =C4/C30 -> 10613.303 | E32: =E4/E30 -> 10835.329 | G32: =G4/G30 -> 11218.34 | I32: =I4/I30 -> 11085.523 | K32: =K4/K30 -> 11534.556 | M32: =M4/M30 -> 12060.782 | O32: =O4/O30 -> 12373.587 | Q32: =Q4/Q30 -> 12675.197 | S32: =S4/S30 -> 13062.979 | U32: =U4/U30 -> 13233.826 | W32: =W4/W30 -> 13651.755 | Y32: =Y4/Y30 -> 13913.023
B33: Numero de Clientes | C33: =C34/1.38 -> 300.66977 | E33: =E34/1.38 -> 330.2517 | G33: =G34/1.38 -> 352.00541 | I33: =I34/1.38 -> 377.78291 | K33: =K34/1.38 -> 402.43492 | M33: =M34/1.38 -> 423.7875 | O33: =O34/1.38 -> 449.22341 | Q33: =Q34/1.38 -> 474.6896 | S33: =S34/1.37 -> 500.42409 | U33: =U34/1.4 -> 515.46212 | W33: =W34/1.4 -> 541.19276 | Y33: =Y34/1.4 -> 563.56566
B34: Numero de Contratos | C34: =CSV!C12+CSV!C85+CSV!C141+CSV!C202+CSV!C225+CAC!Q42+CAC!Q47+CAC!Q52+CAC!Q57+CAC!Q62+CAC!Q67 -> 414.92429 | E34: =CSV!D12+CSV!D85+CSV!D141+CSV!D202+CSV!D225+CAC!R42+CAC!R47+CAC!R52+CAC!R57+CAC!R62+CAC!R67 -> 455.74735 | G34: =CSV!E12+CSV!E85+CSV!E141+CSV!E202+CSV!E225+CAC!S42+CAC!S47+CAC!S52+CAC!S57+CAC!S62+CAC!S67 -> 485.76747 | I34: =CSV!F12+CSV!F85+CSV!F141+CSV!F202+CSV!F225+CAC!T42+CAC!T47+CAC!T52+CAC!T57+CAC!T62+CAC!T67 -> 521.34042 | K34: =CSV!G12+CSV!G85+CSV!G141+CSV!G202+CSV!G225+CAC!U42+CAC!U47+CAC!U52+CAC!U57+CAC!U62+CAC!U67 -> 555.36019 | M34: =CSV!H12+CSV!H85+CSV!H141+CSV!H202+CSV!H225+CAC!V42+CAC!V47+CAC!V52+CAC!V57+CAC!V62+CAC!V67 -> 584.82675 | O34: =CSV!I12+CSV!I85+CSV!I141+CSV!I202+CSV!I225+CAC!W42+CAC!W47+CAC!W52+CAC!W57+CAC!W62+CAC!W67 -> 619.9283 | Q34: =CSV!J12+CSV!J85+CSV!J141+CSV!J202+CSV!J225+CAC!X42+CAC!X47+CAC!X52+CAC!X57+CAC!X62+CAC!X67 -> 655.07165 | S34: =CSV!K12+CSV!K85+CSV!K141+CSV!K202+CSV!K225+CAC!Y42+CAC!Y47+CAC!Y52+CAC!Y57+CAC!Y62+CAC!Y67 -> 685.581 | U34: =CSV!L12+CSV!L85+CSV!L141+CSV!L202+CSV!L225+CAC!Z42+CAC!Z47+CAC!Z52+CAC!Z57+CAC!Z62+CAC!Z67 -> 721.64697 | W34: =CSV!M12+CSV!M85+CSV!M141+CSV!M202+CSV!M225+CAC!AA42+CAC!AA47+CAC!AA52+CAC!AA57+CAC!AA62+CAC!AA67 -> 757.66986 | Y34: =CSV!N12+CSV!N85+CSV!N141+CSV!N202+CSV!N225+CAC!AB42+CAC!AB47+CAC!AB52+CAC!AB57+CAC!AB62+CAC!AB67 -> 788.99192
B35: Ticket Medio Cliente | C35: =C7/C33 -> 4714.8626 | E35: =E7/E33 -> 4869.442 | G35: =G7/G33 -> 4727.9504 | I35: =I7/I33 -> 4809.2967 | K35: =K7/K33 -> 4941.2512 | M35: =M7/M33 -> 4866.3372 | O35: =O7/O33 -> 4976.2552 | Q35: =Q7/Q33 -> 5079.8137 | S35: =S7/S33 -> 4937.3032 | U35: =U7/U33 -> 5172.0307 | W35: =W7/W33 -> 5233.9228 | Y35: =Y7/Y33 -> 5162.4766
B36: Ticket Medio Contratos | C36: =C7/C34 -> 3416.5671 | E36: =E7/E34 -> 3528.5811 | G36: =G7/G34 -> 3426.051 | I36: =I7/I34 -> 3484.9976 | K36: =K7/K34 -> 3580.6168 | M36: =M7/M34 -> 3526.3313 | O36: =O7/O34 -> 3605.9821 | Q36: =Q7/Q34 -> 3681.0244 | S36: =S7/S34 -> 3603.871 | U36: =U7/U34 -> 3694.3077 | W36: =W7/W34 -> 3738.5163 | Y36: =Y7/Y34 -> 3687.4833
B37: Churn Mês | C37: =Revenue!D32 -> 104116.5 | E37: =Revenue!E32 -> 114096.01 | G37: =Revenue!F32 -> 123177.37 | I37: =Revenue!G32 -> 133691.41 | K37: =Revenue!H32 -> 143259.18 | M37: =Revenue!I32 -> 151965.86 | O37: =Revenue!J32 -> 162588.93 | Q37: =Revenue!K32 -> 172255.93 | S37: =Revenue!L32 -> 181052.89 | U37: =Revenue!M32 -> 191758.13 | W37: =Revenue!N32 -> 201499.9 | Y37: =Revenue!O32 -> 210364.91
B38: Aliquota Imposto Efetiva | C38: =(C19+C9)/C7 -> 0.16412118 | E38: =(E19+E9)/E7 -> 0.17854206 | G38: =(G19+G9)/G7 -> 0.17568937 | I38: =(I19+I9)/I7 -> 0.17655463 | K38: =(K19+K9)/K7 -> 0.17508083 | M38: =(M19+M9)/M7 -> 0.19018993 | O38: =(O19+O9)/O7 -> 0.17880883 | Q38: =(Q19+Q9)/Q7 -> 0.20303207 | S38: =(S19+S9)/S7 -> 0.20320333 | U38: =(U19+U9)/U7 -> 0.20225322 | W38: =(W19+W9)/W7 -> 0.2111602 | Y38: =(Y19+Y9)/Y7 -> 0.20742841
B39: Geracao de caixa | C39: =C21 -> 104202.63 | E39: =E21 -> 207892.11 | G39: =G21 -> 208398.53 | I39: =I21 -> 256868.34 | K39: =K21 -> 280254.86 | M39: =M21 -> 353023.08 | O39: =O21 -> 337547.94 | Q39: =Q21 -> 481493.03 | S39: =S21 -> 495430.77 | U39: =U21 -> 533682.76 | W39: =W21 -> 619181.43 | Y39: =Y21 -> 616280.72
B40: Margem de geração | C40: =C22 -> 0.073505506 | E40: =E22 -> 0.12927476 | G40: =G22 -> 0.12521962 | I40: =I22 -> 0.14137958 | K40: =K22 -> 0.14093555 | M40: =M22 -> 0.1711799 | O40: =O22 -> 0.15099773 | Q40: =Q22 -> 0.19967905 | S40: =S22 -> 0.20051874 | U40: =U22 -> 0.20018214 | W40: =W22 -> 0.2185942 | Y40: =Y22 -> 0.21182439
B41: Saldo de Caixa | C41: =535000+C39 -> 639202.63 | E41: =C41+E39 -> 847094.74 | G41: =E41+G39 -> 1055493.3 | I41: =G41+I39 -> 1312361.6 | K41: =I41+K39 -> 1592616.5 | M41: =K41+M39 -> 1945639.5 | O41: =M41+O39 -> 2283187.5 | Q41: =O41+Q39 -> 2764680.5 | S41: =Q41+S39 -> 3260111.3 | U41: =S41+U39 -> 3793794 | W41: =U41+W39 -> 4412975.5 | Y41: =W41+Y39 -> 5029256.2
B42: Numero de Colaboradores | C42: =CSV!D7+count('SG&A'!C20:C22)+count('SG&A'!C28:C37)+count(CAC!C22:C38)+count(CAC!C44:C59)+count(CAC!C66:C71)+count(CAC!C77:C86) -> 109 | E42: =CSV!E7+count('SG&A'!D20:D22)+count('SG&A'!D28:D37)+count(CAC!D22:D38)+count(CAC!D44:D59)+count(CAC!D66:D71)+count(CAC!D77:D86) -> 117 | G42: =CSV!F7+count('SG&A'!E20:E22)+count('SG&A'!E28:E37)+count(CAC!E22:E38)+count(CAC!E44:E59)+count(CAC!E66:E71)+count(CAC!E77:E86) -> 122 | I42: =CSV!G7+count('SG&A'!F20:F22)+count('SG&A'!F28:F37)+count(CAC!F22:F38)+count(CAC!F44:F59)+count(CAC!F66:F71)+count(CAC!F77:F86) -> 134 | K42: =CSV!H7+count('SG&A'!G20:G22)+count('SG&A'!G28:G37)+count(CAC!G22:G38)+count(CAC!G44:G59)+count(CAC!G66:G71)+count(CAC!G77:G86) -> 138 | M42: =CSV!I7+count('SG&A'!H20:H22)+count('SG&A'!H28:H37)+count(CAC!H22:H38)+count(CAC!H44:H59)+count(CAC!H66:H71)+count(CAC!H77:H86) -> 140 | O42: =CSV!J7+count('SG&A'!I20:I22)+count('SG&A'!I28:I37)+count(CAC!I22:I38)+count(CAC!I44:I59)+count(CAC!I66:I71)+count(CAC!I77:I86) -> 146 | Q42: =CSV!K7+count('SG&A'!J20:J22)+count('SG&A'!J28:J37)+count(CAC!J22:J38)+count(CAC!J44:J59)+count(CAC!J66:J71)+count(CAC!J77:J86) -> 151 | S42: =CSV!L7+count('SG&A'!K20:K22)+count('SG&A'!K28:K37)+count(CAC!K22:K38)+count(CAC!K44:K59)+count(CAC!K66:K71)+count(CAC!K77:K86) -> 154 | U42: =CSV!M7+count('SG&A'!L20:L22)+count('SG&A'!L28:L37)+count(CAC!L22:L38)+count(CAC!L44:L59)+count(CAC!L66:L71)+count(CAC!L77:L86) -> 161 | W42: =CSV!N7+count('SG&A'!M20:M22)+count('SG&A'!M28:M37)+count(CAC!M22:M38)+count(CAC!M44:M59)+count(CAC!M66:M71)+count(CAC!M77:M86) -> 164 | Y42: =CSV!O7+count('SG&A'!N20:N22)+count('SG&A'!N28:N37)+count(CAC!N22:N38)+count(CAC!N44:N59)+count(CAC!N66:N71)+count(CAC!N77:N86) -> 168
B43: Pessoas em CSV | C43: =CSV!D7 -> 73 | E43: =CSV!E7 -> 80 | G43: =CSV!F7 -> 83 | I43: =CSV!G7 -> 93 | K43: =CSV!H7 -> 97 | M43: =CSV!I7 -> 98 | O43: =CSV!J7 -> 104 | Q43: =CSV!K7 -> 108 | S43: =CSV!L7 -> 110 | U43: =CSV!M7 -> 116 | W43: =CSV!N7 -> 119 | Y43: =CSV!O7 -> 122
B44: Pessoas em CAC | C44: =CAC!C5 -> 24 | E44: =CAC!D5 -> 25 | G44: =CAC!E5 -> 27 | I44: =CAC!F5 -> 30 | K44: =CAC!G5 -> 30 | M44: =CAC!H5 -> 30 | O44: =CAC!I5 -> 30 | Q44: =CAC!J5 -> 31 | S44: =CAC!K5 -> 32 | U44: =CAC!L5 -> 33 | W44: =CAC!M5 -> 33 | Y44: =CAC!N5 -> 34
B45: Pessoas em SGEA | C45: ='SG&A'!C5 -> 12 | E45: ='SG&A'!D5 -> 12 | G45: ='SG&A'!E5 -> 12 | I45: ='SG&A'!F5 -> 11 | K45: ='SG&A'!G5 -> 11 | M45: ='SG&A'!H5 -> 12 | O45: ='SG&A'!I5 -> 12 | Q45: ='SG&A'!J5 -> 12 | S45: ='SG&A'!K5 -> 12 | U45: ='SG&A'!L5 -> 12 | W45: ='SG&A'!M5 -> 12 | Y45: ='SG&A'!N5 -> 12

Sheet CAC
Q1: =Q11+Q16+Q22+Q27+Q32+Q42+Q47+Q52+Q57+Q62+Q67 -> 107.03938 | R1: =R11+R16+R22+R27+R32+R42+R47+R52+R57+R62+R67 -> 107.03938 | S1: =S11+S16+S22+S27+S32+S42+S47+S52+S57+S62+S67 -> 107.03938 | T1: =T11+T16+T22+T27+T32+T42+T47+T52+T57+T62+T67 -> 123.06361 | U1: =U11+U16+U22+U27+U32+U42+U47+U52+U57+U62+U67 -> 123.06361 | V1: =V11+V16+V22+V27+V32+V42+V47+V52+V57+V62+V67 -> 123.06361 | W1: =W11+W16+W22+W27+W32+W42+W47+W52+W57+W62+W67 -> 140.6254 | X1: =X11+X16+X22+X27+X32+X42+X47+X52+X57+X62+X67 -> 140.6254 | ... AB1: =AB11+AB16+AB22+AB27+AB32+AB42+AB47+AB52+AB57+AB62+AB67 -> 158.18719
B2: CAC | P2: Aquisition Recorrente
B3: Trimestre | C3: 1 Trimestre | F3: 2 Trimestre | I3: 3 Trimestre | L3: 4 Trimestre | P3: Trimestre | Q3: 1 Trimestre | T3: 2 Trimestre | W3: 3 Trimestre | Z3: 4 Trimestre
B4: Mês | C4: Janeiro | D4: Feveiro | E4: Março | F4: Abril | G4: Maio | H4: Junho | I4: Julho | J4: Agosto | K4: Setembro | L4: Outubro | M4: Novembro | N4: Dezembro | P4: Mês | Q4: Janeiro | R4: Feveiro | S4: Março | T4: Abril | U4: Maio | V4: Junho | W4: Julho | X4: Agosto | Y4: Setembro | Z4: Outubro | AA4: Novembro | AB4: Dezembro
B5: Pessoas Totais Commerce (CSV) | C5: =count(C22:C38)+count(C44:C59)+count(C66:C71)+count(C77:C86) -> 24 | D5: =count(D22:D38)+count(D44:D59)+count(D66:D71)+count(D77:D86) -> 25 | E5: =count(E22:E38)+count(E44:E59)+count(E66:E71)+count(E77:E86) -> 27 | F5: =count(F22:F38)+count(F44:F59)+count(F66:F71)+count(F77:F86) -> 30 | G5: =count(G22:G38)+count(G44:G59)+count(G66:G71)+count(G77:G86) -> 30 | H5: =count(H22:H38)+count(H44:H59)+count(H66:H71)+count(H77:H86) -> 30 | I5: =count(I22:I38)+count(I44:I59)+count(I66:I71)+count(I77:I86) -> 30 | J5: =count(J22:J38)+count(J44:J59)+count(J66:J71)+count(J77:J86) -> 31 | ... N5: =count(N22:N38)+count(N44:N59)+count(N66:N71)+count(N77:N86) -> 34 | P5: Meta Vendas Novas MRR | Q5: 200000 | R5: 200000 | S5: 200000 | T5: 220000 | U5: 220000 | V5: 220000 | W5: 240000 | X5: 240000 | Y5: 240000 | Z5: 260000 | AA5: 260000 | AB5: 260000
B6: (=) CAC | C6: =SUM(C7:C15) -> 262495.71 | D6: =SUM(D7:D15) -> 285895.71 | E6: =SUM(E7:E15) -> 311895.71 | F6: =SUM(F7:F15) -> 337573.77 | G6: =SUM(G7:G15) -> 422573.77 | H6: =SUM(H7:H15) -> 362573.77 | I6: =SUM(I7:I15) -> 453925.18 | J6: =SUM(J7:J15) -> 371925.18 | ... N6: =SUM(N7:N15) -> 428776.58 | O6: =sum(C6:N6) -> 4449113.7 | P6: Meta Monetizacao MRR | Q6: 15000 | R6: 15000 | S6: 15000 | T6: 20000 | U6: 20000 | V6: 20000 | W6: 30000 | X6: 30000 | Y6: 30000 | Z6: 40000 | AA6: 40000 | AB6: 40000
B7: (-) Pré Vendas | C7: =C21 -> 27350 | D7: =D21 -> 27350 | E7: =E21 -> 33350 | F7: =F21 -> 34350 | G7: =G21 -> 34350 | H7: =H21 -> 34350 | I7: =I21 -> 34850 | J7: =J21 -> 37850 | ... N7: =N21 -> 46850 | P7: Meta de Vendas Totais MRR | Q7: =Q5+Q6 -> 215000 | R7: =R5+R6 -> 215000 | S7: =S5+S6 -> 215000 | T7: =T5+T6 -> 240000 | U7: =U5+U6 -> 240000 | V7: =V5+V6 -> 240000 | W7: =W5+W6 -> 270000 | X7: =X5+X6 -> 270000 | ... AB7: =AB5+AB6 -> 300000
B8: (-) Vendas | C8: =C43 -> 28400 | D8: =D43 -> 31800 | E8: =E43 -> 31800 | F8: =F43 -> 35400 | G8: =G43 -> 35400 | H8: =H43 -> 35400 | I8: =I43 -> 35400 | J8: =J43 -> 35400 | ... N8: =N43 -> 35400 | P8: % Performance | Q8: 0.3 | R8: 0.3 | S8: 0.3 | T8: 0.3 | U8: 0.3 | V8: 0.3 | W8: 0.3 | X8: 0.3 | Y8: 0.3 | Z8: 0.3 | AA8: 0.3 | AB8: 0.3
B9: (-) Gerencia | C9: =C65 -> 20000 | D9: =D65 -> 20000 | E9: =E65 -> 20000 | F9: =F65 -> 21000 | G9: =G65 -> 21000 | H9: =H65 -> 21000 | I9: =I65 -> 22000 | J9: =J65 -> 22000 | ... N9: =N65 -> 22000 | P9: MRR Performance | Q9: =Q7*Q8 -> 64500 | R9: =R7*R8 -> 64500 | S9: =S7*S8 -> 64500 | T9: =T7*T8 -> 72000 | U9: =U7*U8 -> 72000 | V9: =V7*V8 -> 72000 | W9: =W7*W8 -> 81000 | X9: =X7*X8 -> 81000 | ... AB9: =AB7*AB8 -> 90000
B10: (-) Comissões | C10: =(Q7*0.125)+(Q38*0.1)+(50*Q72) -> 63745.709 | D10: =(R7*0.125)+(R38*0.1)+(50*R72) -> 63745.709 | E10: =(S7*0.125)+(S38*0.1)+(50*S72) -> 63745.709 | F10: =(T7*0.125)+(T38*0.1)+(50*T72) -> 73823.774 | G10: =(U7*0.125)+(U38*0.1)+(50*U72) -> 73823.774 | H10: =(V7*0.125)+(V38*0.1)+(50*V72) -> 73823.774 | I10: =(W7*0.125)+(W38*0.1)+(50*W72) -> 84675.175 | J10: =(X7*0.125)+(X38*0.1)+(50*X72) -> 84675.175 | ... N10: =(AB7*0.125)+(AB38*0.1)+(50*AB72) -> 95526.577 | P10: AOV Performance | Q10: 3000 | R10: 3000 | S10: 3000 | T10: 3000 | U10: 3000 | V10: 3000 | W10: 3000 | X10: 3000 | Y10: 3000 | Z10: 3000 | AA10: 3000 | AB10: 3000
B11: (-) Growth | C11: =C76 -> 23000 | D11: =D76 -> 23000 | E11: =E76 -> 23000 | F11: =F76 -> 33000 | G11: =G76 -> 33000 | H11: =H76 -> 33000 | I11: =I76 -> 37000 | J11: =J76 -> 37000 | ... N11: =N76 -> 39000 | P11: Contratos Performance | Q11: =Q9/Q10 -> 21.5 | R11: =R9/R10 -> 21.5 | S11: =S9/S10 -> 21.5 | T11: =T9/T10 -> 24 | U11: =U9/U10 -> 24 | V11: =V9/V10 -> 24 | W11: =W9/W10 -> 27 | X11: =X9/X10 -> 27 | ... AB11: =AB9/AB10 -> 30
B12: (-) ADs | C12: 80000 | D12: 100000 | E12: 100000 | F12: 110000 | G12: 110000 | H12: 110000 | I12: 120000 | J12: 120000 | K12: 120000 | L12: 130000 | M12: 130000 | N12: 130000
B13: (-) Eventos | C13: 5000 | D13: 5000 | E13: 25000 | F13: 15000 | G13: 100000 | H13: 40000 | I13: 100000 | J13: 15000 | K13: 25000 | L13: 20000 | M13: 5000 | N13: 25000 | P13: % Creators | Q13: 0.25 | R13: 0.25 | S13: 0.25 | T13: 0.25 | U13: 0.25 | V13: 0.25 | W13: 0.25 | X13: 0.25 | Y13: 0.25 | Z13: 0.25 | AA13: 0.25 | AB13: 0.25
B14: (-) Brindes | C14: 10000 | D14: 10000 | E14: 10000 | F14: 10000 | G14: 10000 | H14: 10000 | I14: 15000 | J14: 15000 | K14: 15000 | L14: 30000 | M14: 30000 | N14: 30000 | P14: MRR Creators | Q14: =Q7*Q13 -> 53750 | R14: =R7*R13 -> 53750 | S14: =S7*S13 -> 53750 | T14: =T7*T13 -> 60000 | U14: =U7*U13 -> 60000 | V14: =V7*V13 -> 60000 | W14: =W7*W13 -> 67500 | X14: =X7*X13 -> 67500 | ... AB14: =AB7*AB13 -> 75000
B15: (-) Viagens | C15: 5000 | D15: 5000 | E15: 5000 | F15: 5000 | G15: 5000 | H15: 5000 | I15: 5000 | J15: 5000 | K15: 5000 | L15: 5000 | M15: 5000 | N15: 5000 | P15: AOV Creators | Q15: 5000 | R15: 5000 | S15: 5000 | T15: 5000 | U15: 5000 | V15: 5000 | W15: 5000 | X15: 5000 | Y15: 5000 | Z15: 5000 | AA15: 5000 | AB15: 5000
C16: =C6/Q1 -> 2452.3283 | D16: =D6/R1 -> 2670.9395 | E16: =E6/S1 -> 2913.8407 | F16: =F6/T1 -> 2743.0836 | G16: =G6/U1 -> 3433.7833 | H16: =H6/V1 -> 2946.2305 | I16: =I6/W1 -> 3227.9031 | J16: =J6/X1 -> 2644.7937 | ... N16: =N6/AB1 -> 2710.5644 | P16: Contratos Creators | Q16: =Q14/Q15 -> 10.75 | R16: =R14/R15 -> 10.75 | S16: =S14/S15 -> 10.75 | T16: =T14/T15 -> 12 | U16: =U14/U15 -> 12 | V16: =V14/V15 -> 12 | W16: =W14/W15 -> 13.5 | X16: =X14/X15 -> 13.5 | ... AB16: =AB14/AB15 -> 15
C17: 100
B18: PRÉ VENDAS
B19: Trimestre | C19: 1 Trimestre | F19: 2 Trimestre | I19: 3 Trimestre | L19: 4 Trimestre | P19: % Social | Q19: 0.2 | R19: 0.2 | S19: 0.2 | T19: 0.2 | U19: 0.2 | V19: 0.2 | W19: 0.2 | X19: 0.2 | Y19: 0.2 | Z19: 0.2 | AA19: 0.2 | AB19: 0.2
B20: Mês | C20: Janeiro | D20: Feveiro | E20: Março | F20: Abril | G20: Maio | H20: Junho | I20: Julho | J20: Agosto | K20: Setembro | L20: Outubro | M20: Novembro | N20: Dezembro | P20: MRR Social | Q20: =Q7*Q19 -> 43000 | R20: =R7*R19 -> 43000 | S20: =S7*S19 -> 43000 | T20: =T7*T19 -> 48000 | U20: =U7*U19 -> 48000 | V20: =V7*V19 -> 48000 | W20: =W7*W19 -> 54000 | X20: =X7*X19 -> 54000 | ... AB20: =AB7*AB19 -> 60000
B21: (=) Pré Vendas | C21: =SUM(C22:C38) -> 27350 | D21: =SUM(D22:D38) -> 27350 | E21: =SUM(E22:E38) -> 33350 | F21: =SUM(F22:F38) -> 34350 | G21: =SUM(G22:G38) -> 34350 | H21: =SUM(H22:H38) -> 34350 | I21: =SUM(I22:I38) -> 34850 | J21: =SUM(J22:J38) -> 37850 | ... N21: =SUM(N22:N38) -> 46850 | P21: AOV Social | Q21: 2300 | R21: 2300 | S21: 2300 | T21: 2300 | U21: 2300 | V21: 2300 | W21: 2300 | X21: 2300 | Y21: 2300 | Z21: 2300 | AA21: 2300 | AB21: 2300
B22: Guilherme Cassemiro | C22: 3850 | D22: 3850 | E22: 3850 | F22: 3850 | G22: 3850 | H22: 3850 | I22: 3850 | J22: 3850 | K22: 3850 | L22: 3850 | M22: 3850 | N22: 3850 | P22: Contratos Social | Q22: =Q20/Q21 -> 18.695652 | R22: =R20/R21 -> 18.695652 | S22: =S20/S21 -> 18.695652 | T22: =T20/T21 -> 20.869565 | U22: =U20/U21 -> 20.869565 | V22: =V20/V21 -> 20.869565 | W22: =W20/W21 -> 23.478261 | X22: =X20/X21 -> 23.478261 | ... AB22: =AB20/AB21 -> 26.086957
B23: Lenize Pretti | C23: 3000 | D23: 3000 | E23: 3000 | F23: 3000 | G23: 3000 | H23: 3000 | I23: 3000 | J23: 3000 | K23: 3000 | L23: 3000 | M23: 3000 | N23: 3000
B24: Eduarda Grippa | C24: 3000 | D24: 3000 | E24: 3000 | F24: 3500 | G24: 3500 | H24: 3500 | I24: 3500 | J24: 3500 | K24: 3500 | L24: 3500 | M24: 3500 | N24: 3500 | P24: % Gestão de Comunidade | Q24: 0.15 | R24: 0.15 | S24: 0.15 | T24: 0.15 | U24: 0.15 | V24: 0.15 | W24: 0.15 | X24: 0.15 | Y24: 0.15 | Z24: 0.15 | AA24: 0.15 | AB24: 0.15
B25: Kaike | C25: 3000 | D25: 3000 | E25: 3000 | F25: 3000 | G25: 3000 | H25: 3000 | I25: 3000 | J25: 3000 | K25: 3000 | L25: 3000 | M25: 3000 | N25: 3000 | P25: MRR Gestão de Comunidade | Q25: =Q7*Q24 -> 32250 | R25: =R7*R24 -> 32250 | S25: =S7*S24 -> 32250 | T25: =T7*T24 -> 36000 | U25: =U7*U24 -> 36000 | V25: =V7*V24 -> 36000 | W25: =W7*W24 -> 40500 | X25: =X7*X24 -> 40500 | ... AB25: =AB7*AB24 -> 45000
B26: Isabella | C26: 3000 | D26: 3000 | E26: 3000 | F26: 3500 | G26: 3500 | H26: 3500 | I26: 3500 | J26: 3500 | K26: 3500 | L26: 3500 | M26: 3500 | N26: 3500 | P26: AOV Gestão de Comunidade | Q26: 10000 | R26: 10000 | S26: 10000 | T26: 10000 | U26: 10000 | V26: 10000 | W26: 10000 | X26: 10000 | Y26: 10000 | Z26: 10000 | AA26: 10000 | AB26: 10000
B27: Fabiely | C27: 3000 | D27: 3000 | E27: 3000 | F27: 3000 | G27: 3000 | H27: 3000 | I27: 3000 | J27: 3000 | K27: 3000 | L27: 3000 | M27: 3000 | N27: 3000 | P27: Contratos Gestão de Comunidade | Q27: =Q25/Q26 -> 3.225 | R27: =R25/R26 -> 3.225 | S27: =S25/S26 -> 3.225 | T27: =T25/T26 -> 3.6 | U27: =U25/U26 -> 3.6 | V27: =V25/V26 -> 3.6 | W27: =W25/W26 -> 4.05 | X27: =X25/X26 -> 4.05 | ... AB27: =AB25/AB26 -> 4.5
B28: Pedro Teodoro | C28: 3000 | D28: 3000 | E28: 3000 | F28: 3000 | G28: 3000 | H28: 3000 | I28: 3500 | J28: 3500 | K28: 3500 | L28: 3500 | M28: 3500 | N28: 3500
B29: Joao Pedro | C29: 2500 | D29: 2500 | E29: 2500 | F29: 2500 | G29: 2500 | H29: 2500 | I29: 2500 | J29: 2500 | K29: 2500 | L29: 2500 | M29: 2500 | N29: 2500 | P29: % Others | Q29: 0.1 | R29: 0.1 | S29: 0.1 | T29: 0.1 | U29: 0.1 | V29: 0.1 | W29: 0.1 | X29: 0.1 | Y29: 0.1 | Z29: 0.1 | AA29: 0.1 | AB29: 0.1
B30: Novo - Contratar | C30: 3000 | D30: 3000 | E30: 3000 | F30: 3000 | G30: 3000 | H30: 3000 | I30: 3000 | J30: 3000 | K30: 3000 | L30: 3000 | M30: 3000 | N30: 3000 | P30: MRR Others | Q30: =Q7*Q29 -> 21500 | R30: =R7*R29 -> 21500 | S30: =S7*S29 -> 21500 | T30: =T7*T29 -> 24000 | U30: =U7*U29 -> 24000 | V30: =V7*V29 -> 24000 | W30: =W7*W29 -> 27000 | X30: =X7*X29 -> 27000 | ... AB30: =AB7*AB29 -> 30000
B31: Novo - Contratar | E31: 3000 | F31: 3000 | G31: 3000 | H31: 3000 | I31: 3000 | J31: 3000 | K31: 3000 | L31: 3000 | M31: 3000 | N31: 3000 | P31: AOV Others | Q31: 1800 | R31: 1800 | S31: 1800 | T31: 1800 | U31: 1800 | V31: 1800 | W31: 1800 | X31: 1800 | Y31: 1800 | Z31: 1800 | AA31: 1800 | AB31: 1800
B32: Novo - Contratar | E32: 3000 | F32: 3000 | G32: 3000 | H32: 3000 | I32: 3000 | J32: 3000 | K32: 3000 | L32: 3000 | M32: 3000 | N32: 3000 | P32: Contratos Others | Q32: =Q30/Q31 -> 11.944444 | R32: =R30/R31 -> 11.944444 | S32: =S30/S31 -> 11.944444 | T32: =T30/T31 -> 13.333333 | U32: =U30/U31 -> 13.333333 | V32: =V30/V31 -> 13.333333 | W32: =W30/W31 -> 15 | X32: =X30/X31 -> 15 | ... AB32: =AB30/AB31 -> 16.666667
B33: Novo - Contratar | J33: 3000 | K33: 3000 | L33: 3000 | M33: 3000 | N33: 3000
B34: Novo - Contratar | K34: 3000 | L34: 3000 | M34: 3000 | N34: 3000 | P34: Aquisition Pontual
B35: Novo - Contratar | L35: 3000 | M35: 3000 | N35: 3000 | P35: Trimestre | Q35: 1 Trimestre | T35: 2 Trimestre | W35: 3 Trimestre | Z35: 4 Trimestre
B36: Novo - Contratar | N36: 3000 | P36: Meta de Vendas Novas Pontual | Q36: 250000 | R36: 250000 | S36: 250000 | T36: 300000 | U36: 300000 | V36: 300000 | W36: 350000 | X36: 350000 | Y36: 350000 | Z36: 400000 | AA36: 400000 | AB36: 400000
B37: Novo - Contratar | P37: Monetizacao Base Pontual | Q37: 20000 | R37: 20000 | S37: 20000 | T37: 25000 | U37: 25000 | V37: 25000 | W37: 30000 | X37: 30000 | Y37: 30000 | Z37: 35000 | AA37: 35000 | AB37: 35000
B38: Novo - Contratar | P38: Meta de Vendas Totais Pontual | Q38: =Q36+Q37 -> 270000 | R38: =R36+R37 -> 270000 | S38: =S36+S37 -> 270000 | T38: =T36+T37 -> 325000 | U38: =U36+U37 -> 325000 | V38: =V36+V37 -> 325000 | W38: =W36+W37 -> 380000 | X38: =X36+X37 -> 380000 | ... AB38: =AB36+AB37 -> 435000
P39: % E-commerce | Q39: 0.42 | R39: 0.42 | S39: 0.42 | T39: 0.42 | U39: 0.42 | V39: 0.42 | W39: 0.42 | X39: 0.42 | Y39: 0.42 | Z39: 0.42 | AA39: 0.42 | AB39: 0.42
B40: Vendas | P40: Pontual e-commerce | Q40: =Q38*Q39 -> 113400 | R40: =R38*R39 -> 113400 | S40: =S38*S39 -> 113400 | T40: =T38*T39 -> 136500 | U40: =U38*U39 -> 136500 | V40: =V38*V39 -> 136500 | W40: =W38*W39 -> 159600 | X40: =X38*X39 -> 159600 | ... AB40: =AB38*AB39 -> 182700
B41: Trimestre | C41: 1 Trimestre | F41: 2 Trimestre | I41: 3 Trimestre | L41: 4 Trimestre | P41: AOV E-commerce | Q41: 15000 | R41: 15000 | S41: 15000 | T41: 15000 | U41: 15000 | V41: 15000 | W41: 15000 | X41: 15000 | Y41: 15000 | Z41: 15000 | AA41: 15000 | AB41: 15000
B42: Mês | C42: Janeiro | D42: Feveiro | E42: Março | F42: Abril | G42: Maio | H42: Junho | I42: Julho | J42: Agosto | K42: Setembro | L42: Outubro | M42: Novembro | N42: Dezembro | P42: Contratos E-commerce | Q42: =Q40/Q41 -> 7.56 | R42: =R40/R41 -> 7.56 | S42: =S40/S41 -> 7.56 | T42: =T40/T41 -> 9.1 | U42: =U40/U41 -> 9.1 | V42: =V40/V41 -> 9.1 | W42: =W40/W41 -> 10.64 | X42: =X40/X41 -> 10.64 | ... AB42: =AB40/AB41 -> 12.18
B43: (=) Vendas | C43: =SUM(C44:C59) -> 28400 | D43: =SUM(D44:D59) -> 31800 | E43: =SUM(E44:E59) -> 31800 | F43: =SUM(F44:F59) -> 35400 | G43: =SUM(G44:G59) -> 35400 | H43: =SUM(H44:H59) -> 35400 | I43: =SUM(I44:I59) -> 35400 | J43: =SUM(J44:J59) -> 35400 | ... N43: =SUM(N44:N59) -> 35400
B44: Arthur Zon | C44: 4400 | D44: 4400 | E44: 4400 | F44: 4400 | G44: 4400 | H44: 4400 | I44: 4400 | J44: 4400 | K44: 4400 | L44: 4400 | M44: 4400 | N44: 4400 | P44: % Site Institucional | Q44: 0.1 | R44: 0.1 | S44: 0.1 | T44: 0.1 | U44: 0.1 | V44: 0.1 | W44: 0.1 | X44: 0.1 | Y44: 0.1 | Z44: 0.1 | AA44: 0.1 | AB44: 0.1
B45: Daniel Pato | C45: 5900 | D45: 5900 | E45: 5900 | F45: 5900 | G45: 5900 | H45: 5900 | I45: 5900 | J45: 5900 | K45: 5900 | L45: 5900 | M45: 5900 | N45: 5900 | P45: Pontual Site | Q45: =Q38*Q44 -> 27000 | R45: =R38*R44 -> 27000 | S45: =S38*S44 -> 27000 | T45: =T38*T44 -> 32500 | U45: =U38*U44 -> 32500 | V45: =V38*V44 -> 32500 | W45: =W38*W44 -> 38000 | X45: =X38*X44 -> 38000 | ... AB45: =AB38*AB44 -> 43500
B46: Matheus Scalfoni | C46: 4400 | D46: 4400 | E46: 4400 | F46: 4400 | G46: 4400 | H46: 4400 | I46: 4400 | J46: 4400 | K46: 4400 | L46: 4400 | M46: 4400 | N46: 4400 | P46: AOV Site | Q46: 12000 | R46: 12000 | S46: 12000 | T46: 12000 | U46: 12000 | V46: 12000 | W46: 12000 | X46: 12000 | Y46: 12000 | Z46: 12000 | AA46: 12000 | AB46: 12000
B47: Yan Roldi | C47: 3400 | D47: 3400 | E47: 3400 | F47: 3400 | G47: 3400 | H47: 3400 | I47: 3400 | J47: 3400 | K47: 3400 | L47: 3400 | M47: 3400 | N47: 3400 | P47: Contratos Site | Q47: =Q45/Q46 -> 2.25 | R47: =R45/R46 -> 2.25 | S47: =S45/S46 -> 2.25 | T47: =T45/T46 -> 2.7083333 | U47: =U45/U46 -> 2.7083333 | V47: =V45/V46 -> 2.7083333 | W47: =W45/W46 -> 3.1666667 | X47: =X45/X46 -> 3.1666667 | ... AB47: =AB45/AB46 -> 3.625
B48: Fabio Richard | C48: 5900 | D48: 5900 | E48: 5900 | F48: 5900 | G48: 5900 | H48: 5900 | I48: 5900 | J48: 5900 | K48: 5900 | L48: 5900 | M48: 5900 | N48: 5900
B49: Ramon | C49: 4400 | D49: 4400 | E49: 4400 | F49: 4400 | G49: 4400 | H49: 4400 | I49: 4400 | J49: 4400 | K49: 4400 | L49: 4400 | M49: 4400 | N49: 4400 | P49: % Landing Page | Q49: 0.08 | R49: 0.08 | S49: 0.08 | T49: 0.08 | U49: 0.08 | V49: 0.08 | W49: 0.08 | X49: 0.08 | Y49: 0.08 | Z49: 0.08 | AA49: 0.08 | AB49: 0.08
B50: Novo - Contratar | D50: 3400 | E50: 3400 | F50: 3500 | G50: 3500 | H50: 3500 | I50: 3500 | J50: 3500 | K50: 3500 | L50: 3500 | M50: 3500 | N50: 3500 | P50: Pontual Landing Page | Q50: =Q38*Q49 -> 21600 | R50: =R38*R49 -> 21600 | S50: =S38*S49 -> 21600 | T50: =T38*T49 -> 26000 | U50: =U38*U49 -> 26000 | V50: =V38*V49 -> 26000 | W50: =W38*W49 -> 30400 | X50: =X38*X49 -> 30400 | ... AB50: =AB38*AB49 -> 34800
B51: Novo - Contratar | F51: 3500 | G51: 3500 | H51: 3500 | I51: 3500 | J51: 3500 | K51: 3500 | L51: 3500 | M51: 3500 | N51: 3500 | P51: AOV Landing Page | Q51: 3000 | R51: 3000 | S51: 3000 | T51: 3000 | U51: 3000 | V51: 3000 | W51: 3000 | X51: 3000 | Y51: 3000 | Z51: 3000 | AA51: 3000 | AB51: 3000
B52: Novo - Contratar | P52: Contratos Landing Page | Q52: =Q50/Q51 -> 7.2 | R52: =R50/R51 -> 7.2 | S52: =S50/S51 -> 7.2 | T52: =T50/T51 -> 8.6666667 | U52: =U50/U51 -> 8.6666667 | V52: =V50/V51 -> 8.6666667 | W52: =W50/W51 -> 10.133333 | X52: =X50/X51 -> 10.133333 | ... AB52: =AB50/AB51 -> 11.6
B53: Novo - Contratar
B54: Novo - Contratar | P54: % Creators | Q54: 0.2 | R54: 0.2 | S54: 0.2 | T54: 0.2 | U54: 0.2 | V54: 0.2 | W54: 0.2 | X54: 0.2 | Y54: 0.2 | Z54: 0.2 | AA54: 0.2 | AB54: 0.2
B55: Novo - Contratar | P55: Pontual Creators | Q55: =Q38*Q54 -> 54000 | R55: =R38*R54 -> 54000 | S55: =S38*S54 -> 54000 | T55: =T38*T54 -> 65000 | U55: =U38*U54 -> 65000 | V55: =V38*V54 -> 65000 | W55: =W38*W54 -> 76000 | X55: =X38*X54 -> 76000 | ... AB55: =AB38*AB54 -> 87000
B56: Novo - Contratar | P56: AOV Creators | Q56: 7000 | R56: 7000 | S56: 7000 | T56: 7000 | U56: 7000 | V56: 7000 | W56: 7000 | X56: 7000 | Y56: 7000 | Z56: 7000 | AA56: 7000 | AB56: 7000
B57: Novo - Contratar | P57: Contratos Creators | Q57: =Q55/Q56 -> 7.7142857 | R57: =R55/R56 -> 7.7142857 | S57: =S55/S56 -> 7.7142857 | T57: =T55/T56 -> 9.2857143 | U57: =U55/U56 -> 9.2857143 | V57: =V55/V56 -> 9.2857143 | W57: =W55/W56 -> 10.857143 | X57: =X55/X56 -> 10.857143 | ... AB57: =AB55/AB56 -> 12.428571
B58: Novo - Contratar
B59: Novo - Contratar | P59: % CRM | Q59: 0.05 | R59: 0.05 | S59: 0.05 | T59: 0.05 | U59: 0.05 | V59: 0.05 | W59: 0.05 | X59: 0.05 | Y59: 0.05 | Z59: 0.05 | AA59: 0.05 | AB59: 0.05
P60: Pontual CRM | Q60: =Q38*Q59 -> 13500 | R60: =R38*R59 -> 13500 | S60: =S38*S59 -> 13500 | T60: =T38*T59 -> 16250 | U60: =U38*U59 -> 16250 | V60: =V38*V59 -> 16250 | W60: =W38*W59 -> 19000 | X60: =X38*X59 -> 19000 | ... AB60: =AB38*AB59 -> 21750
P61: AOV CRM | Q61: 5000 | R61: 5000 | S61: 5000 | T61: 5000 | U61: 5000 | V61: 5000 | W61: 5000 | X61: 5000 | Y61: 5000 | Z61: 5000 | AA61: 5000 | AB61: 5000
B62: Gerencia Vendas | P62: Contratos CRM | Q62: =Q60/Q61 -> 2.7 | R62: =R60/R61 -> 2.7 | S62: =S60/S61 -> 2.7 | T62: =T60/T61 -> 3.25 | U62: =U60/U61 -> 3.25 | V62: =V60/V61 -> 3.25 | W62: =W60/W61 -> 3.8 | X62: =X60/X61 -> 3.8 | ... AB62: =AB60/AB61 -> 4.35
B63: Trimestre | C63: 1 Trimestre | F63: 2 Trimestre | I63: 3 Trimestre | L63: 4 Trimestre
B64: Mês | C64: Janeiro | D64: Feveiro | E64: Março | F64: Abril | G64: Maio | H64: Junho | I64: Julho | J64: Agosto | K64: Setembro | L64: Outubro | M64: Novembro | N64: Dezembro | P64: % Others | Q64: 0.15 | R64: 0.15 | S64: 0.15 | T64: 0.15 | U64: 0.15 | V64: 0.15 | W64: 0.15 | X64: 0.15 | Y64: 0.15 | Z64: 0.15 | AA64: 0.15 | AB64: 0.15
B65: (=) Gerencia | C65: =SUM(C66:C71) -> 20000 | D65: =SUM(D66:D71) -> 20000 | E65: =SUM(E66:E71) -> 20000 | F65: =SUM(F66:F71) -> 21000 | G65: =SUM(G66:G71) -> 21000 | H65: =SUM(H66:H71) -> 21000 | I65: =SUM(I66:I71) -> 22000 | J65: =SUM(J66:J71) -> 22000 | ... N65: =SUM(N66:N71) -> 22000 | P65: Pontual Others | Q65: =Q38*Q64 -> 40500 | R65: =R38*R64 -> 40500 | S65: =S38*S64 -> 40500 | T65: =T38*T64 -> 48750 | U65: =U38*U64 -> 48750 | V65: =V38*V64 -> 48750 | W65: =W38*W64 -> 57000 | X65: =X38*X64 -> 57000 | ... AB65: =AB38*AB64 -> 65250
B66: João Guarçoni | C66: 12000 | D66: 12000 | E66: 12000 | F66: 12000 | G66: 12000 | H66: 12000 | I66: 12000 | J66: 12000 | K66: 12000 | L66: 12000 | M66: 12000 | N66: 12000 | P66: AOV Others | Q66: 3000 | R66: 3000 | S66: 3000 | T66: 3000 | U66: 3000 | V66: 3000 | W66: 3000 | X66: 3000 | Y66: 3000 | Z66: 3000 | AA66: 3000 | AB66: 3000
B67: Lucas Pereira | C67: 8000 | D67: 8000 | E67: 8000 | F67: 9000 | G67: 9000 | H67: 9000 | I67: 10000 | J67: 10000 | K67: 10000 | L67: 10000 | M67: 10000 | N67: 10000 | P67: Contratos Others | Q67: =Q65/Q66 -> 13.5 | R67: =R65/R66 -> 13.5 | S67: =S65/S66 -> 13.5 | T67: =T65/T66 -> 16.25 | U67: =U65/U66 -> 16.25 | V67: =V65/V66 -> 16.25 | W67: =W65/W66 -> 19 | X67: =X65/X66 -> 19 | ... AB67: =AB65/AB66 -> 21.75
B68: Novo - Contratar - Gestor growth?
B69: Novo - Contratar | P69: AOV Pontual | Q69: =(Q39*Q41)+(Q44*Q46)+(Q51*Q49)+(Q54*Q56)+(Q59*Q61)+(Q64*Q66) -> 9840 | R69: =(R39*R41)+(R44*R46)+(R51*R49)+(R54*R56)+(R59*R61)+(R64*R66) -> 9840 | S69: =(S39*S41)+(S44*S46)+(S51*S49)+(S54*S56)+(S59*S61)+(S64*S66) -> 9840 | T69: =(T39*T41)+(T44*T46)+(T51*T49)+(T54*T56)+(T59*T61)+(T64*T66) -> 9840 | U69: =(U39*U41)+(U44*U46)+(U51*U49)+(U54*U56)+(U59*U61)+(U64*U66) -> 9840 | V69: =(V39*V41)+(V44*V46)+(V51*V49)+(V54*V56)+(V59*V61)+(V64*V66) -> 9840 | W69: =(W39*W41)+(W44*W46)+(W51*W49)+(W54*W56)+(W59*W61)+(W64*W66) -> 9840 | X69: =(X39*X41)+(X44*X46)+(X51*X49)+(X54*X56)+(X59*X61)+(X64*X66) -> 9840 | ... AB69: =(AB39*AB41)+(AB44*AB46)+(AB51*AB49)+(AB54*AB56)+(AB59*AB61)+(AB64*AB66) -> 9840
B70: Novo - Contratar | P70: AOV Recorrente | Q70: =(Q10*Q8)+(Q13*Q15)+(Q19*Q21)+(Q29*Q31)+(Q24*Q26) -> 4290 | R70: =(R10*R8)+(R13*R15)+(R19*R21)+(R29*R31)+(R24*R26) -> 4290 | S70: =(S10*S8)+(S13*S15)+(S19*S21)+(S29*S31)+(S24*S26) -> 4290 | T70: =(T10*T8)+(T13*T15)+(T19*T21)+(T29*T31)+(T24*T26) -> 4290 | U70: =(U10*U8)+(U13*U15)+(U19*U21)+(U29*U31)+(U24*U26) -> 4290 | V70: =(V10*V8)+(V13*V15)+(V19*V21)+(V29*V31)+(V24*V26) -> 4290 | W70: =(W10*W8)+(W13*W15)+(W19*W21)+(W29*W31)+(W24*W26) -> 4290 | X70: =(X10*X8)+(X13*X15)+(X19*X21)+(X29*X31)+(X24*X26) -> 4290 | ... AB70: =(AB10*AB8)+(AB13*AB15)+(AB19*AB21)+(AB29*AB31)+(AB24*AB26) -> 4290
B71: Novo - Contratar | P71: Taxa de conversão | Q71: 0.275 | R71: 0.275 | S71: 0.275 | T71: 0.275 | U71: 0.275 | V71: 0.275 | W71: 0.275 | X71: 0.275 | Y71: 0.275 | Z71: 0.275 | AA71: 0.275 | AB71: 0.275
P72: Reuniões Necessárias | Q72: =((((Q7/Q70))/Q71)+(((Q38/Q69))/Q71))*0.7 -> 197.41419 | R72: =((((R7/R70))/R71)+(((R38/R69))/R71))*0.7 -> 197.41419 | S72: =((((S7/S70))/S71)+(((S38/S69))/S71))*0.7 -> 197.41419 | T72: =((((T7/T70))/T71)+(((T38/T69))/T71))*0.7 -> 226.47548 | U72: =((((U7/U70))/U71)+(((U38/U69))/U71))*0.7 -> 226.47548 | V72: =((((V7/V70))/V71)+(((V38/V69))/V71))*0.7 -> 226.47548 | W72: =((((W7/W70))/W71)+(((W38/W69))/W71))*0.7 -> 258.50351 | X72: =((((X7/X70))/X71)+(((X38/X69))/X71))*0.7 -> 258.50351 | ... AB72: =((((AB7/AB70))/AB71)+(((AB38/AB69))/AB71))*0.7 -> 290.53153
B73: Growth | P73: Reuniões por pré vendedor | Q73: =Q72/count(C22:C38) -> 21.93491 | R73: =R72/count(D22:D38) -> 21.93491 | S73: =S72/count(E22:E38) -> 17.946745 | T73: =T72/count(F22:F38) -> 20.58868 | U73: =U72/count(G22:G38) -> 20.58868 | V73: =V72/count(H22:H38) -> 20.58868 | W73: =W72/count(I22:I38) -> 23.500319 | X73: =X72/count(J22:J38) -> 21.541959 | ... AB73: =AB72/count(N22:N38) -> 19.368769
B74: Trimestre | C74: 1 Trimestre | F74: 2 Trimestre | I74: 3 Trimestre | L74: 4 Trimestre | P74: Reuniões por vendedor | Q74: =Q72/count(C44:C59) -> 32.902365 | R74: =R72/count(D44:D59) -> 28.202027 | S74: =S72/count(E44:E59) -> 28.202027 | T74: =T72/count(F44:F59) -> 28.309435 | U74: =U72/count(G44:G59) -> 28.309435 | V74: =V72/count(H44:H59) -> 28.309435 | W74: =W72/count(I44:I59) -> 32.312938 | X74: =X72/count(J44:J59) -> 32.312938 | ... AB74: =AB72/count(N44:N59) -> 36.316441
B75: Mês | C75: Janeiro | D75: Feveiro | E75: Março | F75: Abril | G75: Maio | H75: Junho | I75: Julho | J75: Agosto | K75: Setembro | L75: Outubro | M75: Novembro | N75: Dezembro | P75: MRR Vendido por vendedor | Q75: =Q7/count(C44:C59) -> 35833.333 | R75: =R7/count(D44:D59) -> 30714.286 | S75: =S7/count(E44:E59) -> 30714.286 | T75: =T7/count(F44:F59) -> 30000 | U75: =U7/count(G44:G59) -> 30000 | V75: =V7/count(H44:H59) -> 30000 | W75: =W7/count(I44:I59) -> 33750 | X75: =X7/count(J44:J59) -> 33750 | ... AB75: =AB7/count(N44:N59) -> 37500
B76: (=) Growth | C76: =SUM(C77:C86) -> 23000 | D76: =SUM(D77:D86) -> 23000 | E76: =SUM(E77:E86) -> 23000 | F76: =SUM(F77:F86) -> 33000 | G76: =SUM(G77:G86) -> 33000 | H76: =SUM(H77:H86) -> 33000 | I76: =SUM(I77:I86) -> 37000 | J76: =SUM(J77:J86) -> 37000 | ... N76: =SUM(N77:N86) -> 39000 | P76: Pontual Vendido por vendedor | Q76: =Q38/count(C44:C59) -> 45000 | R76: =R38/count(D44:D59) -> 38571.429 | S76: =S38/count(E44:E59) -> 38571.429 | T76: =T38/count(F44:F59) -> 40625 | U76: =U38/count(G44:G59) -> 40625 | V76: =V38/count(H44:H59) -> 40625 | W76: =W38/count(I44:I59) -> 47500 | X76: =X38/count(J44:J59) -> 47500 | ... AB76: =AB38/count(N44:N59) -> 54375
B77: Vinicius Ichinosek | C77: 4000 | D77: 4000 | E77: 4000 | F77: 4500 | G77: 4500 | H77: 4500 | I77: 5000 | J77: 5000 | K77: 5000 | L77: 5500 | M77: 5500 | N77: 5500
B78: Esther Fiorio | C78: 4000 | D78: 4000 | E78: 4000 | F78: 4500 | G78: 4500 | H78: 4500 | I78: 5000 | J78: 5000 | K78: 5000 | L78: 5500 | M78: 5500 | N78: 5500
B79: Matheus Oliveira | C79: 3500 | D79: 3500 | E79: 3500 | F79: 4000 | G79: 4000 | H79: 4000 | I79: 4500 | J79: 4500 | K79: 4500 | L79: 5000 | M79: 5000 | N79: 5000
B80: Amanda Lovise | C80: 3500 | D80: 3500 | E80: 3500 | F80: 4000 | G80: 4000 | H80: 4000 | I80: 4000 | J80: 4000 | K80: 4000 | L80: 4500 | M80: 4500 | N80: 4500
B81: Caio | C81: 1000 | D81: 1000 | E81: 1000 | F81: 1000 | G81: 1000 | H81: 1000 | I81: 2000 | J81: 2000 | K81: 2000 | L81: 2000 | M81: 2000 | N81: 2000
B82: Novo - Contratar (Substituir) | C82: 3000 | D82: 3000 | E82: 3000 | F82: 3000 | G82: 3000 | H82: 3000 | I82: 4000 | J82: 4000 | K82: 4000 | L82: 4000 | M82: 4000 | N82: 4000
B83: Emerson | C83: 4000 | D83: 4000 | E83: 4000 | F83: 4500 | G83: 4500 | H83: 4500 | I83: 5000 | J83: 5000 | K83: 5000 | L83: 5000 | M83: 5000 | N83: 5000
B84: Novo - Contratar - Webdesigner | F84: 3500 | G84: 3500 | H84: 3500 | I84: 3500 | J84: 3500 | K84: 3500 | L84: 3500 | M84: 3500 | N84: 3500
B85: Novo - Contratar (Social Media Socios) | F85: 4000 | G85: 4000 | H85: 4000 | I85: 4000 | J85: 4000 | K85: 4000 | L85: 4000 | M85: 4000 | N85: 4000
B86: Novo - Contratar

Sheet Revenue
B2: Receita Recorrente
B3: Trimestre | C3: Bookado | D3: 1 Trimestre | G3: 2 Trimestre | J3: 3 Trimestre | M3: 4 Trimestre
B4: Mês | C4: Dezembro | D4: Janeiro | E4: Feveiro | F4: Março | G4: Abril | H4: Maio | I4: Junho | J4: Julho | K4: Agosto | L4: Setembro | M4: Outubro | N4: Novembro | O4: Dezembro
B5: MRR Ativo | C5: =C7+C12+C17+C27+C22 -> 1035000 | D5: =D7+D12+D17+D27+D22 -> 1156850 | E5: =E7+E12+E17+E27+E22 -> 1267733.5 | F5: =F7+F12+F17+F27+F22 -> 1368637.5 | G5: =G7+G12+G17+G27+G22 -> 1485460.1 | H5: =H7+H12+H17+H27+H22 -> 1591768.7 | I5: =I7+I12+I17+I27+I22 -> 1688509.5 | J5: =J7+J12+J17+J27+J22 -> 1806543.7 | ... O5: =O7+O12+O17+O27+O22 -> 2337387.9
B7: MRR Performance | C7: 475000 | D7: =((1-C10)*C7)+CAC!Q9 -> 496750 | E7: =((1-D10)*D7)+CAC!R9 -> 516542.5 | F7: =((1-E10)*E7)+CAC!S9 -> 534553.68 | G7: =((1-F10)*F7)+CAC!T9 -> 558443.84 | H7: =((1-G10)*G7)+CAC!U9 -> 580183.9 | I7: =((1-H10)*H7)+CAC!V9 -> 599967.35 | J7: =((1-I10)*I7)+CAC!W9 -> 626970.29 | K7: =((1-J10)*J7)+CAC!X9 -> 651542.96 | ... O7: =((1-N10)*N7)+CAC!AB9 -> 754263.58
B8: AOV Performance | C8: =C7/C9 -> 2698.8636 | D8: =((C8*C9)+(CAC!Q10*CAC!Q11))/(CAC!Q11+C9) -> 2731.6456 | E8: =((D8*D9)+(CAC!R10*CAC!R11))/(CAC!R11+D9) -> 2760.0184 | F8: =((E8*E9)+(CAC!S10*CAC!S11))/(CAC!S11+E9) -> 2784.7467 | G8: =((F8*F9)+(CAC!T10*CAC!T11))/(CAC!T11+F9) -> 2808.6684 | H8: =((G8*G9)+(CAC!U10*CAC!U11))/(CAC!U11+G9) -> 2829.276 | I8: =((H8*H9)+(CAC!V10*CAC!V11))/(CAC!V11+H9) -> 2847.1634 | J8: =((I8*I9)+(CAC!W10*CAC!W11))/(CAC!W11+I9) -> 2864.5221 | K8: =((J8*J9)+(CAC!X10*CAC!X11))/(CAC!X11+J9) -> 2879.3992 | ... O8: =((N8*N9)+(CAC!AB10*CAC!AB11))/(CAC!AB11+N9) -> 2924.1555
B9: Contratos Performance | C9: 176 | D9: =D7/D8 -> 181.85009 | E9: =E7/E8 -> 187.15183 | F9: =F7/F8 -> 191.95774 | G9: =G7/G8 -> 198.82868 | H9: =H7/H8 -> 205.06444 | I9: =I7/I8 -> 210.72459 | J9: =J7/J8 -> 218.8743 | K9: =K7/K8 -> 226.2774 | ... O9: =O7/O8 -> 257.94236 | Q9: Churn
B10: Churn Performance | C10: =$Q$10 -> 0.09 | D10: =$Q$10 -> 0.09 | E10: =$Q$10 -> 0.09 | F10: =$Q$10 -> 0.09 | G10: =$Q$10 -> 0.09 | H10: =$Q$10 -> 0.09 | I10: =$Q$10 -> 0.09 | J10: =$Q$10 -> 0.09 | ... O10: =$Q$10 -> 0.09 | Q10: 0.09
D11: 0.15 | E11: 0.0769 | F11: 0.1571 | G11: 0.1121 | H11: 0.1263
B12: MRR Creators | C12: 223000 | D12: =((1-C15)*C12)+CAC!Q14 -> 256680 | E12: =((1-D15)*D12)+CAC!R14 -> 287328.8 | F12: =((1-E15)*E12)+CAC!S14 -> 315219.21 | G12: =((1-F15)*F12)+CAC!T14 -> 346849.48 | H12: =((1-G15)*G12)+CAC!U14 -> 375633.03 | I12: =((1-H15)*H12)+CAC!V14 -> 401826.05 | J12: =((1-I15)*I12)+CAC!W14 -> 433161.71 | K12: =((1-J15)*J12)+CAC!X14 -> 461677.16 | ... O12: =((1-N15)*N12)+CAC!AB14 -> 572818.47
B13: AOV Creators | C13: =C12/C14 -> 4207.5472 | D13: =((C13*C14)+(CAC!Q15*CAC!Q16))/(CAC!Q16+C14) -> 4341.1765 | E13: =((D13*D14)+(CAC!R15*CAC!R16))/(CAC!R16+D14) -> 4442.5313 | F13: =((E13*E14)+(CAC!S15*CAC!S16))/(CAC!S16+E14) -> 4521.983 | G13: =((F13*F14)+(CAC!T15*CAC!T16))/(CAC!T16+F14) -> 4592.1865 | H13: =((G13*G14)+(CAC!U15*CAC!U16))/(CAC!U16+G14) -> 4648.0958 | I13: =((H13*H14)+(CAC!V15*CAC!V16))/(CAC!V16+H14) -> 4693.5936 | J13: =((I13*I14)+(CAC!W15*CAC!W16))/(CAC!W16+I14) -> 4735.3293 | K13: =((J13*J14)+(CAC!X15*CAC!X16))/(CAC!X16+J14) -> 4769.3666 | ... O13: =((N13*N14)+(CAC!AB15*CAC!AB16))/(CAC!AB16+N14) -> 4863.3662
B14: Contratos Creators | C14: 53 | D14: =D12/D13 -> 59.126829 | E14: =E12/E13 -> 64.676821 | F14: =F12/F13 -> 69.708181 | G14: =G12/G13 -> 75.530355 | H14: =H12/H13 -> 80.814389 | I14: =I12/I13 -> 85.611599 | J14: =J12/J13 -> 91.474464 | K14: =K12/K13 -> 96.800517 | ... O14: =O12/O13 -> 117.7823 | Q14: Churn
B15: Churn Creators | C15: =$Q$15 -> 0.09 | D15: =$Q$15 -> 0.09 | E15: =$Q$15 -> 0.09 | F15: =$Q$15 -> 0.09 | G15: =$Q$15 -> 0.09 | H15: =$Q$15 -> 0.09 | I15: =$Q$15 -> 0.09 | J15: =$Q$15 -> 0.09 | ... O15: =$Q$15 -> 0.09 | Q15: 0.09
B17: MRR Social | C17: 180000 | D17: =((1-C20)*C17)+CAC!Q20 -> 206800 | E17: =((1-E20)*D17)+CAC!R20 -> 231188 | F17: =((1-F20)*E17)+CAC!S20 -> 253381.08 | G17: =((1-G20)*F17)+CAC!T20 -> 278576.78 | H17: =((1-H20)*G17)+CAC!U20 -> 301504.87 | I17: =((1-I20)*H17)+CAC!V20 -> 322369.43 | J17: =((1-J20)*I17)+CAC!W20 -> 347356.18 | K17: =((1-K20)*J17)+CAC!X20 -> 370094.13 | L17: =((1-L20)*K17)+CAC!Y20 -> 390785.66 | ... O17: =((1-O20)*N17)+CAC!AB20 -> 458770.74
B18: AOV Social | C18: =C17/C19 -> 2117.6471 | D18: =((C18*C19)+(CAC!Q21*CAC!Q22))/(CAC!Q22+C19) -> 2150.5241 | E18: =((D18*D19)+(CAC!R21*CAC!R22))/(CAC!R22+D19) -> 2174.8545 | F18: =((E18*E19)+(CAC!S21*CAC!S22))/(CAC!S22+E19) -> 2193.5725 | G18: =((F18*F19)+(CAC!T21*CAC!T22))/(CAC!T22+F19) -> 2209.8586 | H18: =((G18*G19)+(CAC!U21*CAC!U22))/(CAC!U22+G19) -> 2222.662 | I18: =((H18*H19)+(CAC!V21*CAC!V22))/(CAC!V22+H19) -> 2232.9738 | J18: =((I18*I19)+(CAC!W21*CAC!W22))/(CAC!W22+I19) -> 2242.3494 | K18: =((J18*J19)+(CAC!X21*CAC!X22))/(CAC!X22+J19) -> 2249.9371 | ... O18: =((N18*N19)+(CAC!AB21*CAC!AB22))/(CAC!AB22+N19) -> 2270.6225
B19: Contratos Social | C19: 85 | D19: =D17/D18 -> 96.162605 | E19: =E17/E18 -> 106.30044 | F19: =F17/F18 -> 115.51069 | G19: =G17/G18 -> 126.06091 | H19: =H17/H18 -> 135.65035 | I19: =I17/I18 -> 144.36776 | J19: =J17/J18 -> 154.90725 | K19: =K17/K18 -> 164.49087 | ... O19: =O17/O18 -> 202.04624 | Q19: Churn
B20: Churn Social | C20: =$Q$20 -> 0.09 | D20: =$Q$20 -> 0.09 | E20: =$Q$20 -> 0.09 | F20: =$Q$20 -> 0.09 | G20: =$Q$20 -> 0.09 | H20: =$Q$20 -> 0.09 | I20: =$Q$20 -> 0.09 | J20: =$Q$20 -> 0.09 | ... O20: =$Q$20 -> 0.09 | Q20: 0.09
B22: MRR Gestão de Comunidade | C22: 80000 | D22: =(((1-C25)*C22))+CAC!Q25 -> 105050 | E22: =(((1-D25)*D22))+CAC!R25 -> 127845.5 | F22: =(((1-E25)*E22))+CAC!S25 -> 148589.4 | G22: =(((1-F25)*F22))+CAC!T25 -> 171216.36 | H22: =(((1-G25)*G22))+CAC!U25 -> 191806.89 | I22: =(((1-H25)*H22))+CAC!V25 -> 210544.27 | J22: =(((1-I25)*I22))+CAC!W25 -> 232095.28 | K22: =(((1-J25)*J22))+CAC!X25 -> 251706.71 | ... O22: =(((1-N25)*N22))+CAC!AB25 -> 326341.9
B23: AOV Gestão de Comunidade | C23: =C22/C24 -> 7272.7273 | D23: =((C23*C24)+(CAC!Q27*CAC!Q26))/(CAC!Q27+C24) -> 7891.0369 | E23: =((D23*D24)+(CAC!R27*CAC!R26))/(CAC!R27+D24) -> 8302.3068 | F23: =((E23*E24)+(CAC!S27*CAC!S26))/(CAC!S27+E24) -> 8596.2889 | G23: =((F23*F24)+(CAC!T27*CAC!T26))/(CAC!T27+F24) -> 8838.2466 | H23: =((G23*G24)+(CAC!U27*CAC!U26))/(CAC!U27+G24) -> 9020.3063 | I23: =((H23*H24)+(CAC!V27*CAC!V26))/(CAC!V27+H24) -> 9162.1544 | J23: =((I23*I24)+(CAC!W27*CAC!W26))/(CAC!W27+I24) -> 9287.6928 | K23: =((J23*J24)+(CAC!X27*CAC!X26))/(CAC!X27+J24) -> 9387.0347 | ... O23: =((N23*N24)+(CAC!AB27*CAC!AB26))/(CAC!AB27+N24) -> 9648.5046
B24: Contratos Gestão de Comunidade | C24: 11 | D24: =D22/D23 -> 13.312572 | E24: =E22/E23 -> 15.398793 | F24: =F22/F23 -> 17.285297 | G24: =G22/G23 -> 19.372209 | H24: =H22/H23 -> 21.2639 | I24: =I22/I23 -> 22.979777 | J24: =J22/J23 -> 24.989552 | K24: =K22/K23 -> 26.814294 | ... O24: =O22/O23 -> 33.823055 | Q24: Churn
B25: Churn Gestão de Comunidade | C25: =$Q$25 -> 0.09 | D25: =$Q$25 -> 0.09 | E25: =$Q$25 -> 0.09 | F25: =$Q$25 -> 0.09 | G25: =$Q$25 -> 0.09 | H25: =$Q$25 -> 0.09 | I25: =$Q$25 -> 0.09 | J25: =$Q$25 -> 0.09 | ... O25: =$Q$25 -> 0.09 | Q25: 0.09
B27: MRR Others | C27: 77000 | D27: =((1-C30)*C27)+CAC!Q30 -> 91570 | E27: =((1-D30)*D27)+CAC!R30 -> 104828.7 | F27: =((1-E30)*E27)+CAC!S30 -> 116894.12 | G27: =((1-F30)*F27)+CAC!T30 -> 130373.65 | H27: =((1-G30)*G27)+CAC!U30 -> 142640.02 | I27: =((1-H30)*H27)+CAC!V30 -> 153802.42 | J27: =((1-I30)*I27)+CAC!W30 -> 166960.2 | K27: =((1-J30)*J27)+CAC!X30 -> 178933.78 | ... O27: =((1-N30)*N27)+CAC!AB30 -> 225193.19
B28: AOV Others | C28: =C27/C29 -> 1571.4286 | D28: =((C28*C29)+(CAC!Q31*CAC!Q32))/(CAC!Q32+C29) -> 1616.2261 | E28: =((D28*D29)+(CAC!R31*CAC!R32))/(CAC!R32+D29) -> 1648.2238 | F28: =((E28*E29)+(CAC!S31*CAC!S32))/(CAC!S32+E29) -> 1672.221 | G28: =((F28*F29)+(CAC!T31*CAC!T32))/(CAC!T32+F29) -> 1692.6893 | H28: =((G28*G29)+(CAC!U31*CAC!U32))/(CAC!U32+G29) -> 1708.5248 | I28: =((H28*H29)+(CAC!V31*CAC!V32))/(CAC!V32+H29) -> 1721.122 | J28: =((I28*I29)+(CAC!W31*CAC!W32))/(CAC!W32+I29) -> 1732.4592 | K28: =((J28*J29)+(CAC!X31*CAC!X32))/(CAC!X32+J29) -> 1741.5559 | ... O28: =((N28*N29)+(CAC!AB31*CAC!AB32))/(CAC!AB32+N29) -> 1766.0172
B29: Contratos Others | C29: =22+3+8+5+11 -> 49 | D29: =D27/D28 -> 56.656678 | E29: =E27/E28 -> 63.601012 | F29: =F27/F28 -> 69.903509 | G29: =G27/G28 -> 77.021603 | H29: =H27/H28 -> 83.48724 | I29: =I27/I28 -> 89.361717 | J29: =J27/J28 -> 96.371793 | K29: =K27/K28 -> 102.74364 | ... O29: =O27/O28 -> 127.51472 | Q29: Churn
B30: Churn Others | C30: =$Q$30 -> 0.09 | D30: =$Q$30 -> 0.09 | E30: =$Q$30 -> 0.09 | F30: =$Q$30 -> 0.09 | G30: =$Q$30 -> 0.09 | H30: =$Q$30 -> 0.09 | I30: =$Q$30 -> 0.09 | J30: =$Q$30 -> 0.09 | ... O30: =$Q$30 -> 0.09 | Q30: 0.09
B32: Churn Total | C32: =(Revenue!C7*Revenue!C10)+(Revenue!C12*Revenue!C15)+(Revenue!C17*Revenue!C20)+(Revenue!C22*Revenue!C25)+(Revenue!C27*Revenue!C30) -> 93150 | D32: =(Revenue!D7*Revenue!D10)+(Revenue!D12*Revenue!D15)+(Revenue!D17*Revenue!D20)+(Revenue!D22*Revenue!D25)+(Revenue!D27*Revenue!D30) -> 104116.5 | E32: =(Revenue!E7*Revenue!E10)+(Revenue!E12*Revenue!E15)+(Revenue!E17*Revenue!E20)+(Revenue!E22*Revenue!E25)+(Revenue!E27*Revenue!E30) -> 114096.01 | F32: =(Revenue!F7*Revenue!F10)+(Revenue!F12*Revenue!F15)+(Revenue!F17*Revenue!F20)+(Revenue!F22*Revenue!F25)+(Revenue!F27*Revenue!F30) -> 123177.37 | G32: =(Revenue!G7*Revenue!G10)+(Revenue!G12*Revenue!G15)+(Revenue!G17*Revenue!G20)+(Revenue!G22*Revenue!G25)+(Revenue!G27*Revenue!G30) -> 133691.41 | H32: =(Revenue!H7*Revenue!H10)+(Revenue!H12*Revenue!H15)+(Revenue!H17*Revenue!H20)+(Revenue!H22*Revenue!H25)+(Revenue!H27*Revenue!H30) -> 143259.18 | I32: =(Revenue!I7*Revenue!I10)+(Revenue!I12*Revenue!I15)+(Revenue!I17*Revenue!I20)+(Revenue!I22*Revenue!I25)+(Revenue!I27*Revenue!I30) -> 151965.86 | J32: =(Revenue!J7*Revenue!J10)+(Revenue!J12*Revenue!J15)+(Revenue!J17*Revenue!J20)+(Revenue!J22*Revenue!J25)+(Revenue!J27*Revenue!J30) -> 162588.93 | ... O32: =(Revenue!O7*Revenue!O10)+(Revenue!O12*Revenue!O15)+(Revenue!O17*Revenue!O20)+(Revenue!O22*Revenue!O25)+(Revenue!O27*Revenue!O30) -> 210364.91
B34: Receita Pontual
B35: Trimestre | C35: Bookado | D35: 1 Trimestre | G35: 2 Trimestre | J35: 3 Trimestre | M35: 4 Trimestre
B36: Mês | C36: Dezembro | D36: Janeiro | E36: Feveiro | F36: Março | G36: Abril | H36: Maio | I36: Junho | J36: Julho | K36: Agosto | L36: Setembro | M36: Outubro | N36: Novembro | O36: Dezembro
B37: Receita Pontual | D37: =(CAC!Q38/3)+150000 -> 240000 | E37: =((CAC!Q38/3)+(CAC!R38/3))+100000 -> 280000 | F37: =(CAC!R38/3)+(CAC!S38/3)+(CAC!Q38/3) -> 270000 | G37: =(CAC!S38/3)+(CAC!T38/3)+(CAC!R38/3) -> 288333.33 | H37: =(CAC!T38/3)+(CAC!U38/3)+(CAC!S38/3) -> 306666.67 | I37: =(CAC!U38/3)+(CAC!V38/3)+(CAC!T38/3) -> 325000 | J37: =(CAC!V38/3)+(CAC!W38/3)+(CAC!U38/3) -> 343333.33 | K37: =(CAC!W38/3)+(CAC!X38/3)+(CAC!V38/3) -> 361666.67 | L37: =(CAC!X38/3)+(CAC!Y38/3)+(CAC!W38/3) -> 380000 | M37: =(CAC!Y38/3)+(CAC!Z38/3)+(CAC!X38/3) -> 398333.33 | ... O37: =(CAC!AA38/3)+(CAC!AB38/3)+(CAC!Z38/3) -> 435000

Sheet CAPEX e Giro
B2: CAPEX
B3: Trimestre | D3: 1 Trimestre | G3: 2 Trimestre | J3: 3 Trimestre | M3: 4 Trimestre
B4: Mês | C4: Dezembro | D4: Janeiro | E4: Feveiro | F4: Março | G4: Abril | H4: Maio | I4: Junho | J4: Julho | K4: Agosto | L4: Setembro | M4: Outubro | N4: Novembro | O4: Dezembro
B5: (=) CAPEX | D5: =IF(7000*D9>0, 7000*D9, 0) -> 35000 | E5: =IF(7000*E9>0, 7000*E9, 0) -> 35000 | F5: =IF(7000*F9>0, 7000*F9, 0) -> 35000 | G5: =IF(7000*G9>0, 7000*G9, 0) -> 35000 | H5: =IF(7000*H9>0, 7000*H9, 0) -> 35000 | I5: =IF(7000*I9>0, 7000*I9, 0) -> 35000 | J5: =IF(7000*J9>0, 7000*J9, 0) -> 35000 | K5: =IF(7000*K9>0, 7000*K9, 0) -> 35000 | ... O5: =IF(7000*O9>0, 7000*O9, 0) -> 35000
B6: (=) Colaboradores totais | D6: ='Overview Old'!C26 -> 110 | E6: ='Overview Old'!D26 -> 118 | F6: ='Overview Old'!E26 -> 123 | G6: ='Overview Old'!F26 -> 135 | H6: ='Overview Old'!G26 -> 139 | I6: ='Overview Old'!H26 -> 141 | J6: ='Overview Old'!I26 -> 147 | K6: ='Overview Old'!J26 -> 152 | ... O6: ='Overview Old'!N26 -> 169
B7: (=) Computadores totais | D7: 76 | E7: =D7+D9 -> 81 | F7: =E7+E9 -> 86 | G7: =F7+F9 -> 91 | H7: =G7+G9 -> 96 | I7: =H7+H9 -> 101 | J7: =I7+I9 -> 106 | K7: =J7+J9 -> 111 | L7: =K7+K9 -> 116 | ... O7: =N7+N9 -> 131
B8: (=) Computadores a comprar | D8: =D6-D7 -> 34 | E8: =E6-E7 -> 37 | F8: =F6-F7 -> 37 | G8: =G6-G7 -> 44 | H8: =H6-H7 -> 43 | I8: =I6-I7 -> 40 | J8: =J6-J7 -> 41 | K8: =K6-K7 -> 41 | ... O8: =O6-O7 -> 38
B9: (-) Computadores comprados mês | D9: 5 | E9: 5 | F9: 5 | G9: 5 | H9: 5 | I9: 5 | J9: 5 | K9: 5 | L9: 5 | M9: 5 | N9: 5 | O9: 5

Sheet Tributário
B2: 1 Trimestre | E2: Trimestre | F2: 1 Trimestre | I2: 2 Trimestre | L2: 3 Trimestre | O2: 4 Trimestre
B3: % NF Emitida | C3: 0.95 | E3: Mês | F3: Janeiro | G3: Feveiro | H3: Março | I3: Abril | J3: Maio | K3: Junho | L3: Julho | M3: Agosto | N3: Setembro | O3: Outubro | P3: Novembro | Q3: Dezembro
B4: Simples Nacional | C4: 0.14 | E4: Receita Total | F4: ='Overview Old'!C7 -> 1417616.7 | G4: ='Overview Old'!D7 -> 1608141.5 | H4: ='Overview Old'!E7 -> 1664264.2 | I4: ='Overview Old'!F7 -> 1816870.1 | J4: ='Overview Old'!G7 -> 1988532 | K4: ='Overview Old'!H7 -> 2062292.9 | L4: ='Overview Old'!I7 -> 2235450.3 | M4: ='Overview Old'!J7 -> 2411334.7 | ... Q4: ='Overview Old'!N7 -> 2909394.5
B5: ISS | C5: 0.05 | E5: Receita NF | F5: =F4*$C$3 -> 1346735.8 | G5: =G4*$C$3 -> 1527734.4 | H5: =H4*$C$3 -> 1581050.9 | I5: =I4*$C$10 -> 1726026.6 | J5: =J4*$C$10 -> 1889105.4 | K5: =K4*$C$10 -> 1959178.2 | L5: =L4*$C$17 -> 2123677.8 | M5: =M4*$C$17 -> 2290768 | N5: =N4*$C$17 -> 2347208.2 | O5: =O4*$C$24 -> 2532686.6 | P5: =P4*$C$24 -> 2690933.1 | Q5: =Q4*$C$24 -> 2763924.8
B6: PIS/COFINS | C6: 0.05 | E6: Receita Bruta Peixoto | F6: =160000/0.92 -> 173913.04 | G6: =160000/0.92 -> 173913.04 | H6: =160000/0.92 -> 173913.04 | I6: =160000/0.92 -> 173913.04 | J6: =160000/0.92 -> 173913.04 | K6: =160000/0.92 -> 173913.04 | L6: =160000/0.92 -> 173913.04 | M6: =160000/0.92 -> 173913.04 | ... Q6: =160000/0.92 -> 173913.04
B7: CSLL + IRPJ | C7: 0.34 | E7: (=) Receita Liquida Peixoto | F7: =F6*(1-'Overview Old'!$S$3) -> 163478.26 | G7: =G6*(1-'Overview Old'!$S$3) -> 163478.26 | H7: =H6*(1-'Overview Old'!$S$3) -> 163478.26 | I7: =I6*(1-'Overview Old'!$S$6) -> 163478.26 | J7: =J6*(1-'Overview Old'!$S$6) -> 163478.26 | K7: =K6*(1-'Overview Old'!$S$6) -> 163478.26 | L7: =L6*(1-'Overview Old'!$S$9) -> 163478.26 | M7: =M6*(1-'Overview Old'!$S$9) -> 163478.26 | N7: =N6*(1-'Overview Old'!$S$9) -> 163478.26 | O7: =O6*(1-'Overview Old'!$S$12) -> 163478.26 | P7: =P6*(1-'Overview Old'!$S$12) -> 163478.26 | Q7: =Q6*(1-'Overview Old'!$S$12) -> 163478.26
E8: Receita Bruta Turbo Partners | F8: =F5-F6 -> 1172822.8 | G8: =G5-G6 -> 1353821.4 | H8: =H5-H6 -> 1407137.9 | I8: =I5-I6 -> 1552113.6 | J8: =J5-J6 -> 1715192.4 | K8: =K5-K6 -> 1785265.2 | L8: =L5-L6 -> 1949764.8 | M8: =M5-M6 -> 2116855 | ... Q8: =Q5-Q6 -> 2590011.8
B9: 2 Trimestre | E9: (=) Receita Liquida Turbo | F9: =F8*(1-'Overview Old'!$S$3) -> 1102453.4 | G9: =G8*(1-'Overview Old'!$S$3) -> 1272592.1 | H9: =H8*(1-'Overview Old'!$S$3) -> 1322709.6 | I9: =I8*(1-'Overview Old'!$S$6) -> 1458986.7 | J9: =J8*(1-'Overview Old'!$S$6) -> 1612280.8 | K9: =K8*(1-'Overview Old'!$S$6) -> 1678149.3 | L9: =L8*(1-'Overview Old'!$S$9) -> 1832778.9 | M9: =M8*(1-'Overview Old'!$S$9) -> 1989843.7 | N9: =N8*(1-'Overview Old'!$S$9) -> 2042897.4 | O9: =O8*(1-'Overview Old'!$S$12) -> 2217247.2 | P9: =P8*(1-'Overview Old'!$S$12) -> 2365998.8 | Q9: =Q8*(1-'Overview Old'!$S$12) -> 2434611.1
B10: % NF Emitida | C10: 0.95
B11: Simples Nacional | C11: 0.15 | E11: (-) Simples Nacional | F11: =F7*$C$4 -> 22886.957 | G11: =G7*$C$4 -> 22886.957 | H11: =H7*$C$4 -> 22886.957 | I11: =I7*$C$11 -> 24521.739 | J11: =J7*$C$11 -> 24521.739 | K11: =K7*$C$11 -> 24521.739 | L11: =L7*$C$18 -> 24521.739 | M11: =M7*$C$18 -> 24521.739 | N11: =N7*$C$18 -> 24521.739 | O11: =O7*$C$25 -> 24521.739 | P11: =P7*$C$25 -> 24521.739 | Q11: =Q7*$C$25 -> 24521.739
B12: ISS | C12: 0.05 | E12: (-) ISS | F12: =(F9*$C$5) -> 55122.671 | G12: =(G9*$C$5) -> 63629.605 | H12: =(H9*$C$5) -> 66135.481 | I12: =(I9*$C$12) -> 72949.337 | J12: =(J9*$C$12) -> 80614.042 | K12: =(K9*$C$12) -> 83907.463 | L12: =(L9*$C$19) -> 91638.944 | M12: =(M9*$C$19) -> 99492.183 | N12: =(N9*$C$19) -> 102144.87 | O12: =(O9*$C$26) -> 110862.36 | P12: =(P9*$C$26) -> 118299.94 | Q12: =(Q9*$C$26) -> 121730.55
B13: PIS/COFINS | C13: 0.05 | E13: (-) PIS/COFINS | F13: =F9*$C$6 -> 55122.671 | G13: =G9*$C$6 -> 63629.605 | H13: =H9*$C$6 -> 66135.481 | I13: =I9*$C$13 -> 72949.337 | J13: =J9*$C$13 -> 80614.042 | K13: =K9*$C$13 -> 83907.463 | L13: =L9*$C$20 -> 91638.944 | M13: =M9*$C$20 -> 99492.183 | N13: =N9*$C$20 -> 102144.87 | O13: =O9*$C$27 -> 110862.36 | P13: =P9*$C$27 -> 118299.94 | Q13: =Q9*$C$27 -> 121730.55
B14: CSLL + IRPJ | C14: 0.34 | E14: (-) CSLL + IRPJ | F14: ='Overview Old'!C15*$C$7 -> 99528.628 | G14: ='Overview Old'!D15*$C$7 -> 136974.72 | H14: ='Overview Old'!E15*$C$7 -> 137235.61 | I14: ='Overview Old'!F15*$C$14 -> 150356.42 | J14: ='Overview Old'!G15*$C$14 -> 162404.02 | K14: ='Overview Old'!H15*$C$14 -> 199890.68 | L14: ='Overview Old'!I15*$C$21 -> 191918.63 | M14: ='Overview Old'!J15*$C$21 -> 266072.17 | N14: ='Overview Old'!K15*$C$21 -> 273252.22 | O14: ='Overview Old'!L15*$C$28 -> 292957.78 | P14: ='Overview Old'!M15*$C$28 -> 337002.56 | Q14: ='Overview Old'!N15*$C$28 -> 335508.25
B16: 3 Trimestre | E16: Alíquota Efetiva | F16: =SUM(F11:F14)/F4 -> 0.16412118 | G16: =SUM(G11:G14)/G4 -> 0.17854206 | H16: =SUM(H11:H14)/H4 -> 0.17568937 | I16: =SUM(I11:I14)/I4 -> 0.17655463 | J16: =SUM(J11:J14)/J4 -> 0.17508083 | K16: =SUM(K11:K14)/K4 -> 0.19018993 | L16: =SUM(L11:L14)/L4 -> 0.17880883 | M16: =SUM(M11:M14)/M4 -> 0.20303207 | ... Q16: =SUM(Q11:Q14)/Q4 -> 0.20742841
B17: % NF Emitida | C17: 0.95
B18: Simples Nacional | C18: 0.15 | E18: Turbo Partners LTDA | F18: =(F12+F13+F14)/F8 -> 0.17886246 | G18: =(G12+G13+G14)/G8 -> 0.19517636 | H18: =(H12+H13+H14)/H8 -> 0.19152819 | I18: =(I12+I13+I14)/I8 -> 0.19087205 | J18: =(J12+J13+J14)/J8 -> 0.1886856 | K18: =(K12+K13+K14)/K8 -> 0.20596694 | L18: =(L12+L13+L14)/L8 -> 0.19243169 | M18: =(M12+M13+M14)/M8 -> 0.21969221 | ... Q18: =(Q12+Q13+Q14)/Q8 -> 0.22353928
B19: ISS | C19: 0.05 | E19: Peixoto Debanne | F19: =(F11)/F6 -> 0.1316 | G19: =(G11)/G6 -> 0.1316 | H19: =(H11)/H6 -> 0.1316 | I19: =(I11)/I6 -> 0.141 | J19: =(J11)/J6 -> 0.141 | K19: =(K11)/K6 -> 0.141 | L19: =(L11)/L6 -> 0.141 | M19: =(M11)/M6 -> 0.141 | ... Q19: =(Q11)/Q6 -> 0.141
B20: PIS/COFINS | C20: 0.05
B21: CSLL + IRPJ | C21: 0.34
B23: 4 Trimestre
B24: % NF Emitida | C24: 0.95
B25: Simples Nacional | C25: 0.15
B26: ISS | C26: 0.05
B27: PIS/COFINS | C27: 0.05
B28: CSLL + IRPJ | C28: 0.34

Sheet Turbooh
C2: Janeiro | D2: Feveiro | E2: Março | F2: Abril | G2: Maio | H2: Junho | I2: Julho | J2: Agosto | K2: Setembro | L2: Outubro | M2: Novembro | N2: Dezembro
B3: Número de Telas | C3: 40 | D3: 60 | E3: 100 | F3: 150 | G3: 150 | H3: 150 | I3: 200 | J3: 200 | K3: 200 | L3: 300 | M3: 300 | N3: 300
B4: AOV por Slot | C4: 120 | D4: 120 | E4: 120 | F4: 120 | G4: 120 | H4: 120 | I4: 130 | J4: 130 | K4: 130 | L4: 135 | M4: 135 | N4: 135
B5: Ocupacao | C5: 0.25 | D5: 0.3 | E5: 0.35 | F5: 0.4 | G5: 0.45 | H5: 0.5 | I5: 0.55 | J5: 0.6 | K5: 0.6 | L5: 0.6 | M5: 0.6 | N5: 0.6
B6: Receita Bruta | C6: =C3*C4*12*C5 -> 14400 | D6: =D3*D4*12*D5 -> 25920 | E6: =E3*E4*12*E5 -> 50400 | F6: =F3*F4*12*F5 -> 86400 | G6: =G3*G4*12*G5 -> 97200 | H6: =H3*H4*12*H5 -> 108000 | I6: =I3*I4*12*I5 -> 171600 | J6: =J3*J4*12*J5 -> 187200 | ... N6: =N3*N4*12*N5 -> 291600
B7: (-) Impostos | C7: =C6*0.15 -> 2160 | D7: =D6*0.15 -> 3888 | E7: =E6*0.15 -> 7560 | F7: =F6*0.15 -> 12960 | G7: =G6*0.15 -> 14580 | H7: =H6*0.15 -> 16200 | I7: =I6*0.15 -> 25740 | J7: =J6*0.15 -> 28080 | ... N7: =N6*0.15 -> 43740
B8: (-) Comissões | C8: =C6*0.2 -> 2880 | D8: =D6*0.2 -> 5184 | E8: =E6*0.2 -> 10080 | F8: =F6*0.2 -> 17280 | G8: =G6*0.2 -> 19440 | H8: =H6*0.2 -> 21600 | I8: =I6*0.2 -> 34320 | J8: =J6*0.2 -> 37440 | ... N8: =N6*0.2 -> 58320
B9: (=) Receita Líquida | C9: =C6-C7-C8 -> 9360 | D9: =D6-D7-D8 -> 16848 | E9: =E6-E7-E8 -> 32760 | F9: =F6-F7-F8 -> 56160 | G9: =G6-G7-G8 -> 63180 | H9: =H6-H7-H8 -> 70200 | I9: =I6-I7-I8 -> 111540 | J9: =J6-J7-J8 -> 121680 | ... N9: =N6-N7-N8 -> 189540
B10: (-) ADMooh | C10: =59*C3 -> 2360 | D10: =59*D3 -> 3540 | E10: =59*E3 -> 5900 | F10: =59*F3 -> 8850 | G10: =59*G3 -> 8850 | H10: =59*H3 -> 8850 | I10: =59*I3 -> 11800 | J10: =59*J3 -> 11800 | ... N10: =59*N3 -> 17700
B11: (=) Lucro Bruto | C11: =C9-C10 -> 7000 | D11: =D9-D10 -> 13308 | E11: =E9-E10 -> 26860 | F11: =F9-F10 -> 47310 | G11: =G9-G10 -> 54330 | H11: =H9-H10 -> 61350 | I11: =I9-I10 -> 99740 | J11: =J9-J10 -> 109880 | ... N11: =N9-N10 -> 171840
B12: (-) Equipe | C12: 3400 | D12: 3400 | E12: 3400 | F12: 7400 | G12: 7400 | H12: 7400 | I12: 10000 | J12: 10000 | K12: 10000 | L12: 15000 | M12: 15000 | N12: 15000
B13: (-) CAPEX | C13: =((D3-C3)*2000)/12 -> 3333.3333 | D13: =(((D3-C3)*2000)/12)+((E3-D3)*2000)/12 -> 10000 | E13: =(((D3-C3)*2000)/12)+((E3-D3)*2000)/12+((F3-E3)*2000)/12 -> 18333.333 | F13: =(((D3-C3)*2000)/12)+((E3-D3)*2000)/12+((F3-E3)*2000)/12+((G3-F3)*2000)/12 -> 18333.333 | G13: =(((D3-C3)*2000)/12)+((E3-D3)*2000)/12+((F3-E3)*2000)/12+((G3-F3)*2000)/12+((H3-G3)*2000)/12 -> 18333.333 | H13: =(((D3-C3)*2000)/12)+((E3-D3)*2000)/12+((F3-E3)*2000)/12+((G3-F3)*2000)/12+((H3-G3)*2000)/12+((I3-H3)*2000)/12 -> 26666.667 | I13: =(((D3-C3)*2000)/12)+((E3-D3)*2000)/12+((F3-E3)*2000)/12+((G3-F3)*2000)/12+((H3-G3)*2000)/12+((I3-H3)*2000)/12+((J3-I3)*2000)/12 -> 26666.667 | J13: =(((D3-C3)*2000)/12)+((E3-D3)*2000)/12+((F3-E3)*2000)/12+((G3-F3)*2000)/12+((H3-G3)*2000)/12+((I3-H3)*2000)/12+((J3-I3)*2000)/12+((K3-J3)*2000)/12 -> 26666.667 | K13: =((((D3-C3)*2000)/12)+((E3-D3)*2000)/12+((F3-E3)*2000)/12+((G3-F3)*2000)/12+((H3-G3)*2000)/12+((I3-H3)*2000)/12+((J3-I3)*2000)/12+((K3-J3)*2000)/12+((L3-K3)*2000)/12) -> 43333.333 | L13: =((((D3-C3)*2000)/12)+((E3-D3)*2000)/12+((F3-E3)*2000)/12+((G3-F3)*2000)/12+((H3-G3)*2000)/12+((I3-H3)*2000)/12+((J3-I3)*2000)/12+((K3-J3)*2000)/12+((L3-K3)*2000)/12)+((M3-L3)*2000)/12 -> 43333.333 | M13: =((((D3-C3)*2000)/12)+((E3-D3)*2000)/12+((F3-E3)*2000)/12+((G3-F3)*2000)/12+((H3-G3)*2000)/12+((I3-H3)*2000)/12+((J3-I3)*2000)/12+((K3-J3)*2000)/12+((L3-K3)*2000)/12)+((M3-L3)*2000)/12+((N3-M3)*2000)/12 -> 43333.333 | N13: =((((D3-C3)*2000)/12)+((E3-D3)*2000)/12+((F3-E3)*2000)/12+((G3-F3)*2000)/12+((H3-G3)*2000)/12+((I3-H3)*2000)/12+((J3-I3)*2000)/12+((K3-J3)*2000)/12+((L3-K3)*2000)/12)+((M3-L3)*2000)/12+((N3-M3)*2000)/12 -> 43333.333
B14: (=) Resultado | C14: =C11-C12-C13 -> 266.66667 | D14: =D11-D12-D13 -> -92 | E14: =E11-E12-E13 -> 5126.6667 | F14: =F11-F12-F13 -> 21576.667 | G14: =G11-G12-G13 -> 28596.667 | H14: =H11-H12-H13 -> 27283.333 | I14: =I11-I12-I13 -> 63073.333 | J14: =J11-J12-J13 -> 73213.333 | ... N14: =N11-N12-N13 -> 113506.67
B16: Tela Totais | C16: =C3 -> 40 | D16: =D3 -> 60 | E16: =E3 -> 100 | F16: =F3 -> 150 | G16: =G3 -> 150 | H16: =H3 -> 150 | I16: =I3 -> 200 | J16: =J3 -> 200 | ... N16: =N3 -> 300
B17: Anuncios Totais | C17: =C16*12*C5 -> 120 | D17: =D16*12*D5 -> 216 | E17: =E16*12*E5 -> 420 | F17: =F16*12*F5 -> 720 | G17: =G16*12*G5 -> 810 | H17: =H16*12*H5 -> 900 | I17: =I16*12*I5 -> 1320 | J17: =J16*12*J5 -> 1440 | ... N17: =N16*12*N5 -> 2160
B18: Locais Totais | C18: =C17/3 -> 40 | D18: =D17/3 -> 72 | E18: =E17/3 -> 140 | F18: =F17/3 -> 240 | G18: =G17/3 -> 270 | H18: =H17/3 -> 300 | I18: =I17/3 -> 440 | J18: =J17/3 -> 480 | ... N18: =N17/3 -> 720
B19: AOV Local | C19: =C6/C18 -> 360 | D19: =D6/D18 -> 360 | E19: =E6/E18 -> 360 | F19: =F6/F18 -> 360 | G19: =G6/G18 -> 360 | H19: =H6/H18 -> 360 | I19: =I6/I18 -> 390 | J19: =J6/J18 -> 390 | ... N19: =N6/N18 -> 405
B20: Clientes Totais | C20: =C18/1.7 -> 23.529412 | D20: =D18/1.7 -> 42.352941 | E20: =E18/1.7 -> 82.352941 | F20: =F18/1.9 -> 126.31579 | G20: =G18/1.9 -> 142.10526 | H20: =H18/1.9 -> 157.89474 | I20: =I18/2 -> 220 | J20: =J18/2 -> 240 | K20: =K18/2 -> 240 | L20: =L18/2.1 -> 342.85714 | M20: =M18/2.1 -> 342.85714 | N20: =N18/2.1 -> 342.85714
B23: Edifício | C23: Telas | D23: Valor | E23: Valor por Tela
B24: APEX Empresarial | C24: 2 | D24: 547 | E24: =D24/C24 -> 273.5
B25: Edifício Churchill | C25: 1 | D25: 197 | E25: =D25/C25 -> 197
B26: Escritório Turbo | C26: 3 | D26: 297 | E26: =D26/C26 -> 99
B27: Residencial Jardins | C27: 11 | D27: 1497 | E27: =D27/C27 -> 136.09091
B28: Vértice Empresarial | C28: 8 | D28: 1197 | E28: =D28/C28 -> 149.625
B29: Signature | C29: 1 | D29: 297 | E29: =D29/C29 -> 297
B31: Média | C31: =AVERAGE(C24:C29) -> 4.3333333 | D31: =AVERAGE(D24:D29) -> 672 | E31: =AVERAGE(E24:E29) -> 192.03598

Sheet Outras Receitas
C2: Janeiro | D2: Fevereiro | E2: Março | F2: abril | G2: maio | H2: junho | I2: julho | J2: agosto | K2: setembro | L2: outubro | M2: novembro | N2: dezembro
B3: Receita Variavel | C3: 10000 | D3: 10000 | E3: 10000 | F3: 10000 | G3: 10000 | H3: 10000 | I3: 10000 | J3: 10000 | K3: 10000 | L3: 10000 | M3: 10000 | N3: 10000
B4: DR Rafael | D4: 40000 | G4: 40000 | J4: 40000 | M4: 40000
B5: Mentoria | C5: 3500 | D5: 3500 | E5: 3500 | F5: 3500 | G5: 3500 | H5: 3500 | I5: 3500 | J5: 3500 | K5: 3500 | L5: 3500 | M5: 3500 | N5: 3500
B6: Infoproduto Turbo | C6: 2000 | D6: 2000 | E6: 2000 | F6: 2000 | G6: 2000 | H6: 2000 | I6: 2000 | J6: 2000 | K6: 2000 | L6: 2000 | M6: 2000 | N6: 2000
B7: Stack Digital | C7: 5000 | D7: 5000 | E7: 5000 | F7: 6000 | G7: 6000 | H7: 6000 | I7: 7000 | J7: 7000 | K7: 7000 | L7: 8000 | M7: 8000 | N7: 8000
B8: Tools
B9: Estruturação Estrategica
B10: Estruturação Comercial
B11: CMO AS A SERVICE
B12: SAAS
B13: Turbooh | C13: =Turbooh!C14 -> 266.66667 | D13: =Turbooh!D14 -> -92 | E13: =Turbooh!E14 -> 5126.6667 | F13: =Turbooh!F14 -> 21576.667 | G13: =Turbooh!G14 -> 28596.667 | H13: =Turbooh!H14 -> 27283.333 | I13: =Turbooh!I14 -> 63073.333 | J13: =Turbooh!J14 -> 73213.333 | ... N13: =Turbooh!N14 -> 113506.67
B14: Ventures
B15: TOTAL | C15: =sum(C3:C14) -> 20766.667 | D15: =sum(D3:D14) -> 60408 | E15: =sum(E3:E14) -> 25626.667 | F15: =sum(F3:F14) -> 43076.667 | G15: =sum(G3:G14) -> 90096.667 | H15: =sum(H3:H14) -> 48783.333 | I15: =sum(I3:I14) -> 85573.333 | J15: =sum(J3:J14) -> 135713.33 | ... N15: =sum(N3:N14) -> 137006.67

Sheet Eventos
B2: (-) ADs | C2: 80000 | D2: 100000 | E2: 100000 | F2: 110000 | G2: 110000 | H2: 110000 | I2: 120000 | J2: 120000 | K2: 120000 | L2: 130000 | M2: 130000 | N2: 130000 | O2: =SUM(C2:N2) -> 1360000
B3: (-) Eventos | C3: 5000 | D3: 5000 | E3: 25000 | F3: 15000 | G3: 100000 | H3: 40000 | I3: 100000 | J3: 15000 | K3: 25000 | L3: 20000 | M3: 5000 | N3: 25000 | O3: =SUM(C3:N3) -> 380000
B4: (-) Brindes | C4: 10000 | D4: 10000 | E4: 10000 | F4: 10000 | G4: 10000 | H4: 10000 | I4: 15000 | J4: 15000 | K4: 15000 | L4: 30000 | M4: 30000 | N4: 30000 | O4: =SUM(C4:N4) -> 195000
B5: Total | C5: =SUM(C2:C4) -> 95000 | D5: =SUM(D2:D4) -> 115000 | E5: =SUM(E2:E4) -> 135000 | F5: =SUM(F2:F4) -> 135000 | G5: =SUM(G2:G4) -> 220000 | H5: =SUM(H2:H4) -> 160000 | I5: =SUM(I2:I4) -> 235000 | J5: =SUM(J2:J4) -> 150000 | ... N5: =SUM(N2:N4) -> 185000 | O5: =SUM(C5:N5) -> 1935000
B7: EVENTOS
B8: Trimestre | C8: 1 Trimestre | F8: 2 Trimestre | I8: 3 Trimestre | L8: 4 Trimestre
B9: Mês | C9: Janeiro | D9: Fevereiro | E9: Março | F9: Abril | G9: Maio | H9: Junho | I9: Julho | J9: Agosto | K9: Setembro | L9: Outubro | M9: Novembro | N9: Dezembro
B10: (=) Custo | C10: 0 | D10: =SUM(D11:D60) -> 5000 | E10: =SUM(E11:E60) -> 25000 | F10: =SUM(F11:F60) -> 15000 | G10: =SUM(G11:G60) -> 100000 | H10: =SUM(H11:H60) -> 40000 | I10: =SUM(I11:I60) -> 100000 | J10: =SUM(J11:J60) -> 15000 | K10: =SUM(K11:K60) -> 25000 | ... N10: =SUM(N11:N60) -> 25000
B11: Turbo One
B12: - Aluguel do Espaço
B13: - Buffet
B14: - Bebidas
B15: - Audiovisual
B16: - Palestrante
B17: - Papelaria
B18: - Brindes
B19: - Midia/divulgação
B20: Expositor | G20: 100000 | I20: 100000
B21: - Quantas pessoas vão?
B22: - Quantos dias?
B23: - Hospedagem
B24: - Passagem
B25: - Ingresso
B26: - Locomoção
B27: - Stand
B28: - Midia/divulgação
B29: E-commerce BR (Expositor)
B30: - Stand
B31: - Papelaria
B32: - Plotagem Stand
... B37: - Midia/divulgação
B38: Participante | F38: 10000 | H38: 10000 | J38: 10000
B39: - Quantas pessoas vão?
B40: - Quantos dias?
B41: - Hospedagem
B42: - Passagem
B43: - Ingresso
B44: - Locomoção
B45: - Midia/divulgação
B46: Turbo Day | E46: 25000 | H46: 25000 | K46: 25000 | N46: 25000
B47: - Aluguel do Espaço
B48: - Buffet
B49: - Bebida
B50: - Palestrantes
B51: - Papelaria
B52: - Ativação/sorteio
B53: - Audiovisual
B54: - Midia/divulgação
B55: Workshop | D55: 5000 | F55: 5000 | H55: 5000 | J55: 5000 | L55: 5000 | M55: 5000
B58: Patrocínio | L58: 15000
C61: =SUM(C11:C58)/0.2 -> 0 | D61: =SUM(D11:D58)/0.2 -> 25000 | E61: =SUM(E11:E58)/0.2 -> 125000 | F61: =SUM(F11:F58)/0.2 -> 75000 | G61: =SUM(G11:G58)/0.2 -> 500000 | H61: =SUM(H11:H58)/0.2 -> 200000 | I61: =SUM(I11:I58)/0.2 -> 500000 | J61: =SUM(J11:J58)/0.2 -> 75000 | ... N61: =SUM(N11:N58)/0.2 -> 125000
G62: =G61/5 -> 100000 | H62: =H61/5 -> 40000
B64: Turbo Day | C64: 100000 | D64: 4x | E64: coco bambu
B65: Turbo One | C65: 300000 | D65: 1x | E65: BIG EVENT
B66: Expositor | C66: 200000 | D66: 2x | E66: ecom brasil e naturaltech
B67: Patrocinio | C67: 15000 | D67: 1x | E67: focar em pegar o master
B68: Participante | C68: 30000 | D68: 3x | E68: mandar vendedor pra evento
B69: Workshop | C69: 30000 | D69: 5k por evento | E69: 1 a cada 2 meses
B71: Ecommerce Brasil | C71: 100000
B72: Creator Summit | C72: 80000
B73: Natural Tech | C73: 50000
B74: Influencer Summit | C74: 60000 | F74: Arnold | G74: 45k | H74: Permuta
B75: Eventos Internos Turbo | C75: =2000*12 -> 24000 | F75: Zoppy | G75: 20k
B76: Eventos no ES | F76: CMO Summit | G76: 2000

Sheet Gente e Gestão
C1: Janeiro | D1: Feveiro | E1: Março | F1: Abril | G1: Maio | H1: Junho | I1: Julho | J1: Agosto | K1: Setembro | L1: Outubro | M1: Novembro | N1: Dezembro | R1: Janeiro | S1: Feveiro | T1: Março | U1: Abril | V1: Maio | W1: Junho | X1: Julho | Y1: Agosto | Z1: Setembro | AA1: Outubro | AB1: Novembro | AC1: Dezembro
B2: Gestor de Performance | C2: =count(CSV!D25:D50) -> 17 | D2: =count(CSV!E25:E50) -> 19 | E2: =count(CSV!F25:F50) -> 20 | F2: =count(CSV!G25:G50) -> 20 | G2: =count(CSV!H25:H50) -> 21 | H2: =count(CSV!I25:I50) -> 21 | I2: =count(CSV!J25:J50) -> 22 | J2: =count(CSV!K25:K50) -> 22 | ... N2: =count(CSV!O25:O50) -> 25 | Q2: Gestor de Performance | R2: =SUMPRODUCT(CSV!$C$25:$C$50="Novo - Contratar",CSV!D25:D50>0) -> 0 | S2: =SUMPRODUCT(CSV!$C$25:$C$50="Novo - Contratar",CSV!E25:E50>0) -> 2 | T2: =SUMPRODUCT(CSV!$C$25:$C$50="Novo - Contratar",CSV!F25:F50>0) -> 3 | U2: =SUMPRODUCT(CSV!$C$25:$C$50="Novo - Contratar",CSV!G25:G50>0) -> 3 | V2: =SUMPRODUCT(CSV!$C$25:$C$50="Novo - Contratar",CSV!H25:H50>0) -> 4 | W2: =SUMPRODUCT(CSV!$C$25:$C$50="Novo - Contratar",CSV!I25:I50>0) -> 4 | X2: =SUMPRODUCT(CSV!$C$25:$C$50="Novo - Contratar",CSV!J25:J50>0) -> 5 | Y2: =SUMPRODUCT(CSV!$C$25:$C$50="Novo - Contratar",CSV!K25:K50>0) -> 5 | ... AC2: =SUMPRODUCT(CSV!$C$25:$C$50="Novo - Contratar",CSV!O25:O50>0) -> 8
B3: Designer de Performance | C3: =count(CSV!D65:D80) -> 8 | D3: =count(CSV!E65:E80) -> 8 | E3: =count(CSV!F65:F80) -> 8 | F3: =count(CSV!G65:G80) -> 9 | G3: =count(CSV!H65:H80) -> 9 | H3: =count(CSV!I65:I80) -> 9 | I3: =count(CSV!J65:J80) -> 9 | J3: =count(CSV!K65:K80) -> 10 | ... N3: =count(CSV!O65:O80) -> 11 | Q3: Designer de Performance | R3: =SUMPRODUCT(CSV!$C$65:$C$80="Novo - Contratar",CSV!D65:D80>0) -> 0 | S3: =SUMPRODUCT(CSV!$C$65:$C$80="Novo - Contratar",CSV!E65:E80>0) -> 0 | T3: =SUMPRODUCT(CSV!$C$65:$C$80="Novo - Contratar",CSV!F65:F80>0) -> 0 | U3: =SUMPRODUCT(CSV!$C$65:$C$80="Novo - Contratar",CSV!G65:G80>0) -> 1 | V3: =SUMPRODUCT(CSV!$C$65:$C$80="Novo - Contratar",CSV!H65:H80>0) -> 1 | W3: =SUMPRODUCT(CSV!$C$65:$C$80="Novo - Contratar",CSV!I65:I80>0) -> 1 | X3: =SUMPRODUCT(CSV!$C$65:$C$80="Novo - Contratar",CSV!J65:J80>0) -> 1 | Y3: =SUMPRODUCT(CSV!$C$65:$C$80="Novo - Contratar",CSV!K65:K80>0) -> 2 | ... AC3: =SUMPRODUCT(CSV!$C$65:$C$80="Novo - Contratar",CSV!O65:O80>0) -> 3
B4: Analista de Creators | C4: =count(CSV!D97:D109) -> 6 | D4: =count(CSV!E97:E109) -> 7 | E4: =count(CSV!F97:F109) -> 7 | F4: =count(CSV!G97:G109) -> 7 | G4: =count(CSV!H97:H109) -> 7 | H4: =count(CSV!I97:I109) -> 7 | I4: =count(CSV!J97:J109) -> 7 | J4: =count(CSV!K97:K109) -> 8 | ... N4: =count(CSV!O97:O109) -> 9 | Q4: Analista de Creators | R4: =SUMPRODUCT(CSV!$C$97:$C$109="Novo - Contratar",CSV!D97:D109>0) -> 0 | S4: =SUMPRODUCT(CSV!$C$97:$C$109="Novo - Contratar",CSV!E97:E109>0) -> 1 | T4: =SUMPRODUCT(CSV!$C$97:$C$109="Novo - Contratar",CSV!F97:F109>0) -> 1 | U4: =SUMPRODUCT(CSV!$C$97:$C$109="Novo - Contratar",CSV!G97:G109>0) -> 1 | V4: =SUMPRODUCT(CSV!$C$97:$C$109="Novo - Contratar",CSV!H97:H109>0) -> 1 | W4: =SUMPRODUCT(CSV!$C$97:$C$109="Novo - Contratar",CSV!I97:I109>0) -> 1 | X4: =SUMPRODUCT(CSV!$C$97:$C$109="Novo - Contratar",CSV!J97:J109>0) -> 1 | Y4: =SUMPRODUCT(CSV!$C$97:$C$109="Novo - Contratar",CSV!K97:K109>0) -> 2 | ... AC4: =SUMPRODUCT(CSV!$C$97:$C$109="Novo - Contratar",CSV!O97:O109>0) -> 3
B5: Designer Creators | C5: =count(CSV!D125:D135) -> 3 | D5: =count(CSV!E125:E135) -> 4 | E5: =count(CSV!F125:F135) -> 4 | F5: =count(CSV!G125:G135) -> 5 | G5: =count(CSV!H125:H135) -> 5 | H5: =count(CSV!I125:I135) -> 5 | I5: =count(CSV!J125:J135) -> 6 | J5: =count(CSV!K125:K135) -> 6 | ... N5: =count(CSV!O125:O135) -> 7 | Q5: Designer Creators | R5: =SUMPRODUCT(CSV!$C$125:$C$135="Novo - Contratar",CSV!D125:D135>0) -> 0 | S5: =SUMPRODUCT(CSV!$C$125:$C$135="Novo - Contratar",CSV!E125:E135>0) -> 1 | T5: =SUMPRODUCT(CSV!$C$125:$C$135="Novo - Contratar",CSV!F125:F135>0) -> 1 | U5: =SUMPRODUCT(CSV!$C$125:$C$135="Novo - Contratar",CSV!G125:G135>0) -> 2 | V5: =SUMPRODUCT(CSV!$C$125:$C$135="Novo - Contratar",CSV!H125:H135>0) -> 2 | W5: =SUMPRODUCT(CSV!$C$125:$C$135="Novo - Contratar",CSV!I125:I135>0) -> 2 | X5: =SUMPRODUCT(CSV!$C$125:$C$135="Novo - Contratar",CSV!J125:J135>0) -> 3 | Y5: =SUMPRODUCT(CSV!$C$125:$C$135="Novo - Contratar",CSV!K125:K135>0) -> 3 | ... AC5: =SUMPRODUCT(CSV!$C$125:$C$135="Novo - Contratar",CSV!O125:O135>0) -> 4
B6: Analista de Comunicação | C6: =count(CSV!D153:D167) -> 6 | D6: =count(CSV!E153:E167) -> 7 | E6: =count(CSV!F153:F167) -> 8 | F6: =count(CSV!G153:G167) -> 8 | G6: =count(CSV!H153:H167) -> 9 | H6: =count(CSV!I153:I167) -> 9 | I6: =count(CSV!J153:J167) -> 9 | J6: =count(CSV!K153:K167) -> 9 | ... N6: =count(CSV!O153:O167) -> 11 | Q6: Analista de Comunicação | R6: =IFERROR(__xludf.DUMMYFUNCTION("SUMPRODUCT(REGEXMATCH(CSV!$C$153:$C$167,""Novo - Contratar""),CSV!D153:D167>0) "),0.0) -> 0 | S6: =IFERROR(__xludf.DUMMYFUNCTION("SUMPRODUCT(REGEXMATCH(CSV!$C$153:$C$167,""Novo - Contratar""),CSV!E153:E167>0) "),1.0) -> 1 | T6: =IFERROR(__xludf.DUMMYFUNCTION("SUMPRODUCT(REGEXMATCH(CSV!$C$153:$C$167,""Novo - Contratar""),CSV!F153:F167>0) "),2.0) -> 2 | U6: =IFERROR(__xludf.DUMMYFUNCTION("SUMPRODUCT(REGEXMATCH(CSV!$C$153:$C$167,""Novo - Contratar""),CSV!G153:G167>0) "),2.0) -> 2 | V6: =IFERROR(__xludf.DUMMYFUNCTION("SUMPRODUCT(REGEXMATCH(CSV!$C$153:$C$167,""Novo - Contratar""),CSV!H153:H167>0) "),3.0) -> 3 | W6: =IFERROR(__xludf.DUMMYFUNCTION("SUMPRODUCT(REGEXMATCH(CSV!$C$153:$C$167,""Novo - Contratar""),CSV!I153:I167>0) "),3.0) -> 3 | X6: =IFERROR(__xludf.DUMMYFUNCTION("SUMPRODUCT(REGEXMATCH(CSV!$C$153:$C$167,""Novo - Contratar""),CSV!J153:J167>0) "),3.0) -> 3 | Y6: =IFERROR(__xludf.DUMMYFUNCTION("SUMPRODUCT(REGEXMATCH(CSV!$C$153:$C$167,""Novo - Contratar""),CSV!K153:K167>0) "),3.0) -> 3 | Z6: =IFERROR(__xludf.DUMMYFUNCTION("SUMPRODUCT(REGEXMATCH(CSV!$C$153:$C$167,""Novo - Contratar""),CSV!L153:L167>0) "),4.0) -> 4 | AA6: =IFERROR(__xludf.DUMMYFUNCTION("SUMPRODUCT(REGEXMATCH(CSV!$C$153:$C$167,""Novo - Contratar""),CSV!M153:M167>0) "),4.0) -> 4 | AB6: =IFERROR(__xludf.DUMMYFUNCTION("SUMPRODUCT(REGEXMATCH(CSV!$C$153:$C$167,""Novo - Contratar""),CSV!N153:N167>0) "),5.0) -> 5 | AC6: =IFERROR(__xludf.DUMMYFUNCTION("SUMPRODUCT(REGEXMATCH(CSV!$C$153:$C$167,""Novo - Contratar""),CSV!O153:O167>0) "),5.0) -> 5
B7: Designer Social | C7: =count(CSV!D183:D196) -> 5 | D7: =count(CSV!E183:E196) -> 5 | E7: =count(CSV!F183:F196) -> 5 | F7: =count(CSV!G183:G196) -> 8 | G7: =count(CSV!H183:H196) -> 8 | H7: =count(CSV!I183:I196) -> 9 | I7: =count(CSV!J183:J196) -> 9 | J7: =count(CSV!K183:K196) -> 10 | ... N7: =count(CSV!O183:O196) -> 12 | Q7: Designer Social | R7: =SUMPRODUCT(CSV!$C$183:$C$196="Novo - Contratar",CSV!D183:D196>0) -> 0 | S7: =SUMPRODUCT(CSV!$C$183:$C$196="Novo - Contratar",CSV!E183:E196>0) -> 0 | T7: =SUMPRODUCT(CSV!$C$183:$C$196="Novo - Contratar",CSV!F183:F196>0) -> 0 | U7: =SUMPRODUCT(CSV!$C$183:$C$196="Novo - Contratar",CSV!G183:G196>0) -> 3 | V7: =SUMPRODUCT(CSV!$C$183:$C$196="Novo - Contratar",CSV!H183:H196>0) -> 3 | W7: =SUMPRODUCT(CSV!$C$183:$C$196="Novo - Contratar",CSV!I183:I196>0) -> 4 | X7: =SUMPRODUCT(CSV!$C$183:$C$196="Novo - Contratar",CSV!J183:J196>0) -> 4 | Y7: =SUMPRODUCT(CSV!$C$183:$C$196="Novo - Contratar",CSV!K183:K196>0) -> 5 | ... AC7: =SUMPRODUCT(CSV!$C$183:$C$196="Novo - Contratar",CSV!O183:O196>0) -> 7
B8: Gestor de Comunidade | C8: =count(CSV!D214:D220) -> 0 | D8: =count(CSV!E214:E220) -> 1 | E8: =count(CSV!F214:F220) -> 1 | F8: =count(CSV!G214:G220) -> 3 | G8: =count(CSV!H214:H220) -> 3 | H8: =count(CSV!I214:I220) -> 3 | I8: =count(CSV!J214:J220) -> 4 | J8: =count(CSV!K214:K220) -> 4 | ... N8: =count(CSV!O214:O220) -> 5 | Q8: Gestor de Comunidade | R8: =SUMPRODUCT(CSV!$C$214:$C$220="Novo - Contratar",CSV!D214:D220>0) -> 0 | S8: =SUMPRODUCT(CSV!$C$214:$C$220="Novo - Contratar",CSV!E214:E220>0) -> 1 | T8: =SUMPRODUCT(CSV!$C$214:$C$220="Novo - Contratar",CSV!F214:F220>0) -> 1 | U8: =SUMPRODUCT(CSV!$C$214:$C$220="Novo - Contratar",CSV!G214:G220>0) -> 3 | V8: =SUMPRODUCT(CSV!$C$214:$C$220="Novo - Contratar",CSV!H214:H220>0) -> 3 | W8: =SUMPRODUCT(CSV!$C$214:$C$220="Novo - Contratar",CSV!I214:I220>0) -> 3 | X8: =SUMPRODUCT(CSV!$C$214:$C$220="Novo - Contratar",CSV!J214:J220>0) -> 4 | Y8: =SUMPRODUCT(CSV!$C$214:$C$220="Novo - Contratar",CSV!K214:K220>0) -> 4 | ... AC8: =SUMPRODUCT(CSV!$C$214:$C$220="Novo - Contratar",CSV!O214:O220>0) -> 5
B9: Gestor de Others | C9: =count(CSV!D237:D251) -> 3 | D9: =count(CSV!E237:E251) -> 3 | E9: =count(CSV!F237:F251) -> 3 | F9: =count(CSV!G237:G251) -> 4 | G9: =count(CSV!H237:H251) -> 4 | H9: =count(CSV!I237:I251) -> 4 | I9: =count(CSV!J237:J251) -> 5 | J9: =count(CSV!K237:K251) -> 5 | ... N9: =count(CSV!O237:O251) -> 6 | Q9: Gestor de Others | R9: =SUMPRODUCT(CSV!$C$237:$C$251="Novo - Contratar",CSV!D237:D251>0) -> 3 | S9: =SUMPRODUCT(CSV!$C$237:$C$251="Novo - Contratar",CSV!E237:E251>0) -> 3 | T9: =SUMPRODUCT(CSV!$C$237:$C$251="Novo - Contratar",CSV!F237:F251>0) -> 3 | U9: =SUMPRODUCT(CSV!$C$237:$C$251="Novo - Contratar",CSV!G237:G251>0) -> 4 | V9: =SUMPRODUCT(CSV!$C$237:$C$251="Novo - Contratar",CSV!H237:H251>0) -> 4 | W9: =SUMPRODUCT(CSV!$C$237:$C$251="Novo - Contratar",CSV!I237:I251>0) -> 4 | X9: =SUMPRODUCT(CSV!$C$237:$C$251="Novo - Contratar",CSV!J237:J251>0) -> 5 | Y9: =SUMPRODUCT(CSV!$C$237:$C$251="Novo - Contratar",CSV!K237:K251>0) -> 5 | ... AC9: =SUMPRODUCT(CSV!$C$237:$C$251="Novo - Contratar",CSV!O237:O251>0) -> 6
B10: CXCS | C10: =count(CSV!D266:D281) -> 6 | D10: =count(CSV!E266:E281) -> 6 | E10: =count(CSV!F266:F281) -> 7 | F10: =count(CSV!G266:G281) -> 8 | G10: =count(CSV!H266:H281) -> 9 | H10: =count(CSV!I266:I281) -> 9 | I10: =count(CSV!J266:J281) -> 9 | J10: =count(CSV!K266:K281) -> 10 | ... N10: =count(CSV!O266:O281) -> 11 | Q10: CXCS | R10: =SUMPRODUCT(CSV!$C$266:$C$281="Novo - Contratar",CSV!D266:D281>0) -> 2 | S10: =SUMPRODUCT(CSV!$C$266:$C$281="Novo - Contratar",CSV!E266:E281>0) -> 2 | T10: =SUMPRODUCT(CSV!$C$266:$C$281="Novo - Contratar",CSV!F266:F281>0) -> 3 | U10: =SUMPRODUCT(CSV!$C$266:$C$281="Novo - Contratar",CSV!G266:G281>0) -> 4 | V10: =SUMPRODUCT(CSV!$C$266:$C$281="Novo - Contratar",CSV!H266:H281>0) -> 5 | W10: =SUMPRODUCT(CSV!$C$266:$C$281="Novo - Contratar",CSV!I266:I281>0) -> 5 | X10: =SUMPRODUCT(CSV!$C$266:$C$281="Novo - Contratar",CSV!J266:J281>0) -> 5 | Y10: =SUMPRODUCT(CSV!$C$266:$C$281="Novo - Contratar",CSV!K266:K281>0) -> 6 | ... AC10: =SUMPRODUCT(CSV!$C$266:$C$281="Novo - Contratar",CSV!O266:O281>0) -> 7
B11: Líderes Commerce | C11: =count(CSV!D296:D309) -> 6 | D11: =count(CSV!E296:E309) -> 7 | E11: =count(CSV!F296:F309) -> 7 | F11: =count(CSV!G296:G309) -> 7 | G11: =count(CSV!H296:H309) -> 8 | H11: =count(CSV!I296:I309) -> 8 | I11: =count(CSV!J296:J309) -> 9 | J11: =count(CSV!K296:K309) -> 9 | ... N11: =count(CSV!O296:O309) -> 10 | Q11: Líderes Commerce | R11: =SUMPRODUCT(CSV!$C$296:$C$309="Novo - Contratar",CSV!D296:D309>0) -> 0 | S11: =SUMPRODUCT(CSV!$C$296:$C$309="Novo - Contratar",CSV!E296:E309>0) -> 1 | T11: =SUMPRODUCT(CSV!$C$296:$C$309="Novo - Contratar",CSV!F296:F309>0) -> 1 | U11: =SUMPRODUCT(CSV!$C$296:$C$309="Novo - Contratar",CSV!G296:G309>0) -> 1 | V11: =SUMPRODUCT(CSV!$C$296:$C$309="Novo - Contratar",CSV!H296:H309>0) -> 2 | W11: =SUMPRODUCT(CSV!$C$296:$C$309="Novo - Contratar",CSV!I296:I309>0) -> 2 | X11: =SUMPRODUCT(CSV!$C$296:$C$309="Novo - Contratar",CSV!J296:J309>0) -> 3 | Y11: =SUMPRODUCT(CSV!$C$296:$C$309="Novo - Contratar",CSV!K296:K309>0) -> 3 | ... AC11: =SUMPRODUCT(CSV!$C$296:$C$309="Novo - Contratar",CSV!O296:O309>0) -> 4
B12: Tech | C12: =count(CSV!D323:D337) -> 13 | D12: =count(CSV!E323:E337) -> 13 | E12: =count(CSV!F323:F337) -> 13 | F12: =count(CSV!G323:G337) -> 14 | G12: =count(CSV!H323:H337) -> 14 | H12: =count(CSV!I323:I337) -> 14 | I12: =count(CSV!J323:J337) -> 15 | J12: =count(CSV!K323:K337) -> 15 | ... N12: =count(CSV!O323:O337) -> 15 | Q12: Tech | R12: =IFERROR(__xludf.DUMMYFUNCTION("SUMPRODUCT(REGEXMATCH(CSV!$C$323:$C$337,""Novo - Contratar""),CSV!D323:D337>0) "),0.0) -> 0 | S12: =IFERROR(__xludf.DUMMYFUNCTION("SUMPRODUCT(REGEXMATCH(CSV!$C$323:$C$337,""Novo - Contratar""),CSV!E323:E337>0) "),0.0) -> 0 | T12: =IFERROR(__xludf.DUMMYFUNCTION("SUMPRODUCT(REGEXMATCH(CSV!$C$323:$C$337,""Novo - Contratar""),CSV!F323:F337>0) "),0.0) -> 0 | U12: =IFERROR(__xludf.DUMMYFUNCTION("SUMPRODUCT(REGEXMATCH(CSV!$C$323:$C$337,""Novo - Contratar""),CSV!G323:G337>0) "),1.0) -> 1 | V12: =IFERROR(__xludf.DUMMYFUNCTION("SUMPRODUCT(REGEXMATCH(CSV!$C$323:$C$337,""Novo - Contratar""),CSV!H323:H337>0) "),1.0) -> 1 | W12: =IFERROR(__xludf.DUMMYFUNCTION("SUMPRODUCT(REGEXMATCH(CSV!$C$323:$C$337,""Novo - Contratar""),CSV!I323:I337>0) "),1.0) -> 1 | X12: =IFERROR(__xludf.DUMMYFUNCTION("SUMPRODUCT(REGEXMATCH(CSV!$C$323:$C$337,""Novo - Contratar""),CSV!J323:J337>0) "),2.0) -> 2 | Y12: =IFERROR(__xludf.DUMMYFUNCTION("SUMPRODUCT(REGEXMATCH(CSV!$C$323:$C$337,""Novo - Contratar""),CSV!K323:K337>0) "),2.0) -> 2 | Z12: =IFERROR(__xludf.DUMMYFUNCTION("SUMPRODUCT(REGEXMATCH(CSV!$C$323:$C$337,""Novo - Contratar""),CSV!L323:L337>0) "),2.0) -> 2 | AA12: =IFERROR(__xludf.DUMMYFUNCTION("SUMPRODUCT(REGEXMATCH(CSV!$C$323:$C$337,""Novo - Contratar""),CSV!M323:M337>0) "),2.0) -> 2 | AB12: =IFERROR(__xludf.DUMMYFUNCTION("SUMPRODUCT(REGEXMATCH(CSV!$C$323:$C$337,""Novo - Contratar""),CSV!N323:N337>0) "),2.0) -> 2 | AC12: =IFERROR(__xludf.DUMMYFUNCTION("SUMPRODUCT(REGEXMATCH(CSV!$C$323:$C$337,""Novo - Contratar""),CSV!O323:O337>0) "),2.0) -> 2
B13: Pré-Vendas | C13: =count(CAC!C22:C38) -> 9 | D13: =count(CAC!D22:D38) -> 9 | E13: =count(CAC!E22:E38) -> 11 | F13: =count(CAC!F22:F38) -> 11 | G13: =count(CAC!G22:G38) -> 11 | H13: =count(CAC!H22:H38) -> 11 | I13: =count(CAC!I22:I38) -> 11 | J13: =count(CAC!J22:J38) -> 12 | ... N13: =count(CAC!N22:N38) -> 15 | Q13: Pré-Vendas | R13: =IFERROR(__xludf.DUMMYFUNCTION("SUMPRODUCT(REGEXMATCH(CAC!$B$22:$B$38,""Novo - Contratar""),CAC!C22:C38>0) "),1.0) -> 1 | S13: =IFERROR(__xludf.DUMMYFUNCTION("SUMPRODUCT(REGEXMATCH(CAC!$B$22:$B$38,""Novo - Contratar""),CAC!D22:D38>0) "),1.0) -> 1 | T13: =IFERROR(__xludf.DUMMYFUNCTION("SUMPRODUCT(REGEXMATCH(CAC!$B$22:$B$38,""Novo - Contratar""),CAC!E22:E38>0) "),3.0) -> 3 | U13: =IFERROR(__xludf.DUMMYFUNCTION("SUMPRODUCT(REGEXMATCH(CAC!$B$22:$B$38,""Novo - Contratar""),CAC!F22:F38>0) "),3.0) -> 3 | V13: =IFERROR(__xludf.DUMMYFUNCTION("SUMPRODUCT(REGEXMATCH(CAC!$B$22:$B$38,""Novo - Contratar""),CAC!G22:G38>0) "),3.0) -> 3 | W13: =IFERROR(__xludf.DUMMYFUNCTION("SUMPRODUCT(REGEXMATCH(CAC!$B$22:$B$38,""Novo - Contratar""),CAC!H22:H38>0) "),3.0) -> 3 | X13: =IFERROR(__xludf.DUMMYFUNCTION("SUMPRODUCT(REGEXMATCH(CAC!$B$22:$B$38,""Novo - Contratar""),CAC!I22:I38>0) "),3.0) -> 3 | Y13: =IFERROR(__xludf.DUMMYFUNCTION("SUMPRODUCT(REGEXMATCH(CAC!$B$22:$B$38,""Novo - Contratar""),CAC!J22:J38>0) "),4.0) -> 4 | Z13: =IFERROR(__xludf.DUMMYFUNCTION("SUMPRODUCT(REGEXMATCH(CAC!$B$22:$B$38,""Novo - Contratar""),CAC!K22:K38>0) "),5.0) -> 5 | AA13: =IFERROR(__xludf.DUMMYFUNCTION("SUMPRODUCT(REGEXMATCH(CAC!$B$22:$B$38,""Novo - Contratar""),CAC!L22:L38>0) "),6.0) -> 6 | AB13: =IFERROR(__xludf.DUMMYFUNCTION("SUMPRODUCT(REGEXMATCH(CAC!$B$22:$B$38,""Novo - Contratar""),CAC!M22:M38>0) "),6.0) -> 6 | AC13: =IFERROR(__xludf.DUMMYFUNCTION("SUMPRODUCT(REGEXMATCH(CAC!$B$22:$B$38,""Novo - Contratar""),CAC!N22:N38>0) "),7.0) -> 7
B14: Vendas | C14: =count(CAC!C44:C59) -> 6 | D14: =count(CAC!D44:D59) -> 7 | E14: =count(CAC!E44:E59) -> 7 | F14: =count(CAC!F44:F59) -> 8 | G14: =count(CAC!G44:G59) -> 8 | H14: =count(CAC!H44:H59) -> 8 | I14: =count(CAC!I44:I59) -> 8 | J14: =count(CAC!J44:J59) -> 8 | ... N14: =count(CAC!N44:N59) -> 8 | Q14: Vendas | R14: =IFERROR(__xludf.DUMMYFUNCTION("SUMPRODUCT(REGEXMATCH(CAC!$B$44:$B$59,""Novo - Contratar""),CAC!C44:C59>0) "),0.0) -> 0 | S14: =IFERROR(__xludf.DUMMYFUNCTION("SUMPRODUCT(REGEXMATCH(CAC!$B$44:$B$59,""Novo - Contratar""),CAC!D44:D59>0) "),1.0) -> 1 | T14: =IFERROR(__xludf.DUMMYFUNCTION("SUMPRODUCT(REGEXMATCH(CAC!$B$44:$B$59,""Novo - Contratar""),CAC!E44:E59>0) "),1.0) -> 1 | U14: =IFERROR(__xludf.DUMMYFUNCTION("SUMPRODUCT(REGEXMATCH(CAC!$B$44:$B$59,""Novo - Contratar""),CAC!F44:F59>0) "),2.0) -> 2 | V14: =IFERROR(__xludf.DUMMYFUNCTION("SUMPRODUCT(REGEXMATCH(CAC!$B$44:$B$59,""Novo - Contratar""),CAC!G44:G59>0) "),2.0) -> 2 | W14: =IFERROR(__xludf.DUMMYFUNCTION("SUMPRODUCT(REGEXMATCH(CAC!$B$44:$B$59,""Novo - Contratar""),CAC!H44:H59>0) "),2.0) -> 2 | X14: =IFERROR(__xludf.DUMMYFUNCTION("SUMPRODUCT(REGEXMATCH(CAC!$B$44:$B$59,""Novo - Contratar""),CAC!I44:I59>0) "),2.0) -> 2 | Y14: =IFERROR(__xludf.DUMMYFUNCTION("SUMPRODUCT(REGEXMATCH(CAC!$B$44:$B$59,""Novo - Contratar""),CAC!J44:J59>0) "),2.0) -> 2 | Z14: =IFERROR(__xludf.DUMMYFUNCTION("SUMPRODUCT(REGEXMATCH(CAC!$B$44:$B$59,""Novo - Contratar""),CAC!K44:K59>0) "),2.0) -> 2 | AA14: =IFERROR(__xludf.DUMMYFUNCTION("SUMPRODUCT(REGEXMATCH(CAC!$B$44:$B$59,""Novo - Contratar""),CAC!L44:L59>0) "),2.0) -> 2 | AB14: =IFERROR(__xludf.DUMMYFUNCTION("SUMPRODUCT(REGEXMATCH(CAC!$B$44:$B$59,""Novo - Contratar""),CAC!M44:M59>0) "),2.0) -> 2 | AC14: =IFERROR(__xludf.DUMMYFUNCTION("SUMPRODUCT(REGEXMATCH(CAC!$B$44:$B$59,""Novo - Contratar""),CAC!N44:N59>0) "),2.0) -> 2
B15: Lideres Venda | C15: =count(CAC!C66:C71) -> 2 | D15: =count(CAC!D66:D71) -> 2 | E15: =count(CAC!E66:E71) -> 2 | F15: =count(CAC!F66:F71) -> 2 | G15: =count(CAC!G66:G71) -> 2 | H15: =count(CAC!H66:H71) -> 2 | I15: =count(CAC!I66:I71) -> 2 | J15: =count(CAC!J66:J71) -> 2 | ... N15: =count(CAC!N66:N71) -> 2 | Q15: Lideres Venda | R15: =IFERROR(__xludf.DUMMYFUNCTION("SUMPRODUCT(REGEXMATCH(CAC!$B$66:$B$71,""Novo - Contratar""),CAC!C66:C71>0) "),0.0) -> 0 | S15: =IFERROR(__xludf.DUMMYFUNCTION("SUMPRODUCT(REGEXMATCH(CAC!$B$66:$B$71,""Novo - Contratar""),CAC!D66:D71>0) "),0.0) -> 0 | T15: =IFERROR(__xludf.DUMMYFUNCTION("SUMPRODUCT(REGEXMATCH(CAC!$B$66:$B$71,""Novo - Contratar""),CAC!E66:E71>0) "),0.0) -> 0 | U15: =IFERROR(__xludf.DUMMYFUNCTION("SUMPRODUCT(REGEXMATCH(CAC!$B$66:$B$71,""Novo - Contratar""),CAC!F66:F71>0) "),0.0) -> 0 | V15: =IFERROR(__xludf.DUMMYFUNCTION("SUMPRODUCT(REGEXMATCH(CAC!$B$66:$B$71,""Novo - Contratar""),CAC!G66:G71>0) "),0.0) -> 0 | W15: =IFERROR(__xludf.DUMMYFUNCTION("SUMPRODUCT(REGEXMATCH(CAC!$B$66:$B$71,""Novo - Contratar""),CAC!H66:H71>0) "),0.0) -> 0 | X15: =IFERROR(__xludf.DUMMYFUNCTION("SUMPRODUCT(REGEXMATCH(CAC!$B$66:$B$71,""Novo - Contratar""),CAC!I66:I71>0) "),0.0) -> 0 | Y15: =IFERROR(__xludf.DUMMYFUNCTION("SUMPRODUCT(REGEXMATCH(CAC!$B$66:$B$71,""Novo - Contratar""),CAC!J66:J71>0) "),0.0) -> 0 | Z15: =IFERROR(__xludf.DUMMYFUNCTION("SUMPRODUCT(REGEXMATCH(CAC!$B$66:$B$71,""Novo - Contratar""),CAC!K66:K71>0) "),0.0) -> 0 | AA15: =IFERROR(__xludf.DUMMYFUNCTION("SUMPRODUCT(REGEXMATCH(CAC!$B$66:$B$71,""Novo - Contratar""),CAC!L66:L71>0) "),0.0) -> 0 | AB15: =IFERROR(__xludf.DUMMYFUNCTION("SUMPRODUCT(REGEXMATCH(CAC!$B$66:$B$71,""Novo - Contratar""),CAC!M66:M71>0) "),0.0) -> 0 | AC15: =IFERROR(__xludf.DUMMYFUNCTION("SUMPRODUCT(REGEXMATCH(CAC!$B$66:$B$71,""Novo - Contratar""),CAC!N66:N71>0) "),0.0) -> 0
B16: Growth | C16: =count(CAC!C77:C86) -> 7 | D16: =count(CAC!D77:D86) -> 7 | E16: =count(CAC!E77:E86) -> 7 | F16: =count(CAC!F77:F86) -> 9 | G16: =count(CAC!G77:G86) -> 9 | H16: =count(CAC!H77:H86) -> 9 | I16: =count(CAC!I77:I86) -> 9 | J16: =count(CAC!J77:J86) -> 9 | ... N16: =count(CAC!N77:N86) -> 9 | Q16: Growth | R16: =IFERROR(__xludf.DUMMYFUNCTION("SUMPRODUCT(REGEXMATCH(CAC!$B$77:$B$86,""Novo - Contratar""),CAC!C77:C86>0) "),1.0) -> 1 | S16: =IFERROR(__xludf.DUMMYFUNCTION("SUMPRODUCT(REGEXMATCH(CAC!$B$77:$B$86,""Novo - Contratar""),CAC!D77:D86>0) "),1.0) -> 1 | T16: =IFERROR(__xludf.DUMMYFUNCTION("SUMPRODUCT(REGEXMATCH(CAC!$B$77:$B$86,""Novo - Contratar""),CAC!E77:E86>0) "),1.0) -> 1 | U16: =IFERROR(__xludf.DUMMYFUNCTION("SUMPRODUCT(REGEXMATCH(CAC!$B$77:$B$86,""Novo - Contratar""),CAC!F77:F86>0) "),3.0) -> 3 | V16: =IFERROR(__xludf.DUMMYFUNCTION("SUMPRODUCT(REGEXMATCH(CAC!$B$77:$B$86,""Novo - Contratar""),CAC!G77:G86>0) "),3.0) -> 3 | W16: =IFERROR(__xludf.DUMMYFUNCTION("SUMPRODUCT(REGEXMATCH(CAC!$B$77:$B$86,""Novo - Contratar""),CAC!H77:H86>0) "),3.0) -> 3 | X16: =IFERROR(__xludf.DUMMYFUNCTION("SUMPRODUCT(REGEXMATCH(CAC!$B$77:$B$86,""Novo - Contratar""),CAC!I77:I86>0) "),3.0) -> 3 | Y16: =IFERROR(__xludf.DUMMYFUNCTION("SUMPRODUCT(REGEXMATCH(CAC!$B$77:$B$86,""Novo - Contratar""),CAC!J77:J86>0) "),3.0) -> 3 | Z16: =IFERROR(__xludf.DUMMYFUNCTION("SUMPRODUCT(REGEXMATCH(CAC!$B$77:$B$86,""Novo - Contratar""),CAC!K77:K86>0) "),3.0) -> 3 | AA16: =IFERROR(__xludf.DUMMYFUNCTION("SUMPRODUCT(REGEXMATCH(CAC!$B$77:$B$86,""Novo - Contratar""),CAC!L77:L86>0) "),3.0) -> 3 | AB16: =IFERROR(__xludf.DUMMYFUNCTION("SUMPRODUCT(REGEXMATCH(CAC!$B$77:$B$86,""Novo - Contratar""),CAC!M77:M86>0) "),3.0) -> 3 | AC16: =IFERROR(__xludf.DUMMYFUNCTION("SUMPRODUCT(REGEXMATCH(CAC!$B$77:$B$86,""Novo - Contratar""),CAC!N77:N86>0) "),3.0) -> 3
B17: Backoffice | C17: =count('SG&A'!C28:C37) -> 9 | D17: =count('SG&A'!D28:D37) -> 9 | E17: =count('SG&A'!E28:E37) -> 9 | F17: =count('SG&A'!F28:F37) -> 8 | G17: =count('SG&A'!G28:G37) -> 8 | H17: =count('SG&A'!H28:H37) -> 9 | I17: =count('SG&A'!I28:I37) -> 9 | J17: =count('SG&A'!J28:J37) -> 9 | ... N17: =count('SG&A'!N28:N37) -> 9 | Q17: Backoffice | R17: =IFERROR(__xludf.DUMMYFUNCTION("SUMPRODUCT(REGEXMATCH('SG&A'!$B$28:$B$37,""Novo - Contratar""),'SG&A'!C28:C37>0) "),0.0) -> 0 | S17: =IFERROR(__xludf.DUMMYFUNCTION("SUMPRODUCT(REGEXMATCH('SG&A'!$B$28:$B$37,""Novo - Contratar""),'SG&A'!D28:D37>0) "),0.0) -> 0 | T17: =IFERROR(__xludf.DUMMYFUNCTION("SUMPRODUCT(REGEXMATCH('SG&A'!$B$28:$B$37,""Novo - Contratar""),'SG&A'!E28:E37>0) "),0.0) -> 0 | U17: =IFERROR(__xludf.DUMMYFUNCTION("SUMPRODUCT(REGEXMATCH('SG&A'!$B$28:$B$37,""Novo - Contratar""),'SG&A'!F28:F37>0) "),0.0) -> 0 | V17: =IFERROR(__xludf.DUMMYFUNCTION("SUMPRODUCT(REGEXMATCH('SG&A'!$B$28:$B$37,""Novo - Contratar""),'SG&A'!G28:G37>0) "),0.0) -> 0 | W17: =IFERROR(__xludf.DUMMYFUNCTION("SUMPRODUCT(REGEXMATCH('SG&A'!$B$28:$B$37,""Novo - Contratar""),'SG&A'!H28:H37>0) "),1.0) -> 1 | X17: =IFERROR(__xludf.DUMMYFUNCTION("SUMPRODUCT(REGEXMATCH('SG&A'!$B$28:$B$37,""Novo - Contratar""),'SG&A'!I28:I37>0) "),1.0) -> 1 | Y17: =IFERROR(__xludf.DUMMYFUNCTION("SUMPRODUCT(REGEXMATCH('SG&A'!$B$28:$B$37,""Novo - Contratar""),'SG&A'!J28:J37>0) "),1.0) -> 1 | Z17: =IFERROR(__xludf.DUMMYFUNCTION("SUMPRODUCT(REGEXMATCH('SG&A'!$B$28:$B$37,""Novo - Contratar""),'SG&A'!K28:K37>0) "),1.0) -> 1 | AA17: =IFERROR(__xludf.DUMMYFUNCTION("SUMPRODUCT(REGEXMATCH('SG&A'!$B$28:$B$37,""Novo - Contratar""),'SG&A'!L28:L37>0) "),1.0) -> 1 | AB17: =IFERROR(__xludf.DUMMYFUNCTION("SUMPRODUCT(REGEXMATCH('SG&A'!$B$28:$B$37,""Novo - Contratar""),'SG&A'!M28:M37>0) "),1.0) -> 1 | AC17: =IFERROR(__xludf.DUMMYFUNCTION("SUMPRODUCT(REGEXMATCH('SG&A'!$B$28:$B$37,""Novo - Contratar""),'SG&A'!N28:N37>0) "),1.0) -> 1
B18: UZK | C18: =count('SG&A'!C20:C22) -> 3 | D18: =count('SG&A'!D20:D22) -> 3 | E18: =count('SG&A'!E20:E22) -> 3 | F18: =count('SG&A'!F20:F22) -> 3 | G18: =count('SG&A'!G20:G22) -> 3 | H18: =count('SG&A'!H20:H22) -> 3 | I18: =count('SG&A'!I20:I22) -> 3 | J18: =count('SG&A'!J20:J22) -> 3 | ... N18: =count('SG&A'!N20:N22) -> 3 | Q18: UZK | R18: =IFERROR(__xludf.DUMMYFUNCTION("SUMPRODUCT(REGEXMATCH('SG&A'!$B$20:$B$22,""Novo - Contratar""),'SG&A'!C20:C22>0) "),0.0) -> 0 | S18: =IFERROR(__xludf.DUMMYFUNCTION("SUMPRODUCT(REGEXMATCH('SG&A'!$B$20:$B$22,""Novo - Contratar""),'SG&A'!D20:D22>0) "),0.0) -> 0 | T18: =IFERROR(__xludf.DUMMYFUNCTION("SUMPRODUCT(REGEXMATCH('SG&A'!$B$20:$B$22,""Novo - Contratar""),'SG&A'!E20:E22>0) "),0.0) -> 0 | U18: =IFERROR(__xludf.DUMMYFUNCTION("SUMPRODUCT(REGEXMATCH('SG&A'!$B$20:$B$22,""Novo - Contratar""),'SG&A'!F20:F22>0) "),0.0) -> 0 | V18: =IFERROR(__xludf.DUMMYFUNCTION("SUMPRODUCT(REGEXMATCH('SG&A'!$B$20:$B$22,""Novo - Contratar""),'SG&A'!G20:G22>0) "),0.0) -> 0 | W18: =IFERROR(__xludf.DUMMYFUNCTION("SUMPRODUCT(REGEXMATCH('SG&A'!$B$20:$B$22,""Novo - Contratar""),'SG&A'!H20:H22>0) "),0.0) -> 0 | X18: =IFERROR(__xludf.DUMMYFUNCTION("SUMPRODUCT(REGEXMATCH('SG&A'!$B$20:$B$22,""Novo - Contratar""),'SG&A'!I20:I22>0) "),0.0) -> 0 | Y18: =IFERROR(__xludf.DUMMYFUNCTION("SUMPRODUCT(REGEXMATCH('SG&A'!$B$20:$B$22,""Novo - Contratar""),'SG&A'!J20:J22>0) "),0.0) -> 0 | Z18: =IFERROR(__xludf.DUMMYFUNCTION("SUMPRODUCT(REGEXMATCH('SG&A'!$B$20:$B$22,""Novo - Contratar""),'SG&A'!K20:K22>0) "),0.0) -> 0 | AA18: =IFERROR(__xludf.DUMMYFUNCTION("SUMPRODUCT(REGEXMATCH('SG&A'!$B$20:$B$22,""Novo - Contratar""),'SG&A'!L20:L22>0) "),0.0) -> 0 | AB18: =IFERROR(__xludf.DUMMYFUNCTION("SUMPRODUCT(REGEXMATCH('SG&A'!$B$20:$B$22,""Novo - Contratar""),'SG&A'!M20:M22>0) "),0.0) -> 0 | AC18: =IFERROR(__xludf.DUMMYFUNCTION("SUMPRODUCT(REGEXMATCH('SG&A'!$B$20:$B$22,""Novo - Contratar""),'SG&A'!N20:N22>0) "),0.0) -> 0
B19: Total | C19: =SUM(C2:C18) -> 109 | D19: =SUM(D2:D18) -> 117 | E19: =SUM(E2:E18) -> 122 | F19: =SUM(F2:F18) -> 134 | G19: =SUM(G2:G18) -> 138 | H19: =SUM(H2:H18) -> 140 | I19: =SUM(I2:I18) -> 146 | J19: =SUM(J2:J18) -> 151 | ... N19: =SUM(N2:N18) -> 168 | Q19: Total | R19: =SUM(R2:R18) -> 7 | S19: =SUM(S2:S18) -> 15 | T19: =SUM(T2:T18) -> 20 | U19: =SUM(U2:U18) -> 33 | V19: =SUM(V2:V18) -> 37 | W19: =SUM(W2:W18) -> 39 | X19: =SUM(X2:X18) -> 45 | Y19: =SUM(Y2:Y18) -> 50 | ... AC19: =SUM(AC2:AC18) -> 67
B22: (-) Premiações | C22: 5000 | D22: 5000 | E22: 5000 | F22: 5000 | G22: 5000 | H22: 5000 | I22: 5000 | J22: 5000 | K22: 5000 | L22: 5000 | M22: 5000 | N22: 5000 | O22: =SUM(C22:N22) -> 60000 | Q22: Gestor de Performance | R22: =C2+C9 -> 20 | S22: =D2+D9 -> 22 | T22: =E2+E9 -> 23 | U22: =F2+F9 -> 24 | V22: =G2+G9 -> 25 | W22: =H2+H9 -> 25 | X22: =I2+I9 -> 27 | Y22: =J2+J9 -> 27 | ... AC22: =N2+N9 -> 31
B23: (-) Eventos e Brindes Internos | C23: 30000 | D23: 10000 | E23: 10000 | F23: 10000 | G23: 10000 | H23: 10000 | I23: 10000 | J23: 10000 | K23: 10000 | L23: 10000 | M23: 20000 | N23: 40000 | O23: =SUM(C23:N23) -> 180000 | Q23: Analista | R23: =C4+C6+C8 -> 12 | S23: =D4+D6+D8 -> 15 | T23: =E4+E6+E8 -> 16 | U23: =F4+F6+F8 -> 18 | V23: =G4+G6+G8 -> 19 | W23: =H4+H6+H8 -> 19 | X23: =I4+I6+I8 -> 20 | Y23: =J4+J6+J8 -> 21 | ... AC23: =N4+N6+N8 -> 25
Q24: Designer | R24: =C3+C5+C7 -> 16 | S24: =D3+D5+D7 -> 17 | T24: =E3+E5+E7 -> 17 | U24: =F3+F5+F7 -> 22 | V24: =G3+G5+G7 -> 22 | W24: =H3+H5+H7 -> 23 | X24: =I3+I5+I7 -> 24 | Y24: =J3+J5+J7 -> 26 | ... AC24: =N3+N5+N7 -> 30
B25: Turbo Vision | C25: =7500+500+1800+5200+850+150 -> 16000 | O25: =sum(C25:N25) -> 16000 | Q25: CXCS | R25: =C10 -> 6 | S25: =D10 -> 6 | T25: =E10 -> 7 | U25: =F10 -> 8 | V25: =G10 -> 9 | W25: =H10 -> 9 | X25: =I10 -> 9 | Y25: =J10 -> 10 | ... AC25: =N10 -> 11
B26: Brinde Natal | N26: =100*Overview!N42 -> 16800 | O26: =sum(C26:N26) -> 16800 | Q26: Lideres commerce | R26: =C11 -> 6 | S26: =D11 -> 7 | T26: =E11 -> 7 | U26: =F11 -> 7 | V26: =G11 -> 8 | W26: =H11 -> 8 | X26: =I11 -> 9 | Y26: =J11 -> 9 | ... AC26: =N11 -> 10
B27: Turbo Fit | C27: 1000 | E27: 3000 | G27: 3000 | I27: 3000 | K27: 3000 | M27: 3000 | O27: =sum(C27:N27) -> 16000 | Q27: Tech | R27: =C12 -> 13 | S27: =D12 -> 13 | T27: =E12 -> 13 | U27: =F12 -> 14 | V27: =G12 -> 14 | W27: =H12 -> 14 | X27: =I12 -> 15 | Y27: =J12 -> 15 | ... AC27: =N12 -> 15
B28: Turbo Moviments | F28: 2500 | H28: 2500 | J28: 2500 | L28: 2500 | O28: =sum(C28:N28) -> 10000 | Q28: Vendas | R28: =C14 -> 6 | S28: =D14 -> 7 | T28: =E14 -> 7 | U28: =F14 -> 8 | V28: =G14 -> 8 | W28: =H14 -> 8 | X28: =I14 -> 8 | Y28: =J14 -> 8 | ... AC28: =N14 -> 8
B29: Aniversario de Empresa | C29: 1400 | D29: 1400 | E29: 1400 | F29: 1400 | G29: 1400 | H29: 1400 | I29: 1400 | J29: 1400 | K29: 1400 | L29: 1400 | M29: 1400 | N29: 1400 | O29: =sum(C29:N29) -> 16800 | Q29: Pre vendas | R29: =C13 -> 9 | S29: =D13 -> 9 | T29: =E13 -> 11 | U29: =F13 -> 11 | V29: =G13 -> 11 | W29: =H13 -> 11 | X29: =I13 -> 11 | Y29: =J13 -> 12 | ... AC29: =N13 -> 15
B30: Aniversario do Colaborador | C30: 400 | D30: 400 | E30: 400 | F30: 400 | G30: 400 | H30: 400 | I30: 400 | J30: 400 | K30: 400 | L30: 400 | M30: 400 | N30: 400 | O30: =sum(C30:N30) -> 4800 | Q30: Lideres venda | R30: =C15 -> 2 | S30: =D15 -> 2 | T30: =E15 -> 2 | U30: =F15 -> 2 | V30: =G15 -> 2 | W30: =H15 -> 2 | X30: =I15 -> 2 | Y30: =J15 -> 2 | ... AC30: =N15 -> 2
B31: Uniforme Polo | C31: 1250 | D31: 1250 | E31: 1250 | F31: 1250 | G31: 1250 | H31: 1250 | I31: 1250 | J31: 1250 | K31: 1250 | L31: 1250 | M31: 1250 | N31: 1250 | O31: =sum(C31:N31) -> 15000 | Q31: Growth | R31: =C16 -> 7 | S31: =D16 -> 7 | T31: =E16 -> 7 | U31: =F16 -> 9 | V31: =G16 -> 9 | W31: =H16 -> 9 | X31: =I16 -> 9 | Y31: =J16 -> 9 | ... AC31: =N16 -> 9
B32: Kit Onboarding | C32: =1500 -> 1500 | D32: =1500 -> 1500 | E32: =1500 -> 1500 | F32: =1500 -> 1500 | G32: =1500 -> 1500 | H32: =1500 -> 1500 | I32: =1500 -> 1500 | J32: =1500 -> 1500 | ... N32: =1500 -> 1500 | O32: =sum(C32:N32) -> 18000 | Q32: Backoffice | R32: =C17+C18 -> 12 | S32: =D17+D18 -> 12 | T32: =E17+E18 -> 12 | U32: =F17+F18 -> 11 | V32: =G17+G18 -> 11 | W32: =H17+H18 -> 12 | X32: =I17+I18 -> 12 | Y32: =J17+J18 -> 12 | ... AC32: =N17+N18 -> 12
B33: Camisa Fit | C33: 850 | D33: 850 | E33: 850 | F33: 850 | G33: 850 | H33: 850 | I33: 850 | J33: 850 | K33: 850 | L33: 850 | M33: 850 | N33: 850 | O33: =sum(C33:N33) -> 10200
B34: Bootcamp + Aquisição de Talentos | C34: 2000 | E34: 3000 | H34: 1500 | K34: 1500 | N34: 1500 | O34: =sum(C34:N34) -> 9500
B35: Outros Eventos Time interno | C35: 500 | D35: 500 | E35: 500 | F35: 500 | G35: 500 | H35: 500 | I35: 500 | J35: 500 | K35: 500 | L35: 500 | M35: 500 | N35: 500 | O35: =sum(C35:N35) -> 6000 | Q35: Gestor de Performance | R35: =R2+R9 -> 3 | S35: =S2+S9 -> 5 | T35: =T2+T9 -> 6 | U35: =U2+U9 -> 7 | V35: =V2+V9 -> 8 | W35: =W2+W9 -> 8 | X35: =X2+X9 -> 10 | Y35: =Y2+Y9 -> 10 | ... AC35: =AC2+AC9 -> 14
B36: Lanches + Café da Manha | C36: 600 | D36: 600 | E36: 600 | F36: 600 | G36: 600 | H36: 600 | I36: 600 | J36: 600 | K36: 600 | L36: 600 | M36: 600 | N36: 600 | O36: =sum(C36:N36) -> 7200 | Q36: Analista | R36: =R4+R6+R8 -> 0 | S36: =S4+S6+S8 -> 3 | T36: =T4+T6+T8 -> 4 | U36: =U4+U6+U8 -> 6 | V36: =V4+V6+V8 -> 7 | W36: =W4+W6+W8 -> 7 | X36: =X4+X6+X8 -> 8 | Y36: =Y4+Y6+Y8 -> 9 | ... AC36: =AC4+AC6+AC8 -> 13
B37: Eventos Tematicos | F37: =50*130 -> 6500 | I37: 5000 | J37: 1500 | L37: 2500 | O37: =sum(C37:N37) -> 15500 | Q37: Designer | R37: =R3+R5+R7 -> 0 | S37: =S3+S5+S7 -> 1 | T37: =T3+T5+T7 -> 1 | U37: =U3+U5+U7 -> 6 | V37: =V3+V5+V7 -> 6 | W37: =W3+W5+W7 -> 7 | X37: =X3+X5+X7 -> 8 | Y37: =Y3+Y5+Y7 -> 10 | ... AC37: =AC3+AC5+AC7 -> 14
B38: Lojinha e Brindes | C38: 1600 | D38: 1600 | E38: 1600 | F38: 1600 | G38: 1600 | H38: 1600 | I38: 1600 | J38: 1600 | K38: 1600 | L38: 1600 | M38: 1600 | N38: 600 | O38: =sum(C38:N38) -> 18200 | Q38: CXCS | R38: =R10 -> 2 | S38: =S10 -> 2 | T38: =T10 -> 3 | U38: =U10 -> 4 | V38: =V10 -> 5 | W38: =W10 -> 5 | X38: =X10 -> 5 | Y38: =Y10 -> 6 | ... AC38: =AC10 -> 7
B39: Total | C39: =sum(C25:C38) -> 27100 | D39: =sum(D25:D38) -> 8100 | E39: =sum(E25:E38) -> 14100 | F39: =sum(F25:F38) -> 17100 | G39: =sum(G25:G38) -> 11100 | H39: =sum(H25:H38) -> 12100 | I39: =sum(I25:I38) -> 16100 | J39: =sum(J25:J38) -> 12100 | ... N39: =sum(N25:N38) -> 25400 | O39: =sum(C39:N39) -> 180000 | Q39: Lideres commerce | R39: =R11 -> 0 | S39: =S11 -> 1 | T39: =T11 -> 1 | U39: =U11 -> 1 | V39: =V11 -> 2 | W39: =W11 -> 2 | X39: =X11 -> 3 | Y39: =Y11 -> 3 | ... AC39: =AC11 -> 4
Q40: Tech | R40: =R12 -> 0 | S40: =S12 -> 0 | T40: =T12 -> 0 | U40: =U12 -> 1 | V40: =V12 -> 1 | W40: =W12 -> 1 | X40: =X12 -> 2 | Y40: =Y12 -> 2 | ... AC40: =AC12 -> 2
Q41: Vendas | R41: =R14 -> 0 | S41: =S14 -> 1 | T41: =T14 -> 1 | U41: =U14 -> 2 | V41: =V14 -> 2 | W41: =W14 -> 2 | X41: =X14 -> 2 | Y41: =Y14 -> 2 | ... AC41: =AC14 -> 2
B42: Kit Onboarding | C42: Presencial | D42: Remota | Q42: Pre vendas | R42: =R13 -> 1 | S42: =S13 -> 1 | T42: =T13 -> 3 | U42: =U13 -> 3 | V42: =V13 -> 3 | W42: =W13 -> 3 | X42: =X13 -> 3 | Y42: =Y13 -> 4 | ... AC42: =AC13 -> 7
B43: Garrafa | C43: 60 | D43: ❌ | Q43: Lideres venda | R43: =R15 -> 0 | S43: =S15 -> 0 | T43: =T15 -> 0 | U43: =U15 -> 0 | V43: =V15 -> 0 | W43: =W15 -> 0 | X43: =X15 -> 0 | Y43: =Y15 -> 0 | ... AC43: =AC15 -> 0
B44: Blusa Normal | C44: 50 | D44: ❌ | Q44: Growth | R44: =R16 -> 1 | S44: =S16 -> 1 | T44: =T16 -> 1 | U44: =U16 -> 3 | V44: =V16 -> 3 | W44: =W16 -> 3 | X44: =X16 -> 3 | Y44: =Y16 -> 3 | ... AC44: =AC16 -> 3
B45: Mochila | C45: 70 | D45: ❌ | Q45: Backoffice | R45: =R17+R18 -> 0 | S45: =S17+S18 -> 0 | T45: =T17+T18 -> 0 | U45: =U17+U18 -> 0 | V45: =V17+V18 -> 0 | W45: =W17+W18 -> 1 | X45: =X17+X18 -> 1 | Y45: =Y17+Y18 -> 1 | ... AC45: =AC17+AC18 -> 1
B46: Perifericos (Mouse, Dongle, Monitor) | C46: ✅ | D46: ✅
B47: Notebook e Carregador | C47: ✅ | D47: ✅
B49: Lojinha colaborador
B50: Guarda Sol | D50: Palestras externas de G&G
B51: Cadeira de Praia | D51: Ambiente de escritorio (Visual)
B52: Camisa Fit | D52: Dinamicas escritorio
B53: Camisa descontraida | D53: Partners Club
B54: Camisa Turbo | D54: Brindes colaboradores
B55: Bone Corrida
B56: Bone Normal | D56: Pontuação gameficado | F56: para clientes | G56: para colaboradores
B57: Moleton Turbo
B58: Moleton Descontraido
B59: Squeeze
B60: Garrafa termica
B61: Copo Termico
B62: Ecobag / Bolsa de tecido
B63: Mochila
B64: Lancheira/Bolsa termica
B65: Café
B66: Cartela de adesivos
B67: Toalha de Praia “grossa”
B68: Toalha fina (Modelo decatlhon)
... B76: •⁠ ⁠Quais os reconhecimentos que vamos validar trimestralmente?

Sheet nao mexer
F2: Janeiro | G2: Fevereiro | H2: março | I2: abril | J2: maio | K2: junho | L2: julho | M2: agosto | N2: setembro | O2: outubro | P2: novembro | Q2: dezembro
B3: Bookado | C3: Ticket Médio | D3: Contratos | E3: =Revenue!C5 -> 1035000 | F3: =E3+F12+F10 -> 1152200 | G3: =F3+G12+G10 -> 1260024 | H3: =G3+H12+H10 -> 1359222.1 | I3: =H3+I12+I10 -> 1470484.3 | J3: =I3+J12+J10 -> 1572845.6 | K3: =J3+K12+K10 -> 1667017.9 | L3: =K3+L12+L10 -> 1773656.5 | M3: =L3+M12+M10 -> 1871764 | ... Q3: =P3+Q12+Q10 -> 2247067.7
B4: Performance | C4: =E4/D4 -> 2698.8636 | D4: =Revenue!C9 -> 176 | E4: =Revenue!C7 -> 475000 | F4: =E4*(1-$F86)+F13 -> 511000 | G4: =F4*(1-$F86)+G13 -> 544120 | H4: =G4*(1-$F86)+H13 -> 574590.4 | I4: =H4*(1-$F86)+I13 -> 610023.17 | J4: =I4*(1-$F86)+J13 -> 642621.31 | K4: =J4*(1-$F86)+K13 -> 672611.61 | L4: =K4*(1-$F86)+L13 -> 707602.68 | M4: =L4*(1-$F86)+M13 -> 739794.47 | ... Q4: =P4*(1-$F86)+Q13 -> 865258.72
B5: Creators | C5: =E5/D5 -> 4207.5472 | D5: =Revenue!C14 -> 53 | E5: =Revenue!C12 -> 223000 | F5: =E5*(1-$F87)+F14 -> 267894.26 | G5: =F5*(1-$F87)+G14 -> 309196.98 | H5: =G5*(1-$F87)+H14 -> 347195.49 | I5: =H5*(1-$F87)+I14 -> 388427.54 | J5: =I5*(1-$F87)+J14 -> 426361.02 | K5: =J5*(1-$F87)+K14 -> 461259.83 | L5: =K5*(1-$F87)+L14 -> 499640.16 | M5: =L5*(1-$F87)+M14 -> 534950.06 | ... Q5: =P5*(1-$F87)+Q14 -> 667467.44
B6: Social Media | C6: =E6/D6 -> 2117.6471 | D6: =Revenue!C19 -> 85 | E6: =Revenue!C17 -> 180000 | F6: =E6*(1-$F88)+F15 -> 204659.34 | G6: =F6*(1-$F88)+G15 -> 227345.93 | H6: =G6*(1-$F88)+H15 -> 248217.59 | I6: =H6*(1-$F88)+I15 -> 271325.45 | J6: =I6*(1-$F88)+J15 -> 292584.69 | K6: =J6*(1-$F88)+K15 -> 312143.18 | L6: =K6*(1-$F88)+L15 -> 334042.93 | M6: =L6*(1-$F88)+M15 -> 354190.7 | ... Q6: =P6*(1-$F88)+Q15 -> 430707.65
B7: Gestão de Comunidade | C7: =E7/D7 -> 7272.7273 | D7: =Revenue!C24 -> 11 | E7: =Revenue!C22 -> 80000 | F7: =E7*(1-$F89)+F16 -> 82631.061 | G7: =F7*(1-$F89)+G16 -> 85051.636 | H7: =G7*(1-$F89)+H16 -> 87278.566 | I7: =H7*(1-$F89)+I16 -> 90230.447 | J7: =I7*(1-$F89)+J16 -> 92946.178 | K7: =J7*(1-$F89)+K16 -> 95444.651 | L7: =K7*(1-$F89)+L16 -> 98646.351 | M7: =L7*(1-$F89)+M16 -> 101591.92 | ... Q7: =P7*(1-$F89)+Q16 -> 113697.17
B8: E-mail Marketing | C8: =E8/D8 -> 1250 | D8: 8 | E8: 10000 | F8: =E8*(1-$F90)+F17 -> 17145.055 | G8: =F8*(1-$F90)+G17 -> 23718.506 | H8: =G8*(1-$F90)+H17 -> 29766.08 | I8: =H8*(1-$F90)+I17 -> 36124.354 | J8: =I8*(1-$F90)+J17 -> 41973.967 | K8: =J8*(1-$F90)+K17 -> 47355.61 | L8: =K8*(1-$F90)+L17 -> 53101.227 | M8: =L8*(1-$F90)+M17 -> 58387.195 | ... Q8: =P8*(1-$F90)+Q17 -> 77825.198
B9: Tech/CRM/outros | C9: =E9/D9 -> 1634.1463 | D9: 41 | E9: =E3-SUM(E4:E8) -> 67000 | F9: =E9*(1-$F91)+F18 -> 68870.285 | G9: =F9*(1-$F91)+G18 -> 70590.947 | H9: =G9*(1-$F91)+H18 -> 72173.956 | I9: =H9*(1-$F91)+I18 -> 74353.353 | J9: =I9*(1-$F91)+J18 -> 76358.398 | K9: =J9*(1-$F91)+K18 -> 78203.04 | L9: =K9*(1-$F91)+L18 -> 80623.139 | M9: =L9*(1-$F91)+M18 -> 82849.63 | ... Q9: =P9*(1-$F91)+Q18 -> 92111.473
B10: Churn | F10: =-E3*$C$83 -> -82800 | G10: =-F3*$C$83 -> -92176 | H10: =-G3*$C$83 -> -100801.92 | I10: =-H3*$C$83 -> -108737.77 | J10: =-I3*$C$83 -> -117638.75 | K10: =-J3*$C$83 -> -125827.65 | L10: =-K3*$C$83 -> -133361.43 | M10: =-L3*$C$83 -> -141892.52 | ... Q10: =-P3*$C$83 -> -172788.49
B12: Meta de Vendas MRR | F12: 200000 | G12: 200000 | H12: 200000 | I12: 220000 | J12: 220000 | K12: 220000 | L12: 240000 | M12: 240000 | N12: 240000 | O12: 260000 | P12: 260000 | Q12: 260000
B13: Performance | E13: =F13/C86 -> 24.666667 | F13: =F$12*$D$86 -> 74000 | G13: =G$12*$D$86 -> 74000 | H13: =H$12*$D$86 -> 74000 | I13: =I$12*$D$86 -> 81400 | J13: =J$12*$D$86 -> 81400 | K13: =K$12*$D$86 -> 81400 | L13: =L$12*$D$86 -> 88800 | M13: =M$12*$D$86 -> 88800 | ... Q13: =Q$12*$D$86 -> 96200
B14: Creators | E14: =F14/C87 -> 20.911421 | F14: =F$12*$D$87 -> 62734.262 | G14: =G$12*$D$87 -> 62734.262 | H14: =H$12*$D$87 -> 62734.262 | I14: =I$12*$D$87 -> 69007.689 | J14: =J$12*$D$87 -> 69007.689 | K14: =K$12*$D$87 -> 69007.689 | L14: =L$12*$D$87 -> 75281.115 | M14: =M$12*$D$87 -> 75281.115 | ... Q14: =Q$12*$D$87 -> 81554.541
B15: Social Media | E15: =F15/C88 -> 15.623735 | F15: =F$12*$D$88 -> 39059.337 | G15: =G$12*$D$88 -> 39059.337 | H15: =H$12*$D$88 -> 39059.337 | I15: =I$12*$D$88 -> 42965.271 | J15: =J$12*$D$88 -> 42965.271 | K15: =K$12*$D$88 -> 42965.271 | L15: =L$12*$D$88 -> 46871.204 | M15: =M$12*$D$88 -> 46871.204 | ... Q15: =Q$12*$D$88 -> 50777.138
B16: Gestão de Comunidade | E16: =F16/C89 -> 1.8062121 | F16: =F$12*$D$89 -> 9031.0606 | G16: =G$12*$D$89 -> 9031.0606 | H16: =H$12*$D$89 -> 9031.0606 | I16: =I$12*$D$89 -> 9934.1666 | J16: =J$12*$D$89 -> 9934.1666 | K16: =K$12*$D$89 -> 9934.1666 | L16: =L$12*$D$89 -> 10837.273 | M16: =M$12*$D$89 -> 10837.273 | ... Q16: =Q$12*$D$89 -> 11740.379
B17: E-mail Marketing | E17: =F17/C90 -> 5.2967034 | F17: =F$12*$D$90 -> 7945.055 | G17: =G$12*$D$90 -> 7945.055 | H17: =H$12*$D$90 -> 7945.055 | I17: =I$12*$D$90 -> 8739.5605 | J17: =J$12*$D$90 -> 8739.5605 | K17: =K$12*$D$90 -> 8739.5605 | L17: =L$12*$D$90 -> 9534.066 | M17: =M$12*$D$90 -> 9534.066 | ... Q17: =Q$12*$D$90 -> 10328.572
B18: Tech/CRM | E18: =F18/C91 -> 4.82019 | F18: =F12-SUM(F13:F17) -> 7230.285 | G18: =G12-SUM(G13:G17) -> 7230.285 | H18: =H12-SUM(H13:H17) -> 7230.285 | I18: =I12-SUM(I13:I17) -> 7953.3135 | J18: =J12-SUM(J13:J17) -> 7953.3135 | K18: =K12-SUM(K13:K17) -> 7953.3135 | L18: =L12-SUM(L13:L17) -> 8676.342 | M18: =M12-SUM(M13:M17) -> 8676.342 | ... Q18: =Q12-SUM(Q13:Q17) -> 9399.3705
G19: =G20-F20 -> 39.895733 | H19: =H20-G20 -> 36.704075 | I19: =I20-H20 -> 41.080242 | J19: =J20-I20 -> 37.793822 | K19: =K20-J20 -> 34.770316 | L19: =L20-K20 -> 39.301184 | M19: =M20-L20 -> 36.157089 | N19: =N20-M20 -> 33.264522 | ... Q19: =Q20-P20 -> 32.091978
B20: Contratos | F20: =SUM(F21:F26) -> 415.36493 | G20: =SUM(G21:G26) -> 455.26066 | H20: =SUM(H21:H26) -> 491.96474 | I20: =SUM(I21:I26) -> 533.04498 | J20: =SUM(J21:J26) -> 570.8388 | K20: =SUM(K21:K26) -> 605.60912 | L20: =SUM(L21:L26) -> 644.9103 | M20: =SUM(M21:M26) -> 681.06739 | ... Q20: =SUM(Q21:Q26) -> 819.22233
B21: Performance | F21: =$F4/$C86 -> 170.33333 | G21: =G$4/$C$86 -> 181.37333 | H21: =H$4/$C$86 -> 191.53013 | I21: =I$4/$C$86 -> 203.34106 | J21: =J$4/$C$86 -> 214.2071 | K21: =K$4/$C$86 -> 224.20387 | L21: =L$4/$C$86 -> 235.86756 | M21: =M$4/$C$86 -> 246.59816 | N21: =N$4/$C$86 -> 256.4703 | ... Q21: =Q$4/$C$86 -> 288.41957
B22: Creators | F22: =F5/$C87 -> 89.298087 | G22: =G5/$C87 -> 103.06566 | H22: =H5/$C87 -> 115.73183 | I22: =I5/$C87 -> 129.47585 | J22: =J5/$C87 -> 142.12034 | K22: =K5/$C87 -> 153.75328 | L22: =L5/$C87 -> 166.54672 | M22: =M5/$C87 -> 178.31669 | ... Q22: =Q5/$C87 -> 222.48915
B23: Social Media | F23: =F6/$C88 -> 81.863735 | G23: =G6/$C88 -> 90.938371 | H23: =H6/$C88 -> 99.287036 | I23: =I6/$C88 -> 108.53018 | J23: =J6/$C88 -> 117.03388 | K23: =K6/$C88 -> 124.85727 | L23: =L6/$C88 -> 133.61717 | M23: =M6/$C88 -> 141.67628 | ... Q23: =Q6/$C88 -> 172.28306
B24: Gestão de Comunidade | F24: =F7/$C89 -> 16.526212 | G24: =G7/$C89 -> 17.010327 | H24: =H7/$C89 -> 17.455713 | I24: =I7/$C89 -> 18.046089 | J24: =J7/$C89 -> 18.589236 | K24: =K7/$C89 -> 19.08893 | L24: =L7/$C89 -> 19.72927 | M24: =M7/$C89 -> 20.318383 | ... Q24: =Q7/$C89 -> 22.739434
B25: E-mail Marketing | F25: =F8/$C90 -> 11.430037 | G25: =G8/$C90 -> 15.812337 | H25: =H8/$C90 -> 19.844053 | I25: =I8/$C90 -> 24.082903 | J25: =J8/$C90 -> 27.982644 | K25: =K8/$C90 -> 31.570406 | L25: =L8/$C90 -> 35.400818 | M25: =M8/$C90 -> 38.924797 | ... Q25: =Q8/$C90 -> 51.883466
B26: Tech/CRM | F26: =F9/$C91 -> 45.913523 | G26: =G9/$C91 -> 47.060631 | H26: =H9/$C91 -> 48.115971 | I26: =I9/$C91 -> 49.568902 | J26: =J9/$C91 -> 50.905599 | K26: =K9/$C91 -> 52.13536 | L26: =L9/$C91 -> 53.748759 | M26: =M9/$C91 -> 55.233086 | ... Q26: =Q9/$C91 -> 61.407649
B28: Operadores | F28: =SUM(F29:F40) -> 64.64824 | G28: =SUM(G29:G40) -> 70.595507 | H28: =SUM(H29:H40) -> 75.243658 | I28: =SUM(I29:I40) -> 81.251537 | J28: =SUM(J29:J40) -> 85.955452 | K28: =SUM(K29:K40) -> 92.623053 | L28: =SUM(L29:L40) -> 97.412159 | M28: =SUM(M29:M40) -> 103.0748 | ... Q28: =SUM(Q29:Q40) -> 123.09073
B29: Performance | F29: =ROUNDUP(F21/$E$86,0) -> 18 | G29: =ROUNDUP(G21/$E$86,0) -> 19 | H29: =ROUNDUP(H21/$E$86,0) -> 20 | I29: =ROUNDUP(I21/$E$86,0) -> 21 | J29: =ROUNDUP(J21/$E$86,0) -> 22 | K29: =ROUNDUP(K21/$E$86,0) -> 23 | L29: =ROUNDUP(L21/$E$86,0) -> 24 | M29: =ROUNDUP(M21/$E$86,0) -> 25 | ... Q29: =ROUNDUP(Q21/$E$86,0) -> 29
B30: Designer Performance | F30: =F21/$E$97 -> 6.5512821 | G30: =G21/$E$97 -> 6.9758974 | H30: =H21/$E$97 -> 7.3665436 | I30: =I21/$E$97 -> 7.8208098 | J30: =J21/$E$97 -> 8.2387348 | K30: =K21/$E$97 -> 8.6232258 | L30: =L21/$E$97 -> 9.0718292 | M30: =M21/$E$97 -> 9.4845444 | ... Q30: =Q21/$E$97 -> 11.093061
B31: Creators | F31: =ROUNDUP(F22/$E$87,0) -> 6 | G31: =ROUNDUP(G22/$E$87,0) -> 7 | H31: =ROUNDUP(H22/$E$87,0) -> 8 | I31: =ROUNDUP(I22/$E$87,0) -> 9 | J31: =ROUNDUP(J22/$E$87,0) -> 10 | K31: =ROUNDUP(K22/$E$87,0) -> 11 | L31: =ROUNDUP(L22/$E$87,0) -> 12 | M31: =ROUNDUP(M22/$E$87,0) -> 12 | ... Q31: =ROUNDUP(Q22/$E$87,0) -> 15
B32: Designer Creator | F32: =F22/$E$96 -> 4.4649044 | G32: =G22/$E$96 -> 5.1532831 | H32: =H22/$E$96 -> 5.7865915 | I32: =I22/$E$96 -> 6.4737923 | J32: =J22/$E$96 -> 7.106017 | K32: =K22/$E$96 -> 7.6876638 | L32: =L22/$E$96 -> 8.327336 | M32: =M22/$E$96 -> 8.9158343 | ... Q32: =Q22/$E$96 -> 11.124457
B33: Social Media | F33: =ROUNDUP(F23/$E$88,0) -> 5 | G33: =ROUNDUP(G23/$E$88,0) -> 5 | H33: =ROUNDUP(H23/$E$88,0) -> 5 | I33: =ROUNDUP(I23/$E$88,0) -> 6 | J33: =ROUNDUP(J23/$E$88,0) -> 6 | K33: =ROUNDUP(K23/$E$88,0) -> 7 | L33: =ROUNDUP(L23/$E$88,0) -> 7 | M33: =ROUNDUP(M23/$E$88,0) -> 8 | ... Q33: =ROUNDUP(Q23/$E$88,0) -> 9
B34: Designer SM | F34: =F23/$E$95 -> 5.4575823 | G34: =G23/$E$95 -> 6.0625581 | H34: =H23/$E$95 -> 6.6191357 | I34: =I23/$E$95 -> 7.2353454 | J34: =J23/$E$95 -> 7.8022583 | K34: =K23/$E$95 -> 8.3238182 | L34: =L23/$E$95 -> 8.9078116 | M34: =M23/$E$95 -> 9.4450854 | ... Q34: =Q23/$E$95 -> 11.485537
B35: Gestão de Comunidade | F35: =ROUNDUP(F24/$E$89,0) -> 2 | G35: =ROUNDUP(G24/$E$89,0) -> 2 | H35: =ROUNDUP(H24/$E$89,0) -> 2 | I35: =ROUNDUP(I24/$E$89,0) -> 2 | J35: =ROUNDUP(J24/$E$89,0) -> 2 | K35: =ROUNDUP(K24/$E$89,0) -> 2 | L35: =ROUNDUP(L24/$E$89,0) -> 2 | M35: =ROUNDUP(M24/$E$89,0) -> 3 | ... Q35: =ROUNDUP(Q24/$E$89,0) -> 3
B36: E-mail Marketing | F36: =ROUNDUP(F25/$E$90,0) -> 1 | G36: =ROUNDUP(G25/$E$90,0) -> 2 | H36: =ROUNDUP(H25/$E$90,0) -> 2 | I36: =ROUNDUP(I25/$E$90,0) -> 2 | J36: =ROUNDUP(J25/$E$90,0) -> 2 | K36: =ROUNDUP(K25/$E$90,0) -> 3 | L36: =ROUNDUP(L25/$E$90,0) -> 3 | M36: =ROUNDUP(M25/$E$90,0) -> 3 | ... Q36: =ROUNDUP(Q25/$E$90,0) -> 4
B37: Designer E-mail Marketing | F37: =F25/$E$98 -> 0.27878138 | G37: =G25/$E$98 -> 0.38566676 | H37: =H25/$E$98 -> 0.4840013 | I37: =I25/$E$98 -> 0.58738788 | J37: =J25/$E$98 -> 0.68250352 | K37: =K25/$E$98 -> 0.77000991 | L37: =L25/$E$98 -> 0.86343459 | M37: =M25/$E$98 -> 0.94938528 | ... Q37: =Q25/$E$98 -> 1.2654504
B38: Tech/CRM | F38: =ROUNDUP(F26/$E$91,0) -> 4 | G38: =ROUNDUP(G26/$E$91,0) -> 4 | H38: =ROUNDUP(H26/$E$91,0) -> 4 | I38: =ROUNDUP(I26/$E$91,0) -> 4 | J38: =ROUNDUP(J26/$E$91,0) -> 4 | K38: =ROUNDUP(K26/$E$91,0) -> 4 | L38: =ROUNDUP(L26/$E$91,0) -> 4 | M38: =ROUNDUP(M26/$E$91,0) -> 4 | ... Q38: =ROUNDUP(Q26/$E$91,0) -> 5
B39: CX | F39: =F20/60 -> 6.9227488 | G39: =G20/60 -> 7.5876777 | H39: =H20/60 -> 8.1994123 | I39: =I20/60 -> 8.884083 | J39: =J20/60 -> 9.51398 | K39: =K20/60 -> 10.093485 | L39: =L20/60 -> 10.748505 | M39: =M20/60 -> 11.351123 | ... Q39: =Q20/60 -> 13.653705
B40: Líder | F40: =SUM(F29:F39)/12 -> 4.9729416 | G40: =SUM(G29:G39)/12 -> 5.4304236 | H40: =SUM(H29:H39)/12 -> 5.7879737 | I40: =SUM(I29:I39)/12 -> 6.2501182 | J40: =SUM(J29:J39)/12 -> 6.6119578 | K40: =SUM(K29:K39)/12 -> 7.1248503 | L40: =SUM(L29:L39)/12 -> 7.493243 | M40: =SUM(M29:M39)/12 -> 7.9288311 | ... Q40: =SUM(Q29:Q39)/12 -> 9.4685176
B42: Salário | F42: =SUM(F43:F54) -> 275337.47 | G42: =SUM(G43:G54) -> 297566.47 | H42: =SUM(H43:H54) -> 316510.48 | I42: =SUM(I43:I54) -> 339967.91 | J42: =SUM(J43:J54) -> 359122.07 | K42: =SUM(K43:K54) -> 384023.9 | L42: =SUM(L43:L54) -> 403469.19 | M42: =SUM(M43:M54) -> 424472.19 | ... Q42: =SUM(Q43:Q54) -> 505895.11
B43: Performance | F43: =F29*$G86 -> 81000 | G43: =G29*$G86 -> 85500 | H43: =H29*$G86 -> 90000 | I43: =I29*$G86 -> 94500 | J43: =J29*$G86 -> 99000 | K43: =K29*$G86 -> 103500 | L43: =L29*$G86 -> 108000 | M43: =M29*$G86 -> 112500 | ... Q43: =Q29*$G86 -> 130500
B44: Designer Performance | F44: =F30*$G$97 -> 19653.846 | G44: =G30*$G$97 -> 20927.692 | H44: =H30*$G$97 -> 22099.631 | I44: =I30*$G$97 -> 23462.43 | J44: =J30*$G$97 -> 24716.204 | K44: =K30*$G$97 -> 25869.677 | L44: =L30*$G$97 -> 27215.488 | M44: =M30*$G$97 -> 28453.633 | ... Q44: =Q30*$G$97 -> 33279.182
B45: Creators | F45: =F31*$G87 -> 18000 | G45: =G31*$G87 -> 21000 | H45: =H31*$G87 -> 24000 | I45: =I31*$G87 -> 27000 | J45: =J31*$G87 -> 30000 | K45: =K31*$G87 -> 33000 | L45: =L31*$G87 -> 36000 | M45: =M31*$G87 -> 36000 | ... Q45: =Q31*$G87 -> 45000
B46: Designer Creator | F46: =F31*$G$96 -> 18000 | G46: =G31*$G$96 -> 21000 | H46: =H31*$G$96 -> 24000 | I46: =I31*$G$96 -> 27000 | J46: =J31*$G$96 -> 30000 | K46: =K31*$G$96 -> 33000 | L46: =L31*$G$96 -> 36000 | M46: =M31*$G$96 -> 36000 | ... Q46: =Q31*$G$96 -> 45000
B47: Social Media | F47: =F33*$G88 -> 15000 | G47: =G33*$G88 -> 15000 | H47: =H33*$G88 -> 15000 | I47: =I33*$G88 -> 18000 | J47: =J33*$G88 -> 18000 | K47: =K33*$G88 -> 21000 | L47: =L33*$G88 -> 21000 | M47: =M33*$G88 -> 24000 | ... Q47: =Q33*$G88 -> 27000
B48: Designer SM | F48: =F34*$G$95 -> 16372.747 | G48: =G34*$G$95 -> 18187.674 | H48: =H34*$G$95 -> 19857.407 | I48: =I34*$G$95 -> 21706.036 | J48: =J34*$G$95 -> 23406.775 | K48: =K34*$G$95 -> 24971.455 | L48: =L34*$G$95 -> 26723.435 | M48: =M34*$G$95 -> 28335.256 | ... Q48: =Q34*$G$95 -> 34456.612
B49: Gestão de Comunidade | F49: =F35*$G89 -> 9000 | G49: =G35*$G89 -> 9000 | H49: =H35*$G89 -> 9000 | I49: =I35*$G89 -> 9000 | J49: =J35*$G89 -> 9000 | K49: =K35*$G89 -> 9000 | L49: =L35*$G89 -> 9000 | M49: =M35*$G89 -> 13500 | ... Q49: =Q35*$G89 -> 13500
B50: E-mail Marketing | F50: =F36*$G90 -> 2000 | G50: =G36*$G90 -> 4000 | H50: =H36*$G90 -> 4000 | I50: =I36*$G90 -> 4000 | J50: =J36*$G90 -> 4000 | K50: =K36*$G90 -> 6000 | L50: =L36*$G90 -> 6000 | M50: =M36*$G90 -> 6000 | ... Q50: =Q36*$G90 -> 8000
B51: Designer E-mail Marketing | F51: =F37*$G$98 -> 836.34415 | G51: =G37*$G$98 -> 1157.0003 | H51: =H37*$G$98 -> 1452.0039 | I51: =I37*$G$98 -> 1762.1636 | J51: =J37*$G$98 -> 2047.5106 | K51: =K37*$G$98 -> 2310.0297 | L51: =L37*$G$98 -> 2590.3038 | M51: =M37*$G$98 -> 2848.1558 | ... Q51: =Q37*$G$98 -> 3796.3511
B52: Tech/CRM | F52: =F38*$G91 -> 28000 | G52: =G38*$G91 -> 28000 | H52: =H38*$G91 -> 28000 | I52: =I38*$G91 -> 28000 | J52: =J38*$G91 -> 28000 | K52: =K38*$G91 -> 28000 | L52: =L38*$G91 -> 28000 | M52: =M38*$G91 -> 28000 | ... Q52: =Q38*$G91 -> 35000
B53: CX | F53: =F39*$G$92 -> 27690.995 | G53: =G39*$G$92 -> 30350.711 | H53: =H39*$G$92 -> 32797.649 | I53: =I39*$G$92 -> 35536.332 | J53: =J39*$G$92 -> 38055.92 | K53: =K39*$G$92 -> 40373.941 | L53: =L39*$G$92 -> 42994.02 | M53: =M39*$G$92 -> 45404.493 | ... Q53: =Q39*$G$92 -> 54614.822
B54: Líder | F54: =F40*$G$93 -> 39783.533 | G54: =G40*$G$93 -> 43443.389 | H54: =H40*$G$93 -> 46303.79 | I54: =I40*$G$93 -> 50000.946 | J54: =J40*$G$93 -> 52895.662 | K54: =K40*$G$93 -> 56998.802 | L54: =L40*$G$93 -> 59945.944 | M54: =M40*$G$93 -> 63430.648 | ... Q54: =Q40*$G$93 -> 75748.141
B57: Caju | F57: =F28*600 -> 38788.944 | G57: =G28*600 -> 42357.304 | H57: =H28*600 -> 45146.195 | I57: =I28*600 -> 48750.922 | J57: =J28*600 -> 51573.271 | K57: =K28*600 -> 55573.832 | L57: =L28*600 -> 58447.296 | M57: =M28*600 -> 61844.882 | ... Q57: =Q28*600 -> 73854.437
F58: =(F42+F57)/F3 -> 0.27263184 | G58: =(G42+G57)/G3 -> 0.26977563 | H58: =(H42+H57)/H3 -> 0.26607622 | I58: =(I42+I57)/I3 -> 0.26434748 | J58: =(J42+J57)/J3 -> 0.26111613 | K58: =(K42+K57)/K3 -> 0.26370307 | L58: =(L42+L57)/L3 -> 0.26043176 | M58: =(M42+M57)/M3 -> 0.25981752 | ... Q58: =(Q42+Q57)/Q3 -> 0.25800271
C61: Recorrente
C62: Task Name | D62: Recorrente | E62: Qtd Recorrente | F62: AOV Recorrente
C63: Performance | D63: 179880 | E63: 72 | F63: 2498.3333 | G63: =D63/$D$74 -> 0.36920618
C64: Creators | D64: 152823 | E64: 48 | F64: 3183.8125 | G64: =D64/$D$74 -> 0.31367131
C65: Social Media | D65: 95150 | E65: 48 | F65: 1982.2917 | G65: =D65/$D$74 -> 0.19529669
C66: Gestão de Comunidade | D66: 22000 | E66: 5 | F66: 4400 | G66: =D66/$D$74 -> 0.045155303
C67: E-mail Marketing | D67: 19354.45 | E67: 11 | F67: 1759.4955 | G67: =D67/$D$74 -> 0.039725275
C68: Sustentação | D68: 5091 | E68: 5 | F68: 1018.2 | G68: =D68/$D$74 -> 0.010449348
C69: Account Manager | D69: 3772 | E69: 4 | F69: 943 | G69: =D69/$D$74 -> 0.0077420819
C70: Blog Post | D70: 2555 | E70: 3 | F70: 851.66667 | G70: =D70/$D$74 -> 0.0052441727
C71: Agente AI | D71: 2399 | E71: 2 | F71: 1199.5 | G71: =D71/$D$74 -> 0.0049239805
C72: CRM | D72: 2183 | E72: 4 | F72: 545.75 | G72: =D72/$D$74 -> 0.0044806376
C73: Automação | D73: 2000 | E73: 1 | F73: 2000 | G73: =D73/$D$74 -> 0.0041050275
C74: Total geral | D74: 487207.45 | E74: 203 | F74: 2400.0367
F76: 300000
F77: =D74/F76 -> 1.6240248
B81: Crescimento | C81: 0.05
B82: Bookado | C82: 1000000
B83: Churn | C83: 0.08
C85: TM | D85: % Aquisição | E85: CPO | F85: Churn | G85: Salário | H85: Faturamento Esperado
B86: =C63 -> Performance | C86: 3000 | D86: 0.37 | E86: 10 | F86: 0.08 | G86: 4500 | H86: =C86*E86 -> 30000
B87: =C64 -> Creators | C87: 3000 | D87: 0.31367131 | E87: 15 | F87: 0.08 | G87: 3000 | H87: =C87*E87 -> 45000
B88: =C65 -> Social Media | C88: 2500 | D88: 0.19529669 | E88: 20 | F88: 0.08 | G88: 3000 | H88: =C88*E88 -> 50000
B89: =C66 -> Gestão de Comunidade | C89: 5000 | D89: 0.045155303 | E89: 10 | F89: 0.08 | G89: 4500 | H89: =C89*E89 -> 50000
B90: =C67 -> E-mail Marketing | C90: 1500 | D90: =G67 -> 0.039725275 | E90: 15 | F90: 0.08 | G90: 2000 | H90: =C90*E90 -> 22500
B91: =C68 -> Sustentação | C91: 1500 | D91: =G68 -> 0.010449348 | E91: 15 | F91: 0.08 | G91: 7000 | H91: =C91*E91 -> 22500
B92: CX | G92: 4000
B93: Líder | G93: 8000
E94: Conta
B95: Designer SM | E95: 15 | G95: 3000
B96: Designer Creator | E96: 20 | G96: 3000
B97: Designer Performance | E97: 26 | G97: 3000
B98: Designer E-mail | E98: 41 | G98: 3000
B100: COP | C100: 0.25
B101: CAC | C101: 0.25
B102: Imposto | C102: 0.16
B103: Inadimplencia | C103: 0.08
B104: SG&A | C104: 0.07

Sheet Gazeta
B1: Clientes Gazeta -> Turbo
B2: Clientes | C2: Faturamento Turbo | D2: Rebate Tools
B3: 20 | C3: =20*15000 -> 300000 | D3: =C3*20% -> 60000
B5: Receita Rebate Anuncio TV outras redes
B6: Investimento em outras emissoras | C6: Rebate Turbo | D6: Rebate Tools
B7: =100000*B3 -> 2000000 | C7: =B7*20% -> 400000 | D7: =C7*10% -> 40000
B9: Clientes Turbo -> Gazeta
B10: Clientes
B13: Novos Produtos - JV
B16: Pensar como geramos o valor para Gazeta | D16: Fechar o meio de pagamento do Fonte
D17: aporte
B18: Influencers
B19: Lancamento 30 SaaS
B20: Desenhar o quanto a Turbo consegue trazer de receita
B21: Como a Gazeta vender Turbo
B22: Ganhar rebate Google e Meta

Sheet Hugz
A1: Hi

Sheet Next Years
G2: 2026
C3: 2026 | D3: 2027 | E3: 2028 | G3: Margem / Saldo | H3: 1 | I3: 1.25 | J3: 1.5 | K3: 1.75 | L3: 2
B4: Receita | C4: ='Overview Old'!O7 -> 26083189 | D4: 50000000 | E4: 100000000 | G4: 0.15 | H4: =($C$4*$G$4)-(1*$C$5) -> 1793928.3 | I4: =($C$4*$G$4)-(1.25*$C$5) -> 1264290.7 | J4: =($C$4*$G$4)-(1.5*$C$5) -> 734653.19 | K4: =($C$4*$G$4)-(1.75*$C$5) -> 205015.65 | L4: =($C$4*$G$4)-(2*$C$5) -> -324621.89
B5: Depesa Mensal Dez | C5: ='Overview Old'!N23 -> 2118550.2 | D5: =C5*(1+D9) -> 4061140.9 | E5: =D5*(1+E9) -> 8122281.8 | G5: 0.175 | H5: =($C$4*$G$5)-(1*$C$5) -> 2446008 | I5: =($C$4*$G$5)-(1.25*$C$5) -> 1916370.5 | J5: =($C$4*$G$5)-(1.5*$C$5) -> 1386732.9 | K5: =($C$4*$G$5)-(1.75*$C$5) -> 857095.38 | L5: =($C$4*$G$5)-(2*$C$5) -> 327457.85
B6: Geracao de Caixa | C6: ='Overview Old'!O18 -> 4594256.2 | G6: 0.2 | H6: =($C$4*$G$6)-(1*$C$5) -> 3098087.7 | I6: =($C$4*$G$6)-(1.25*$C$5) -> 2568450.2 | J6: =($C$4*$G$6)-(1.5*$C$5) -> 2038812.7 | K6: =($C$4*$G$6)-(1.75*$C$5) -> 1509175.1 | L6: =($C$4*$G$6)-(2*$C$5) -> 979537.58
B7: Margem Caixa (%) | C7: =C6/C4 -> 0.17613859 | G7: 0.225 | H7: =($C$4*$G$7)-(1*$C$5) -> 3750167.5 | I7: =($C$4*$G$7)-(1.25*$C$5) -> 3220529.9 | J7: =($C$4*$G$7)-(1.5*$C$5) -> 2690892.4 | K7: =($C$4*$G$7)-(1.75*$C$5) -> 2161254.9 | L7: =($C$4*$G$7)-(2*$C$5) -> 1631617.3
G8: 0.25 | H8: =($C$4*$G$8)-(1*$C$5) -> 4402247.2 | I8: =($C$4*$G$8)-(1.25*$C$5) -> 3872609.7 | J8: =($C$4*$G$8)-(1.5*$C$5) -> 3342972.1 | K8: =($C$4*$G$8)-(1.75*$C$5) -> 2813334.6 | L8: =($C$4*$G$8)-(2*$C$5) -> 2283697.1
B9: Crescimento Receita | D9: =(D4/C4)-1 -> 0.91694348 | E9: =(E4/D4)-1 -> 1
G10: 2027
G11: Margem / Saldo | H11: 1 | I11: 1.25 | J11: 1.5 | K11: 1.75 | L11: 2
G12: 0.15 | H12: =($D$4*$G$12)-(H11*$D$5) -> 3438859.1 | I12: =($D$4*$G$12)-(I11*$D$5) -> 2423573.9 | J12: =($D$4*$G$12)-(J11*$D$5) -> 1408288.6 | K12: =($D$4*$G$12)-(K11*$D$5) -> 393003.41 | L12: =($D$4*$G$12)-(L11*$D$5) -> -622281.82
B13: Cenário Base | G13: 0.175 | H13: =($D$4*$G$13)-(H11*$D$5) -> 4688859.1 | I13: =($D$4*$G$13)-(I11*$D$5) -> 3673573.9 | J13: =($D$4*$G$13)-(J11*$D$5) -> 2658288.6 | K13: =($D$4*$G$13)-(K11*$D$5) -> 1643003.4 | L13: =($D$4*$G$13)-(L11*$D$5) -> 627718.18
B14: 2026 | C14: 2027 | D14: 2028 | E14: Total | G14: 0.2 | H14: =($D$4*$G$14)-(H11*$D$5) -> 5938859.1 | I14: =($D$4*$G$14)-(I11*$D$5) -> 4923573.9 | J14: =($D$4*$G$14)-(J11*$D$5) -> 3908288.6 | K14: =($D$4*$G$14)-(K11*$D$5) -> 2893003.4 | L14: =($D$4*$G$14)-(L11*$D$5) -> 1877718.2
B15: =J6 -> 2038812.7 | C15: =J14 -> 3908288.6 | D15: =J22 -> 7816577.3 | E15: =SUM(B15:D15) -> 13763679 | G15: 0.225 | H15: =($D$4*$G$15)-(H11*$D$5) -> 7188859.1 | I15: =($D$4*$G$15)-(I11*$D$5) -> 6173573.9 | J15: =($D$4*$G$15)-(J11*$D$5) -> 5158288.6 | K15: =($D$4*$G$15)-(K11*$D$5) -> 4143003.4 | L15: =($D$4*$G$15)-(L11*$D$5) -> 3127718.2
G16: 0.25 | H16: =($D$4*$G$16)-(H11*$D$5) -> 8438859.1 | I16: =($D$4*$G$16)-(I11*$D$5) -> 7423573.9 | J16: =($D$4*$G$16)-(J11*$D$5) -> 6408288.6 | K16: =($D$4*$G$16)-(K11*$D$5) -> 5393003.4 | L16: =($D$4*$G$16)-(L11*$D$5) -> 4377718.2
G18: 2028
G19: Margem / Saldo | H19: 1 | I19: 1.25 | J19: 1.5 | K19: 1.75 | L19: 2
G20: 0.15 | H20: =($E$4*$G$20)-(H19*$E$5) -> 6877718.2 | I20: =($E$4*$G$20)-(I19*$E$5) -> 4847147.7 | J20: =($E$4*$G$20)-(J19*$E$5) -> 2816577.3 | K20: =($E$4*$G$20)-(K19*$E$5) -> 786006.82 | L20: =($E$4*$G$20)-(L19*$E$5) -> -1244563.6
G21: 0.175 | H21: =($E$4*$G$21)-(H19*$E$5) -> 9377718.2 | I21: =($E$4*$G$21)-(I19*$E$5) -> 7347147.7 | J21: =($E$4*$G$21)-(J19*$E$5) -> 5316577.3 | K21: =($E$4*$G$21)-(K19*$E$5) -> 3286006.8 | L21: =($E$4*$G$21)-(L19*$E$5) -> 1255436.4
G22: 0.2 | H22: =($E$4*$G$22)-(H19*$E$5) -> 11877718 | I22: =($E$4*$G$22)-(I19*$E$5) -> 9847147.7 | J22: =($E$4*$G$22)-(J19*$E$5) -> 7816577.3 | K22: =($E$4*$G$22)-(K19*$E$5) -> 5786006.8 | L22: =($E$4*$G$22)-(L19*$E$5) -> 3755436.4
G23: 0.225 | H23: =($E$4*$G$23)-(H19*$E$5) -> 14377718 | I23: =($E$4*$G$23)-(I19*$E$5) -> 12347148 | J23: =($E$4*$G$23)-(J19*$E$5) -> 10316577 | K23: =($E$4*$G$23)-(K19*$E$5) -> 8286006.8 | L23: =($E$4*$G$23)-(L19*$E$5) -> 6255436.4
